Workbook
Name __1: #REF!
Name __1: #REF!
Name __1: #REF!
Name _2: #REF!
Name _2: #REF!
Name _2: #REF!
Name a: #REF!
Name a: #REF!
Name a: #REF!
Name Ahmed: #REF!
Name Ahmed: #REF!
Name Ahmed: #REF!
Name Ali: #REF!
Name Ali: #REF!
Name Ali: #REF!
Name B: #REF!
Name B: #REF!
Name B: #REF!
Name BlockWork: #REF!
Name BlockWork: #REF!
Name BlockWork: #REF!
Name Budget_code_Rev: #REF!
Name Budget_code_Rev: #REF!
Name Budget_code_Rev: #REF!
Name buyout: #REF!
Name buyout: #REF!
Name buyout: #REF!
Name Buyout_items: #REF!
Name Buyout_items: #REF!
Name Buyout_items: #REF!
Name ConcreteWork: #REF!
Name ConcreteWork: #REF!
Name ConcreteWork: #REF!
Name ConveyingSystems: #REF!
Name ConveyingSystems: #REF!
Name ConveyingSystems: #REF!
Name EarthWork: #REF!
Name EarthWork: #REF!
Name EarthWork: #REF!
Name ElectricalWork: #REF!
Name ElectricalWork: #REF!
Name ElectricalWork: #REF!
Name Finishing: #REF!
Name Finishing: #REF!
Name Finishing: #REF!
Name FireFighting: #REF!
Name FireFighting: #REF!
Name FireFighting: #REF!
Name Furniture: #REF!
Name Furniture: #REF!
Name Furniture: #REF!
Name HVACWork: #REF!
Name HVACWork: #REF!
Name HVACWork: #REF!
Name Insulation: #REF!
Name Insulation: #REF!
Name Insulation: #REF!
Name MetalWork: #REF!
Name MetalWork: #REF!
Name MetalWork: #REF!

Sheet Manual Manpower Database
C2: Manual Manpower Cost Database
C3: Non-Manual Staff Details | T3: Yearly Expenses Proportional in Terms of Basic Salary | X3: Monthly Expense in terms of Basic Salary | Z3: Fixed Yearly Payment | AE3: One time Payment in terms of Basic | AG3: Fixed One time Payment | AJ3: Monthly Expense of all Categories
C4: Type | D4: Portfolio | E4: Devision | F4: Sub-Division | G4: Organization Position | H4: No. | I4: Sum of Basic Salary | J4: Average of Basic Salary | K4: Max of Basic Salary | L4: Min of Basic Salary | M4: Max of Transport Allowance | N4: Min of Transport Allowance | O4: Min of Housing Allowance monthes | P4: Max of Housing Allowance monthes | Q4: Max of Food Allowance | R4: Min of Food Allowance | T4: Vacation Pay | U4: Bonus | V4: EOS Benefits | X4: GOSI | Z4: Air tickets | AA4: medical | AB4: Iqama Cost | AC4: Work Permits | AE4: Recruitment expenses | AG4: Relocation allowance | AH4: Visa cost | AJ4: Basic | AK4: Transportation | AL4: Housing | AM4: Food Allowance | AN4: Vacation Pay | AO4: Bonus | AP4: EOS Benefits | AQ4: GOSI | AR4: Air tickets | AS4: medical | AT4: Iqama Cost | AU4: Work Permits | AV4: Recruitment expenses | AW4: Relocation allowance | AX4: Visa cost | AY4: Total
C5: Manual | E5: Miscelainious | F5: Lab | G5: Assistant Lab Technician | H5: 6 | I5: 9540 | J5: 1590 | K5: 2290 | L5: 1000 | M5: 0 | N5: 0 | O5: 0 | P5: 0 | Q5: 150 | R5: 0 | T5: 1 | U5: 0 | V5: 0.5 | X5: 0.02 | Z5: =IF($J5>=5000,6000,3000) -> 3000 | AA5: =IF($J5>=5000,2650,500) -> 500 | AB5: 650 | AC5: 2500 | AE5: 0 | AG5: 300 | AH5: 2000 | AJ5: =J5 -> 1590 | AK5: =M5 -> 0 | AL5: =P5*J5/12 -> 0 | AM5: =Q5 -> 150 | AN5: =T5*J5/24 -> 66.25 | AO5: =U5*J5/12 -> 0 | AP5: =V5*J5/24 -> 33.125 | AQ5: =X5*(AJ5+AL5) -> 31.8 | AR5: =Z5/24 -> 125 | AS5: =AA5/12 -> 41.666667 | AT5: =AB5/12 -> 54.166667 | AU5: =AC5/12 -> 208.33333 | AV5: =AE5*AJ5/36 -> 0 | AW5: =AG5/36 -> 8.3333333 | AX5: =AH5/36 -> 55.555556 | AY5: =SUM(AJ5:AX5) -> 2364.2306
C6: Manual | E6: Miscelainious | F6: Store | G6: Assistant Store Keeper | H6: 10 | I6: 10837 | J6: 1083.7 | K6: 1365 | L6: 645 | M6: 0 | N6: 0 | O6: 0 | P6: 0 | Q6: 200 | R6: 150 | T6: 1 | U6: 0 | V6: 0.5 | X6: 0.02 | Z6: =IF($J6>=5000,6000,3000) -> 3000 | AA6: =IF($J6>=5000,2650,500) -> 500 | AB6: 650 | AC6: 2500 | AE6: 0 | AG6: 300 | AH6: 2000 | AJ6: =J6 -> 1083.7 | AK6: =M6 -> 0 | AL6: =P6*J6/12 -> 0 | AM6: =Q6 -> 200 | AN6: =T6*J6/24 -> 45.154167 | AO6: =U6*J6/12 -> 0 | AP6: =V6*J6/24 -> 22.577083 | AQ6: =X6*(AJ6+AL6) -> 21.674 | AR6: =Z6/24 -> 125 | AS6: =AA6/12 -> 41.666667 | AT6: =AB6/12 -> 54.166667 | AU6: =AC6/12 -> 208.33333 | AV6: =AE6*AJ6/36 -> 0 | AW6: =AG6/36 -> 8.3333333 | AX6: =AH6/36 -> 55.555556 | AY6: =SUM(AJ6:AX6) -> 1866.1608
C7: Manual | E7: Miscelainious | F7: Surveying | G7: Assistant Surveyor | H7: 18 | I7: 39070 | J7: 2170.5556 | K7: 3675 | L7: 900 | M7: 300 | N7: 0 | O7: 0 | P7: 0 | Q7: 150 | R7: 0 | T7: 1 | U7: 0 | V7: 0.5 | X7: 0.02 | Z7: =IF($J7>=5000,6000,3000) -> 3000 | AA7: =IF($J7>=5000,2650,500) -> 500 | AB7: 650 | AC7: 2500 | AE7: 0 | AG7: 300 | AH7: 2000 | AJ7: =J7 -> 2170.5556 | AK7: =M7 -> 300 | AL7: =P7*J7/12 -> 0 | AM7: =Q7 -> 150 | AN7: =T7*J7/24 -> 90.439815 | AO7: =U7*J7/12 -> 0 | AP7: =V7*J7/24 -> 45.219907 | AQ7: =X7*(AJ7+AL7) -> 43.411111 | AR7: =Z7/24 -> 125 | AS7: =AA7/12 -> 41.666667 | AT7: =AB7/12 -> 54.166667 | AU7: =AC7/12 -> 208.33333 | AV7: =AE7*AJ7/36 -> 0 | AW7: =AG7/36 -> 8.3333333 | AX7: =AH7/36 -> 55.555556 | AY7: =SUM(AJ7:AX7) -> 3292.6819
C8: Manual | D8: Batch pmalnts | E8: Equipment | F8: Equipment | G8: Batching Plant Maintenance Supervisor | H8: 5 | I8: 20000 | J8: 4000 | K8: 5000 | L8: 3000 | M8: 400 | N8: 0 | O8: 2 | P8: 2 | Q8: 0 | R8: 0 | T8: 1 | U8: 0 | V8: 0.5 | X8: 0.02 | Z8: =IF($J8>=5000,6000,3000) -> 3000 | AA8: =IF($J8>=5000,2650,500) -> 500 | AB8: 650 | AC8: 2500 | AE8: 0 | AG8: 300 | AH8: 2000 | AJ8: =J8 -> 4000 | AK8: =M8 -> 400 | AL8: =P8*J8/12 -> 666.66667 | AM8: =Q8 -> 0 | AN8: =T8*J8/24 -> 166.66667 | AO8: =U8*J8/12 -> 0 | AP8: =V8*J8/24 -> 83.333333 | AQ8: =X8*(AJ8+AL8) -> 93.333333 | AR8: =Z8/24 -> 125 | AS8: =AA8/12 -> 41.666667 | AT8: =AB8/12 -> 54.166667 | AU8: =AC8/12 -> 208.33333 | AV8: =AE8*AJ8/36 -> 0 | AW8: =AG8/36 -> 8.3333333 | AX8: =AH8/36 -> 55.555556 | AY8: =SUM(AJ8:AX8) -> 5903.0556
C9: Manual | D9: Cleaning Projects | E9: Work Shop | F9: Equipment | G9: Body Repairman | H9: 3 | I9: 3285 | J9: 1095 | K9: 1200 | L9: 1000 | M9: 0 | N9: 0 | O9: 0 | P9: 0 | Q9: 150 | R9: 0 | T9: 1 | U9: 0 | V9: 0.5 | X9: 0.02 | Z9: =IF($J9>=5000,6000,3000) -> 3000 | AA9: =IF($J9>=5000,2650,500) -> 500 | AB9: 650 | AC9: 2500 | AE9: 0 | AG9: 300 | AH9: 2000 | AJ9: =J9 -> 1095 | AK9: =M9 -> 0 | AL9: =P9*J9/12 -> 0 | AM9: =Q9 -> 150 | AN9: =T9*J9/24 -> 45.625 | AO9: =U9*J9/12 -> 0 | AP9: =V9*J9/24 -> 22.8125 | AQ9: =X9*(AJ9+AL9) -> 21.9 | AR9: =Z9/24 -> 125 | AS9: =AA9/12 -> 41.666667 | AT9: =AB9/12 -> 54.166667 | AU9: =AC9/12 -> 208.33333 | AV9: =AE9*AJ9/36 -> 0 | AW9: =AG9/36 -> 8.3333333 | AX9: =AH9/36 -> 55.555556 | AY9: =SUM(AJ9:AX9) -> 1828.3931
C10: Manual | D10: O&m | E10: Miscelainious | F10: Car Parking | G10: Car Parking Attendant | H10: 7 | I10: 4747 | J10: 678.14286 | K10: 847 | L10: 650 | M10: 0 | N10: 0 | O10: 0 | P10: 0 | Q10: 150 | R10: 150 | T10: 1 | U10: 0 | V10: 0.5 | X10: 0.02 | Z10: =IF($J10>=5000,6000,3000) -> 3000 | AA10: =IF($J10>=5000,2650,500) -> 500 | AB10: 650 | AC10: 2500 | AE10: 0 | AG10: 300 | AH10: 2000 | AJ10: =J10 -> 678.14286 | AK10: =M10 -> 0 | AL10: =P10*J10/12 -> 0 | AM10: =Q10 -> 150 | AN10: =T10*J10/24 -> 28.255952 | AO10: =U10*J10/12 -> 0 | AP10: =V10*J10/24 -> 14.127976 | AQ10: =X10*(AJ10+AL10) -> 13.562857 | AR10: =Z10/24 -> 125 | AS10: =AA10/12 -> 41.666667 | AT10: =AB10/12 -> 54.166667 | AU10: =AC10/12 -> 208.33333 | AV10: =AE10*AJ10/36 -> 0 | AW10: =AG10/36 -> 8.3333333 | AX10: =AH10/36 -> 55.555556 | AY10: =SUM(AJ10:AX10) -> 1377.1452
C11: Manual | E11: Finishing | F11: Concrete Form | G11: Carpenter Finishing | H11: 74 | I11: 72750 | J11: 983.10811 | K11: 1200 | L11: 850 | M11: 0 | N11: 0 | O11: 0 | P11: 0 | Q11: 150 | R11: 150 | T11: 1 | U11: 0 | V11: 0.5 | X11: 0.02 | Z11: =IF($J11>=5000,6000,3000) -> 3000 | AA11: =IF($J11>=5000,2650,500) -> 500 | AB11: 650 | AC11: 2500 | AE11: 0 | AG11: 300 | AH11: 2000 | AJ11: =J11 -> 983.10811 | AK11: =M11 -> 0 | AL11: =P11*J11/12 -> 0 | AM11: =Q11 -> 150 | AN11: =T11*J11/24 -> 40.962838 | AO11: =U11*J11/12 -> 0 | AP11: =V11*J11/24 -> 20.481419 | AQ11: =X11*(AJ11+AL11) -> 19.662162 | AR11: =Z11/24 -> 125 | AS11: =AA11/12 -> 41.666667 | AT11: =AB11/12 -> 54.166667 | AU11: =AC11/12 -> 208.33333 | AV11: =AE11*AJ11/36 -> 0 | AW11: =AG11/36 -> 8.3333333 | AX11: =AH11/36 -> 55.555556 | AY11: =SUM(AJ11:AX11) -> 1707.2701
C12: Manual | E12: Concrete | F12: Concrete Form | G12: Carpenter Shuttering | H12: 1181 | I12: 1055898 | J12: 894.07113 | K12: 1800 | L12: 200 | M12: 0 | N12: 0 | O12: 0 | P12: 0 | Q12: 250 | R12: 0 | T12: 1 | U12: 0 | V12: 0.5 | X12: 0.02 | Z12: =IF($J12>=5000,6000,3000) -> 3000 | AA12: =IF($J12>=5000,2650,500) -> 500 | AB12: 650 | AC12: 2500 | AE12: 0 | AG12: 300 | AH12: 2000 | AJ12: =J12 -> 894.07113 | AK12: =M12 -> 0 | AL12: =P12*J12/12 -> 0 | AM12: =Q12 -> 250 | AN12: =T12*J12/24 -> 37.252964 | AO12: =U12*J12/12 -> 0 | AP12: =V12*J12/24 -> 18.626482 | AQ12: =X12*(AJ12+AL12) -> 17.881423 | AR12: =Z12/24 -> 125 | AS12: =AA12/12 -> 41.666667 | AT12: =AB12/12 -> 54.166667 | AU12: =AC12/12 -> 208.33333 | AV12: =AE12*AJ12/36 -> 0 | AW12: =AG12/36 -> 8.3333333 | AX12: =AH12/36 -> 55.555556 | AY12: =SUM(AJ12:AX12) -> 1710.8875
C13: Manual | E13: IT | F13: Computers | G13: Computer Technician | H13: 7 | I13: 28850 | J13: 4121.4286 | K13: 5500 | L13: 2750 | M13: 400 | N13: 0 | O13: 0 | P13: 0 | Q13: 0 | R13: 0 | T13: 1 | U13: 0 | V13: 0.5 | X13: 0.02 | Z13: =IF($J13>=5000,6000,3000) -> 3000 | AA13: =IF($J13>=5000,2650,500) -> 500 | AB13: 650 | AC13: 2500 | AE13: 0 | AG13: 300 | AH13: 2000 | AJ13: =J13 -> 4121.4286 | AK13: =M13 -> 400 | AL13: =P13*J13/12 -> 0 | AM13: =Q13 -> 0 | AN13: =T13*J13/24 -> 171.72619 | AO13: =U13*J13/12 -> 0 | AP13: =V13*J13/24 -> 85.863095 | AQ13: =X13*(AJ13+AL13) -> 82.428571 | AR13: =Z13/24 -> 125 | AS13: =AA13/12 -> 41.666667 | AT13: =AB13/12 -> 54.166667 | AU13: =AC13/12 -> 208.33333 | AV13: =AE13*AJ13/36 -> 0 | AW13: =AG13/36 -> 8.3333333 | AX13: =AH13/36 -> 55.555556 | AY13: =SUM(AJ13:AX13) -> 5354.502
C14: Manual | E14: Miscelainious | F14: Kitchen | G14: Cook | H14: 28 | I14: 30540 | J14: 1090.7143 | K14: 2000 | L14: 400 | M14: 0 | N14: 0 | O14: 0 | P14: 0 | Q14: 150 | R14: 0 | T14: 1 | U14: 0 | V14: 0.5 | X14: 0.02 | Z14: =IF($J14>=5000,6000,3000) -> 3000 | AA14: =IF($J14>=5000,2650,500) -> 500 | AB14: 650 | AC14: 2500 | AE14: 0 | AG14: 300 | AH14: 2000 | AJ14: =J14 -> 1090.7143 | AK14: =M14 -> 0 | AL14: =P14*J14/12 -> 0 | AM14: =Q14 -> 150 | AN14: =T14*J14/24 -> 45.446429 | AO14: =U14*J14/12 -> 0 | AP14: =V14*J14/24 -> 22.723214 | AQ14: =X14*(AJ14+AL14) -> 21.814286 | AR14: =Z14/24 -> 125 | AS14: =AA14/12 -> 41.666667 | AT14: =AB14/12 -> 54.166667 | AU14: =AC14/12 -> 208.33333 | AV14: =AE14*AJ14/36 -> 0 | AW14: =AG14/36 -> 8.3333333 | AX14: =AH14/36 -> 55.555556 | AY14: =SUM(AJ14:AX14) -> 1823.7538
C15: Manual | E15: Equipment | F15: Equipment | G15: Crusher Operator | H15: 24 | I15: 26950 | J15: 1122.9167 | K15: 1400 | L15: 900 | M15: 0 | N15: 0 | O15: 0 | P15: 0 | Q15: 200 | R15: 150 | T15: 1 | U15: 0 | V15: 0.5 | X15: 0.02 | Z15: =IF($J15>=5000,6000,3000) -> 3000 | AA15: =IF($J15>=5000,2650,500) -> 500 | AB15: 650 | AC15: 2500 | AE15: 0 | AG15: 300 | AH15: 2000 | AJ15: =J15 -> 1122.9167 | AK15: =M15 -> 0 | AL15: =P15*J15/12 -> 0 | AM15: =Q15 -> 200 | AN15: =T15*J15/24 -> 46.788194 | AO15: =U15*J15/12 -> 0 | AP15: =V15*J15/24 -> 23.394097 | AQ15: =X15*(AJ15+AL15) -> 22.458333 | AR15: =Z15/24 -> 125 | AS15: =AA15/12 -> 41.666667 | AT15: =AB15/12 -> 54.166667 | AU15: =AC15/12 -> 208.33333 | AV15: =AE15*AJ15/36 -> 0 | AW15: =AG15/36 -> 8.3333333 | AX15: =AH15/36 -> 55.555556 | AY15: =SUM(AJ15:AX15) -> 1908.6128
C16: Manual | E16: Equipment | F16: Equipment | G16: Crusher Technician | H16: 3 | I16: 4000 | J16: 1333.3333 | K16: 1500 | L16: 1200 | M16: 0 | N16: 0 | O16: 0 | P16: 0 | Q16: 200 | R16: 150 | T16: 1 | U16: 0 | V16: 0.5 | X16: 0.02 | Z16: =IF($J16>=5000,6000,3000) -> 3000 | AA16: =IF($J16>=5000,2650,500) -> 500 | AB16: 650 | AC16: 2500 | AE16: 0 | AG16: 300 | AH16: 2000 | AJ16: =J16 -> 1333.3333 | AK16: =M16 -> 0 | AL16: =P16*J16/12 -> 0 | AM16: =Q16 -> 200 | AN16: =T16*J16/24 -> 55.555556 | AO16: =U16*J16/12 -> 0 | AP16: =V16*J16/24 -> 27.777778 | AQ16: =X16*(AJ16+AL16) -> 26.666667 | AR16: =Z16/24 -> 125 | AS16: =AA16/12 -> 41.666667 | AT16: =AB16/12 -> 54.166667 | AU16: =AC16/12 -> 208.33333 | AV16: =AE16*AJ16/36 -> 0 | AW16: =AG16/36 -> 8.3333333 | AX16: =AH16/36 -> 55.555556 | AY16: =SUM(AJ16:AX16) -> 2136.3889
C17: Manual | E17: Equipment | F17: Equipment | G17: Cutter | H17: 6 | I17: 3695 | J17: 615.83333 | K17: 660 | L17: 535 | M17: 0 | N17: 0 | O17: 0 | P17: 0 | Q17: 250 | R17: 250 | T17: 1 | U17: 0 | V17: 0.5 | X17: 0.02 | Z17: =IF($J17>=5000,6000,3000) -> 3000 | AA17: =IF($J17>=5000,2650,500) -> 500 | AB17: 650 | AC17: 2500 | AE17: 0 | AG17: 300 | AH17: 2000 | AJ17: =J17 -> 615.83333 | AK17: =M17 -> 0 | AL17: =P17*J17/12 -> 0 | AM17: =Q17 -> 250 | AN17: =T17*J17/24 -> 25.659722 | AO17: =U17*J17/12 -> 0 | AP17: =V17*J17/24 -> 12.829861 | AQ17: =X17*(AJ17+AL17) -> 12.316667 | AR17: =Z17/24 -> 125 | AS17: =AA17/12 -> 41.666667 | AT17: =AB17/12 -> 54.166667 | AU17: =AC17/12 -> 208.33333 | AV17: =AE17*AJ17/36 -> 0 | AW17: =AG17/36 -> 8.3333333 | AX17: =AH17/36 -> 55.555556 | AY17: =SUM(AJ17:AX17) -> 1409.6951
C18: Manual | E18: Equipment | F18: Equipment | G18: Denter | H18: 3 | I18: 3090 | J18: 1030 | K18: 1300 | L18: 690 | M18: 0 | N18: 0 | O18: 0 | P18: 0 | Q18: 150 | R18: 120 | T18: 1 | U18: 0 | V18: 0.5 | X18: 0.02 | Z18: =IF($J18>=5000,6000,3000) -> 3000 | AA18: =IF($J18>=5000,2650,500) -> 500 | AB18: 650 | AC18: 2500 | AE18: 0 | AG18: 300 | AH18: 2000 | AJ18: =J18 -> 1030 | AK18: =M18 -> 0 | AL18: =P18*J18/12 -> 0 | AM18: =Q18 -> 150 | AN18: =T18*J18/24 -> 42.916667 | AO18: =U18*J18/12 -> 0 | AP18: =V18*J18/24 -> 21.458333 | AQ18: =X18*(AJ18+AL18) -> 20.6 | AR18: =Z18/24 -> 125 | AS18: =AA18/12 -> 41.666667 | AT18: =AB18/12 -> 54.166667 | AU18: =AC18/12 -> 208.33333 | AV18: =AE18*AJ18/36 -> 0 | AW18: =AG18/36 -> 8.3333333 | AX18: =AH18/36 -> 55.555556 | AY18: =SUM(AJ18:AX18) -> 1758.0306
C19: Manual | E19: Equipment | F19: Equipment | G19: Diesel Mechanic | H19: 1 | I19: 1200 | J19: 1200 | K19: 1200 | L19: 1200 | M19: 0 | N19: 0 | O19: 0 | P19: 0 | Q19: 150 | R19: 150 | T19: 1 | U19: 0 | V19: 0.5 | X19: 0.02 | Z19: =IF($J19>=5000,6000,3000) -> 3000 | AA19: =IF($J19>=5000,2650,500) -> 500 | AB19: 650 | AC19: 2500 | AE19: 0 | AG19: 300 | AH19: 2000 | AJ19: =J19 -> 1200 | AK19: =M19 -> 0 | AL19: =P19*J19/12 -> 0 | AM19: =Q19 -> 150 | AN19: =T19*J19/24 -> 50 | AO19: =U19*J19/12 -> 0 | AP19: =V19*J19/24 -> 25 | AQ19: =X19*(AJ19+AL19) -> 24 | AR19: =Z19/24 -> 125 | AS19: =AA19/12 -> 41.666667 | AT19: =AB19/12 -> 54.166667 | AU19: =AC19/12 -> 208.33333 | AV19: =AE19*AJ19/36 -> 0 | AW19: =AG19/36 -> 8.3333333 | AX19: =AH19/36 -> 55.555556 | AY19: =SUM(AJ19:AX19) -> 1942.0556
C20: Manual | E20: Miscelainious | F20: Drivers | G20: Driver Ambulance | H20: 8 | I20: 8050 | J20: 1006.25 | K20: 1350 | L20: 800 | M20: 0 | N20: 0 | O20: 0 | P20: 0 | Q20: 200 | R20: 150 | T20: 1 | U20: 0 | V20: 0.5 | X20: 0.02 | Z20: =IF($J20>=5000,6000,3000) -> 3000 | AA20: =IF($J20>=5000,2650,500) -> 500 | AB20: 650 | AC20: 2500 | AE20: 0 | AG20: 300 | AH20: 2000 | AJ20: =J20 -> 1006.25 | AK20: =M20 -> 0 | AL20: =P20*J20/12 -> 0 | AM20: =Q20 -> 200 | AN20: =T20*J20/24 -> 41.927083 | AO20: =U20*J20/12 -> 0 | AP20: =V20*J20/24 -> 20.963542 | AQ20: =X20*(AJ20+AL20) -> 20.125 | AR20: =Z20/24 -> 125 | AS20: =AA20/12 -> 41.666667 | AT20: =AB20/12 -> 54.166667 | AU20: =AC20/12 -> 208.33333 | AV20: =AE20*AJ20/36 -> 0 | AW20: =AG20/36 -> 8.3333333 | AX20: =AH20/36 -> 55.555556 | AY20: =SUM(AJ20:AX20) -> 1782.3212
C21: Manual | E21: Miscelainious | F21: Drivers | G21: Driver Concrete Mixer | H21: 5 | I21: 5900 | J21: 1180 | K21: 1300 | L21: 1100 | M21: 0 | N21: 0 | O21: 0 | P21: 0 | Q21: 150 | R21: 150 | T21: 1 | U21: 0 | V21: 0.5 | X21: 0.02 | Z21: =IF($J21>=5000,6000,3000) -> 3000 | AA21: =IF($J21>=5000,2650,500) -> 500 | AB21: 650 | AC21: 2500 | AE21: 0 | AG21: 300 | AH21: 2000 | AJ21: =J21 -> 1180 | AK21: =M21 -> 0 | AL21: =P21*J21/12 -> 0 | AM21: =Q21 -> 150 | AN21: =T21*J21/24 -> 49.166667 | AO21: =U21*J21/12 -> 0 | AP21: =V21*J21/24 -> 24.583333 | AQ21: =X21*(AJ21+AL21) -> 23.6 | AR21: =Z21/24 -> 125 | AS21: =AA21/12 -> 41.666667 | AT21: =AB21/12 -> 54.166667 | AU21: =AC21/12 -> 208.33333 | AV21: =AE21*AJ21/36 -> 0 | AW21: =AG21/36 -> 8.3333333 | AX21: =AH21/36 -> 55.555556 | AY21: =SUM(AJ21:AX21) -> 1920.4056
C22: Manual | E22: Miscelainious | F22: Drivers | G22: Driver Dump Truck | H22: 2 | I22: 2350 | J22: 1175 | K22: 1500 | L22: 850 | M22: 0 | N22: 0 | O22: 0 | P22: 0 | Q22: 150 | R22: 150 | T22: 1 | U22: 0 | V22: 0.5 | X22: 0.02 | Z22: =IF($J22>=5000,6000,3000) -> 3000 | AA22: =IF($J22>=5000,2650,500) -> 500 | AB22: 650 | AC22: 2500 | AE22: 0 | AG22: 300 | AH22: 2000 | AJ22: =J22 -> 1175 | AK22: =M22 -> 0 | AL22: =P22*J22/12 -> 0 | AM22: =Q22 -> 150 | AN22: =T22*J22/24 -> 48.958333 | AO22: =U22*J22/12 -> 0 | AP22: =V22*J22/24 -> 24.479167 | AQ22: =X22*(AJ22+AL22) -> 23.5 | AR22: =Z22/24 -> 125 | AS22: =AA22/12 -> 41.666667 | AT22: =AB22/12 -> 54.166667 | AU22: =AC22/12 -> 208.33333 | AV22: =AE22*AJ22/36 -> 0 | AW22: =AG22/36 -> 8.3333333 | AX22: =AH22/36 -> 55.555556 | AY22: =SUM(AJ22:AX22) -> 1914.9931
... C29: Manual | E29: HVAC | F29: HVAC | G29: Duct Technician | H29: 5 | I29: 5500 | J29: 1100 | K29: 1100 | L29: 1100 | M29: 0 | N29: 0 | O29: 0 | P29: 0 | Q29: 150 | R29: 150 | T29: 1 | U29: 0 | V29: 0.5 | X29: 0.02 | Z29: =IF($J29>=5000,6000,3000) -> 3000 | AA29: =IF($J29>=5000,2650,500) -> 500 | AB29: 650 | AC29: 2500 | AE29: 0 | AG29: 300 | AH29: 2000 | AJ29: =J29 -> 1100 | AK29: =M29 -> 0 | AL29: =P29*J29/12 -> 0 | AM29: =Q29 -> 150 | AN29: =T29*J29/24 -> 45.833333 | AO29: =U29*J29/12 -> 0 | AP29: =V29*J29/24 -> 22.916667 | AQ29: =X29*(AJ29+AL29) -> 22 | AR29: =Z29/24 -> 125 | AS29: =AA29/12 -> 41.666667 | AT29: =AB29/12 -> 54.166667 | AU29: =AC29/12 -> 208.33333 | AV29: =AE29*AJ29/36 -> 0 | AW29: =AG29/36 -> 8.3333333 | AX29: =AH29/36 -> 55.555556 | AY29: =SUM(AJ29:AX29) -> 1833.8056
C30: Manual | E30: Electrical | F30: Electrical | G30: Electrician | H30: 248 | I30: 286891 | J30: 1156.8185 | K30: 4500 | L30: 400 | M30: 300 | N30: 0 | Q30: 250 | R30: 0 | T30: 1 | U30: 0 | V30: 0.5 | X30: 0.02 | Z30: =IF($J30>=5000,6000,3000) -> 3000 | AA30: =IF($J30>=5000,2650,500) -> 500 | AB30: 650 | AC30: 2500 | AE30: 0 | AG30: 300 | AH30: 2000 | AJ30: =J30 -> 1156.8185 | AK30: =M30 -> 300 | AL30: =P30*J30/12 -> 0 | AM30: =Q30 -> 250 | AN30: =T30*J30/24 -> 48.200773 | AO30: =U30*J30/12 -> 0 | AP30: =V30*J30/24 -> 24.100386 | AQ30: =X30*(AJ30+AL30) -> 23.136371 | AR30: =Z30/24 -> 125 | AS30: =AA30/12 -> 41.666667 | AT30: =AB30/12 -> 54.166667 | AU30: =AC30/12 -> 208.33333 | AV30: =AE30*AJ30/36 -> 0 | AW30: =AG30/36 -> 8.3333333 | AX30: =AH30/36 -> 55.555556 | AY30: =SUM(AJ30:AX30) -> 2295.3116
C31: Manual | E31: Foremans | F31: Forman | G31: Foreman | H31: 221 | I31: 586714 | J31: 2654.8145 | K31: 14000 | L31: 200 | M31: 500 | N31: 0 | O31: 2 | P31: 3 | Q31: 250 | R31: 0 | T31: 1 | U31: 0 | V31: 0.5 | X31: 0.02 | Z31: =IF($J31>=5000,6000,3000) -> 3000 | AA31: =IF($J31>=5000,2650,500) -> 500 | AB31: 650 | AC31: 2500 | AE31: 0 | AG31: 300 | AH31: 2000 | AJ31: =J31 -> 2654.8145 | AK31: =M31 -> 500 | AL31: =P31*J31/12 -> 663.70362 | AM31: =Q31 -> 250 | AN31: =T31*J31/24 -> 110.61727 | AO31: =U31*J31/12 -> 0 | AP31: =V31*J31/24 -> 55.308635 | AQ31: =X31*(AJ31+AL31) -> 66.370362 | AR31: =Z31/24 -> 125 | AS31: =AA31/12 -> 41.666667 | AT31: =AB31/12 -> 54.166667 | AU31: =AC31/12 -> 208.33333 | AV31: =AE31*AJ31/36 -> 0 | AW31: =AG31/36 -> 8.3333333 | AX31: =AH31/36 -> 55.555556 | AY31: =SUM(AJ31:AX31) -> 4793.8699
C32: Manual | E32: Asphalt Plant | F32: Asphalt Plant | G32: Foreman Asphalt Plant | H32: 3 | I32: 9850 | J32: 3283.3333 | K32: 4200 | L32: 1650 | M32: 0 | N32: 0 | O32: 0 | P32: 0 | Q32: 150 | R32: 0 | T32: 1 | U32: 0 | V32: 0.5 | X32: 0.02 | Z32: =IF($J32>=5000,6000,3000) -> 3000 | AA32: =IF($J32>=5000,2650,500) -> 500 | AB32: 650 | AC32: 2500 | AE32: 0 | AG32: 300 | AH32: 2000 | AJ32: =J32 -> 3283.3333 | AK32: =M32 -> 0 | AL32: =P32*J32/12 -> 0 | AM32: =Q32 -> 150 | AN32: =T32*J32/24 -> 136.80556 | AO32: =U32*J32/12 -> 0 | AP32: =V32*J32/24 -> 68.402778 | AQ32: =X32*(AJ32+AL32) -> 65.666667 | AR32: =Z32/24 -> 125 | AS32: =AA32/12 -> 41.666667 | AT32: =AB32/12 -> 54.166667 | AU32: =AC32/12 -> 208.33333 | AV32: =AE32*AJ32/36 -> 0 | AW32: =AG32/36 -> 8.3333333 | AX32: =AH32/36 -> 55.555556 | AY32: =SUM(AJ32:AX32) -> 4197.2639
C33: Manual | E33: Supervision | F33: Foremans | G33: Foreman Assistant | H33: 10 | I33: 28100 | J33: 2810 | K33: 3200 | L33: 500 | M33: 300 | N33: 0 | O33: 0 | P33: 0 | Q33: 150 | R33: 0 | T33: 1 | U33: 0 | V33: 0.5 | X33: 0.02 | Z33: =IF($J33>=5000,6000,3000) -> 3000 | AA33: =IF($J33>=5000,2650,500) -> 500 | AB33: 650 | AC33: 2500 | AE33: 0 | AG33: 300 | AH33: 2000 | AJ33: =J33 -> 2810 | AK33: =M33 -> 300 | AL33: =P33*J33/12 -> 0 | AM33: =Q33 -> 150 | AN33: =T33*J33/24 -> 117.08333 | AO33: =U33*J33/12 -> 0 | AP33: =V33*J33/24 -> 58.541667 | AQ33: =X33*(AJ33+AL33) -> 56.2 | AR33: =Z33/24 -> 125 | AS33: =AA33/12 -> 41.666667 | AT33: =AB33/12 -> 54.166667 | AU33: =AC33/12 -> 208.33333 | AV33: =AE33*AJ33/36 -> 0 | AW33: =AG33/36 -> 8.3333333 | AX33: =AH33/36 -> 55.555556 | AY33: =SUM(AJ33:AX33) -> 3984.8806
C34: Manual | E34: Miscelainious | F34: Camp | G34: Foreman Camp | H34: 11 | I34: 12650 | J34: 1150 | K34: 1400 | L34: 1000 | M34: 0 | N34: 0 | O34: 0 | P34: 0 | Q34: 150 | R34: 150 | T34: 1 | U34: 0 | V34: 0.5 | X34: 0.02 | Z34: =IF($J34>=5000,6000,3000) -> 3000 | AA34: =IF($J34>=5000,2650,500) -> 500 | AB34: 650 | AC34: 2500 | AE34: 0 | AG34: 300 | AH34: 2000 | AJ34: =J34 -> 1150 | AK34: =M34 -> 0 | AL34: =P34*J34/12 -> 0 | AM34: =Q34 -> 150 | AN34: =T34*J34/24 -> 47.916667 | AO34: =U34*J34/12 -> 0 | AP34: =V34*J34/24 -> 23.958333 | AQ34: =X34*(AJ34+AL34) -> 23 | AR34: =Z34/24 -> 125 | AS34: =AA34/12 -> 41.666667 | AT34: =AB34/12 -> 54.166667 | AU34: =AC34/12 -> 208.33333 | AV34: =AE34*AJ34/36 -> 0 | AW34: =AG34/36 -> 8.3333333 | AX34: =AH34/36 -> 55.555556 | AY34: =SUM(AJ34:AX34) -> 1887.9306
C35: Manual | E35: Concrete | F35: Concrete Form | G35: Foreman Carpenter | H35: 15 | I35: 43593 | J35: 2906.2 | K35: 3600 | L35: 1418 | M35: 0 | N35: 0 | O35: 0 | P35: 0 | Q35: 250 | R35: 0 | T35: 1 | U35: 0 | V35: 0.5 | X35: 0.02 | Z35: =IF($J35>=5000,6000,3000) -> 3000 | AA35: =IF($J35>=5000,2650,500) -> 500 | AB35: 650 | AC35: 2500 | AE35: 0 | AG35: 300 | AH35: 2000 | AJ35: =J35 -> 2906.2 | AK35: =M35 -> 0 | AL35: =P35*J35/12 -> 0 | AM35: =Q35 -> 250 | AN35: =T35*J35/24 -> 121.09167 | AO35: =U35*J35/12 -> 0 | AP35: =V35*J35/24 -> 60.545833 | AQ35: =X35*(AJ35+AL35) -> 58.124 | AR35: =Z35/24 -> 125 | AS35: =AA35/12 -> 41.666667 | AT35: =AB35/12 -> 54.166667 | AU35: =AC35/12 -> 208.33333 | AV35: =AE35*AJ35/36 -> 0 | AW35: =AG35/36 -> 8.3333333 | AX35: =AH35/36 -> 55.555556 | AY35: =SUM(AJ35:AX35) -> 3889.0171
C36: Manual | E36: Concrete | F36: General | G36: Foreman Civil | H36: 153 | I36: 488789 | J36: 3194.6993 | K36: 5000 | L36: 1400 | M36: 400 | N36: 0 | O36: 2 | P36: 3 | Q36: 150 | R36: 0 | T36: 1 | U36: 0 | V36: 0.5 | X36: 0.02 | Z36: =IF($J36>=5000,6000,3000) -> 3000 | AA36: =IF($J36>=5000,2650,500) -> 500 | AB36: 650 | AC36: 2500 | AE36: 0 | AG36: 300 | AH36: 2000 | AJ36: =J36 -> 3194.6993 | AK36: =M36 -> 400 | AL36: =P36*J36/12 -> 798.67484 | AM36: =Q36 -> 150 | AN36: =T36*J36/24 -> 133.11247 | AO36: =U36*J36/12 -> 0 | AP36: =V36*J36/24 -> 66.556236 | AQ36: =X36*(AJ36+AL36) -> 79.867484 | AR36: =Z36/24 -> 125 | AS36: =AA36/12 -> 41.666667 | AT36: =AB36/12 -> 54.166667 | AU36: =AC36/12 -> 208.33333 | AV36: =AE36*AJ36/36 -> 0 | AW36: =AG36/36 -> 8.3333333 | AX36: =AH36/36 -> 55.555556 | AY36: =SUM(AJ36:AX36) -> 5315.9659
C37: Manual | E37: Cleaning | F37: Cleaning | G37: Foreman Cleaning | H37: 202 | I37: 232429 | J37: 1150.6386 | K37: 5500 | L37: 200 | M37: 500 | N37: 0 | O37: 2 | P37: 2 | Q37: 250 | R37: 0 | T37: 1 | U37: 0 | V37: 0.5 | X37: 0.02 | Z37: =IF($J37>=5000,6000,3000) -> 3000 | AA37: =IF($J37>=5000,2650,500) -> 500 | AB37: 650 | AC37: 2500 | AE37: 0 | AG37: 300 | AH37: 2000 | AJ37: =J37 -> 1150.6386 | AK37: =M37 -> 500 | AL37: =P37*J37/12 -> 191.7731 | AM37: =Q37 -> 250 | AN37: =T37*J37/24 -> 47.943276 | AO37: =U37*J37/12 -> 0 | AP37: =V37*J37/24 -> 23.971638 | AQ37: =X37*(AJ37+AL37) -> 26.848234 | AR37: =Z37/24 -> 125 | AS37: =AA37/12 -> 41.666667 | AT37: =AB37/12 -> 54.166667 | AU37: =AC37/12 -> 208.33333 | AV37: =AE37*AJ37/36 -> 0 | AW37: =AG37/36 -> 8.3333333 | AX37: =AH37/36 -> 55.555556 | AY37: =SUM(AJ37:AX37) -> 2684.2304
C38: Manual | E38: Crushing Plant | F38: Crushing Plant | G38: Foreman Crusher | H38: 2 | I38: 4500 | J38: 2250 | K38: 2500 | L38: 2000 | M38: 0 | N38: 0 | O38: 0 | P38: 0 | Q38: 200 | R38: 0 | T38: 1 | U38: 0 | V38: 0.5 | X38: 0.02 | Z38: =IF($J38>=5000,6000,3000) -> 3000 | AA38: =IF($J38>=5000,2650,500) -> 500 | AB38: 650 | AC38: 2500 | AE38: 0 | AG38: 300 | AH38: 2000 | AJ38: =J38 -> 2250 | AK38: =M38 -> 0 | AL38: =P38*J38/12 -> 0 | AM38: =Q38 -> 200 | AN38: =T38*J38/24 -> 93.75 | AO38: =U38*J38/12 -> 0 | AP38: =V38*J38/24 -> 46.875 | AQ38: =X38*(AJ38+AL38) -> 45 | AR38: =Z38/24 -> 125 | AS38: =AA38/12 -> 41.666667 | AT38: =AB38/12 -> 54.166667 | AU38: =AC38/12 -> 208.33333 | AV38: =AE38*AJ38/36 -> 0 | AW38: =AG38/36 -> 8.3333333 | AX38: =AH38/36 -> 55.555556 | AY38: =SUM(AJ38:AX38) -> 3128.6806
C39: Manual | E39: HVAC | F39: HVAC | G39: Foreman Ducting | H39: 6 | I39: 16875 | J39: 2812.5 | K39: 3200 | L39: 2300 | M39: 0 | N39: 0 | O39: 0 | P39: 0 | Q39: 0 | R39: 0 | T39: 1 | U39: 0 | V39: 0.5 | X39: 0.02 | Z39: =IF($J39>=5000,6000,3000) -> 3000 | AA39: =IF($J39>=5000,2650,500) -> 500 | AB39: 650 | AC39: 2500 | AE39: 0 | AG39: 300 | AH39: 2000 | AJ39: =J39 -> 2812.5 | AK39: =M39 -> 0 | AL39: =P39*J39/12 -> 0 | AM39: =Q39 -> 0 | AN39: =T39*J39/24 -> 117.1875 | AO39: =U39*J39/12 -> 0 | AP39: =V39*J39/24 -> 58.59375 | AQ39: =X39*(AJ39+AL39) -> 56.25 | AR39: =Z39/24 -> 125 | AS39: =AA39/12 -> 41.666667 | AT39: =AB39/12 -> 54.166667 | AU39: =AC39/12 -> 208.33333 | AV39: =AE39*AJ39/36 -> 0 | AW39: =AG39/36 -> 8.3333333 | AX39: =AH39/36 -> 55.555556 | AY39: =SUM(AJ39:AX39) -> 3537.5868
C40: Manual | E40: Earth Work | F40: Earth Work | G40: Foreman Earthwork | H40: 2 | I40: 5500 | J40: 2750 | K40: 3000 | L40: 2500 | M40: 0 | N40: 0 | O40: 0 | P40: 0 | Q40: 0 | R40: 0 | T40: 1 | U40: 0 | V40: 0.5 | X40: 0.02 | Z40: =IF($J40>=5000,6000,3000) -> 3000 | AA40: =IF($J40>=5000,2650,500) -> 500 | AB40: 650 | AC40: 2500 | AE40: 0 | AG40: 300 | AH40: 2000 | AJ40: =J40 -> 2750 | AK40: =M40 -> 0 | AL40: =P40*J40/12 -> 0 | AM40: =Q40 -> 0 | AN40: =T40*J40/24 -> 114.58333 | AO40: =U40*J40/12 -> 0 | AP40: =V40*J40/24 -> 57.291667 | AQ40: =X40*(AJ40+AL40) -> 55 | AR40: =Z40/24 -> 125 | AS40: =AA40/12 -> 41.666667 | AT40: =AB40/12 -> 54.166667 | AU40: =AC40/12 -> 208.33333 | AV40: =AE40*AJ40/36 -> 0 | AW40: =AG40/36 -> 8.3333333 | AX40: =AH40/36 -> 55.555556 | AY40: =SUM(AJ40:AX40) -> 3469.9306
C41: Manual | E41: Electrical | F41: Electrical | G41: Foreman Electrical | H41: 50 | I41: 143791 | J41: 2875.82 | K41: 4000 | L41: 1386 | M41: 400 | N41: 0 | O41: 2 | P41: 2 | Q41: 250 | R41: 0 | T41: 1 | U41: 0 | V41: 0.5 | X41: 0.02 | Z41: =IF($J41>=5000,6000,3000) -> 3000 | AA41: =IF($J41>=5000,2650,500) -> 500 | AB41: 650 | AC41: 2500 | AE41: 0 | AG41: 300 | AH41: 2000 | AJ41: =J41 -> 2875.82 | AK41: =M41 -> 400 | AL41: =P41*J41/12 -> 479.30333 | AM41: =Q41 -> 250 | AN41: =T41*J41/24 -> 119.82583 | AO41: =U41*J41/12 -> 0 | AP41: =V41*J41/24 -> 59.912917 | AQ41: =X41*(AJ41+AL41) -> 67.102467 | AR41: =Z41/24 -> 125 | AS41: =AA41/12 -> 41.666667 | AT41: =AB41/12 -> 54.166667 | AU41: =AC41/12 -> 208.33333 | AV41: =AE41*AJ41/36 -> 0 | AW41: =AG41/36 -> 8.3333333 | AX41: =AH41/36 -> 55.555556 | AY41: =SUM(AJ41:AX41) -> 4745.0201
C42: Manual | E42: Equipment | F42: Equipment | G42: Foreman EMD | H42: 2 | I42: 4500 | J42: 2250 | K42: 2500 | L42: 2000 | M42: 0 | N42: 0 | O42: 0 | P42: 0 | Q42: 150 | R42: 0 | T42: 1 | U42: 0 | V42: 0.5 | X42: 0.02 | Z42: =IF($J42>=5000,6000,3000) -> 3000 | AA42: =IF($J42>=5000,2650,500) -> 500 | AB42: 650 | AC42: 2500 | AE42: 0 | AG42: 300 | AH42: 2000 | AJ42: =J42 -> 2250 | AK42: =M42 -> 0 | AL42: =P42*J42/12 -> 0 | AM42: =Q42 -> 150 | AN42: =T42*J42/24 -> 93.75 | AO42: =U42*J42/12 -> 0 | AP42: =V42*J42/24 -> 46.875 | AQ42: =X42*(AJ42+AL42) -> 45 | AR42: =Z42/24 -> 125 | AS42: =AA42/12 -> 41.666667 | AT42: =AB42/12 -> 54.166667 | AU42: =AC42/12 -> 208.33333 | AV42: =AE42*AJ42/36 -> 0 | AW42: =AG42/36 -> 8.3333333 | AX42: =AH42/36 -> 55.555556 | AY42: =SUM(AJ42:AX42) -> 3078.6806
... C46: Manual | E46: Work Shop | F46: Maintenance | G46: Foreman Mechanical | H46: 25 | I46: 82062 | J46: 3282.48 | K46: 5500 | L46: 2200 | M46: 300 | N46: 0 | O46: 2 | P46: 2 | Q46: 150 | R46: 0 | T46: 1 | U46: 0 | V46: 0.5 | X46: 0.02 | Z46: =IF($J46>=5000,6000,3000) -> 3000 | AA46: =IF($J46>=5000,2650,500) -> 500 | AB46: 650 | AC46: 2500 | AE46: 0 | AG46: 300 | AH46: 2000 | AJ46: =J46 -> 3282.48 | AK46: =M46 -> 300 | AL46: =P46*J46/12 -> 547.08 | AM46: =Q46 -> 150 | AN46: =T46*J46/24 -> 136.77 | AO46: =U46*J46/12 -> 0 | AP46: =V46*J46/24 -> 68.385 | AQ46: =X46*(AJ46+AL46) -> 76.5912 | AR46: =Z46/24 -> 125 | AS46: =AA46/12 -> 41.666667 | AT46: =AB46/12 -> 54.166667 | AU46: =AC46/12 -> 208.33333 | AV46: =AE46*AJ46/36 -> 0 | AW46: =AG46/36 -> 8.3333333 | AX46: =AH46/36 -> 55.555556 | AY46: =SUM(AJ46:AX46) -> 5054.3618
C47: Manual | G47: Foreman Operations | H47: 4 | I47: 7764 | J47: 1941 | K47: 2100 | L47: 1850 | M47: 0 | N47: 0 | O47: 0 | P47: 0 | Q47: 250 | R47: 0 | T47: 1 | U47: 0 | V47: 0.5 | X47: 0.02 | Z47: =IF($J47>=5000,6000,3000) -> 3000 | AA47: =IF($J47>=5000,2650,500) -> 500 | AB47: 650 | AC47: 2500 | AE47: 0 | AG47: 300 | AH47: 2000 | AJ47: =J47 -> 1941 | AK47: =M47 -> 0 | AL47: =P47*J47/12 -> 0 | AM47: =Q47 -> 250 | AN47: =T47*J47/24 -> 80.875 | AO47: =U47*J47/12 -> 0 | AP47: =V47*J47/24 -> 40.4375 | AQ47: =X47*(AJ47+AL47) -> 38.82 | AR47: =Z47/24 -> 125 | AS47: =AA47/12 -> 41.666667 | AT47: =AB47/12 -> 54.166667 | AU47: =AC47/12 -> 208.33333 | AV47: =AE47*AJ47/36 -> 0 | AW47: =AG47/36 -> 8.3333333 | AX47: =AH47/36 -> 55.555556 | AY47: =SUM(AJ47:AX47) -> 2844.1881
C48: Manual | E48: Finishing | F48: Painting | G48: Foreman Painter | H48: 5 | I48: 15545 | J48: 3109 | K48: 3500 | L48: 2800 | M48: 0 | N48: 0 | O48: 2 | P48: 2 | Q48: 0 | R48: 0 | T48: 1 | U48: 0 | V48: 0.5 | X48: 0.02 | Z48: =IF($J48>=5000,6000,3000) -> 3000 | AA48: =IF($J48>=5000,2650,500) -> 500 | AB48: 650 | AC48: 2500 | AE48: 0 | AG48: 300 | AH48: 2000 | AJ48: =J48 -> 3109 | AK48: =M48 -> 0 | AL48: =P48*J48/12 -> 518.16667 | AM48: =Q48 -> 0 | AN48: =T48*J48/24 -> 129.54167 | AO48: =U48*J48/12 -> 0 | AP48: =V48*J48/24 -> 64.770833 | AQ48: =X48*(AJ48+AL48) -> 72.543333 | AR48: =Z48/24 -> 125 | AS48: =AA48/12 -> 41.666667 | AT48: =AB48/12 -> 54.166667 | AU48: =AC48/12 -> 208.33333 | AV48: =AE48*AJ48/36 -> 0 | AW48: =AG48/36 -> 8.3333333 | AX48: =AH48/36 -> 55.555556 | AY48: =SUM(AJ48:AX48) -> 4387.0781
C49: Manual | E49: Plumbing | F49: Sewage | G49: Foreman Piping | H49: 10 | I49: 30300 | J49: 3030 | K49: 4500 | L49: 2200 | M49: 0 | N49: 0 | O49: 2 | P49: 2 | Q49: 150 | R49: 0 | T49: 1 | U49: 0 | V49: 0.5 | X49: 0.02 | Z49: =IF($J49>=5000,6000,3000) -> 3000 | AA49: =IF($J49>=5000,2650,500) -> 500 | AB49: 650 | AC49: 2500 | AE49: 0 | AG49: 300 | AH49: 2000 | AJ49: =J49 -> 3030 | AK49: =M49 -> 0 | AL49: =P49*J49/12 -> 505 | AM49: =Q49 -> 150 | AN49: =T49*J49/24 -> 126.25 | AO49: =U49*J49/12 -> 0 | AP49: =V49*J49/24 -> 63.125 | AQ49: =X49*(AJ49+AL49) -> 70.7 | AR49: =Z49/24 -> 125 | AS49: =AA49/12 -> 41.666667 | AT49: =AB49/12 -> 54.166667 | AU49: =AC49/12 -> 208.33333 | AV49: =AE49*AJ49/36 -> 0 | AW49: =AG49/36 -> 8.3333333 | AX49: =AH49/36 -> 55.555556 | AY49: =SUM(AJ49:AX49) -> 4438.1306
C50: Manual | E50: Equipment | F50: Equipment | G50: Foreman Plant Equipment | H50: 3 | I50: 12364 | J50: 4121.3333 | K50: 6064 | L50: 2900 | M50: 0 | N50: 0 | O50: 2 | P50: 2 | Q50: 0 | R50: 0 | T50: 1 | U50: 0 | V50: 0.5 | X50: 0.02 | Z50: =IF($J50>=5000,6000,3000) -> 3000 | AA50: =IF($J50>=5000,2650,500) -> 500 | AB50: 650 | AC50: 2500 | AE50: 0 | AG50: 300 | AH50: 2000 | AJ50: =J50 -> 4121.3333 | AK50: =M50 -> 0 | AL50: =P50*J50/12 -> 686.88889 | AM50: =Q50 -> 0 | AN50: =T50*J50/24 -> 171.72222 | AO50: =U50*J50/12 -> 0 | AP50: =V50*J50/24 -> 85.861111 | AQ50: =X50*(AJ50+AL50) -> 96.164444 | AR50: =Z50/24 -> 125 | AS50: =AA50/12 -> 41.666667 | AT50: =AB50/12 -> 54.166667 | AU50: =AC50/12 -> 208.33333 | AV50: =AE50*AJ50/36 -> 0 | AW50: =AG50/36 -> 8.3333333 | AX50: =AH50/36 -> 55.555556 | AY50: =SUM(AJ50:AX50) -> 5655.0256
C51: Manual | E51: Plumbing | F51: Building Plumbing | G51: Foreman Plumbing | H51: 25 | I51: 74415 | J51: 2976.6 | K51: 4500 | L51: 2000 | M51: 0 | N51: 0 | O51: 0 | P51: 0 | Q51: 150 | R51: 0 | T51: 1 | U51: 0 | V51: 0.5 | X51: 0.02 | Z51: =IF($J51>=5000,6000,3000) -> 3000 | AA51: =IF($J51>=5000,2650,500) -> 500 | AB51: 650 | AC51: 2500 | AE51: 0 | AG51: 300 | AH51: 2000 | AJ51: =J51 -> 2976.6 | AK51: =M51 -> 0 | AL51: =P51*J51/12 -> 0 | AM51: =Q51 -> 150 | AN51: =T51*J51/24 -> 124.025 | AO51: =U51*J51/12 -> 0 | AP51: =V51*J51/24 -> 62.0125 | AQ51: =X51*(AJ51+AL51) -> 59.532 | AR51: =Z51/24 -> 125 | AS51: =AA51/12 -> 41.666667 | AT51: =AB51/12 -> 54.166667 | AU51: =AC51/12 -> 208.33333 | AV51: =AE51*AJ51/36 -> 0 | AW51: =AG51/36 -> 8.3333333 | AX51: =AH51/36 -> 55.555556 | AY51: =SUM(AJ51:AX51) -> 3865.2251
C52: Manual | E52: Roads | F52: Roads | G52: Foreman Roads | H52: 41 | I52: 143699 | J52: 3504.8537 | K52: 6500 | L52: 1700 | M52: 0 | N52: 0 | O52: 3 | P52: 3 | Q52: 150 | R52: 0 | T52: 1 | U52: 0 | V52: 0.5 | X52: 0.02 | Z52: =IF($J52>=5000,6000,3000) -> 3000 | AA52: =IF($J52>=5000,2650,500) -> 500 | AB52: 650 | AC52: 2500 | AE52: 0 | AG52: 300 | AH52: 2000 | AJ52: =J52 -> 3504.8537 | AK52: =M52 -> 0 | AL52: =P52*J52/12 -> 876.21341 | AM52: =Q52 -> 150 | AN52: =T52*J52/24 -> 146.03557 | AO52: =U52*J52/12 -> 0 | AP52: =V52*J52/24 -> 73.017785 | AQ52: =X52*(AJ52+AL52) -> 87.621341 | AR52: =Z52/24 -> 125 | AS52: =AA52/12 -> 41.666667 | AT52: =AB52/12 -> 54.166667 | AU52: =AC52/12 -> 208.33333 | AV52: =AE52*AJ52/36 -> 0 | AW52: =AG52/36 -> 8.3333333 | AX52: =AH52/36 -> 55.555556 | AY52: =SUM(AJ52:AX52) -> 5330.7973
C53: Manual | E53: Miscelainious | F53: Site | G53: Foreman Scraper | H53: 1 | I53: 4020 | J53: 4020 | K53: 4020 | L53: 4020 | M53: 0 | N53: 0 | O53: 0 | P53: 0 | Q53: 300 | R53: 300 | T53: 1 | U53: 0 | V53: 0.5 | X53: 0.02 | Z53: =IF($J53>=5000,6000,3000) -> 3000 | AA53: =IF($J53>=5000,2650,500) -> 500 | AB53: 650 | AC53: 2500 | AE53: 0 | AG53: 300 | AH53: 2000 | AJ53: =J53 -> 4020 | AK53: =M53 -> 0 | AL53: =P53*J53/12 -> 0 | AM53: =Q53 -> 300 | AN53: =T53*J53/24 -> 167.5 | AO53: =U53*J53/12 -> 0 | AP53: =V53*J53/24 -> 83.75 | AQ53: =X53*(AJ53+AL53) -> 80.4 | AR53: =Z53/24 -> 125 | AS53: =AA53/12 -> 41.666667 | AT53: =AB53/12 -> 54.166667 | AU53: =AC53/12 -> 208.33333 | AV53: =AE53*AJ53/36 -> 0 | AW53: =AG53/36 -> 8.3333333 | AX53: =AH53/36 -> 55.555556 | AY53: =SUM(AJ53:AX53) -> 5144.7056
C54: Manual | E54: Concrete | F54: Reinforcement | G54: Foreman Steel Fixer | H54: 7 | I54: 20240 | J54: 2891.4286 | K54: 3500 | L54: 2000 | M54: 0 | N54: 0 | O54: 2 | P54: 2 | Q54: 150 | R54: 0 | T54: 1 | U54: 0 | V54: 0.5 | X54: 0.02 | Z54: =IF($J54>=5000,6000,3000) -> 3000 | AA54: =IF($J54>=5000,2650,500) -> 500 | AB54: 650 | AC54: 2500 | AE54: 0 | AG54: 300 | AH54: 2000 | AJ54: =J54 -> 2891.4286 | AK54: =M54 -> 0 | AL54: =P54*J54/12 -> 481.90476 | AM54: =Q54 -> 150 | AN54: =T54*J54/24 -> 120.47619 | AO54: =U54*J54/12 -> 0 | AP54: =V54*J54/24 -> 60.238095 | AQ54: =X54*(AJ54+AL54) -> 67.466667 | AR54: =Z54/24 -> 125 | AS54: =AA54/12 -> 41.666667 | AT54: =AB54/12 -> 54.166667 | AU54: =AC54/12 -> 208.33333 | AV54: =AE54*AJ54/36 -> 0 | AW54: =AG54/36 -> 8.3333333 | AX54: =AH54/36 -> 55.555556 | AY54: =SUM(AJ54:AX54) -> 4264.5698
C55: Manual | E55: Traffic | F55: Traffic | G55: Foreman Traffic Safety | H55: 1 | I55: 3000 | J55: 3000 | K55: 3000 | L55: 3000 | M55: 0 | N55: 0 | O55: 0 | P55: 0 | Q55: 0 | R55: 0 | T55: 1 | U55: 0 | V55: 0.5 | X55: 0.02 | Z55: =IF($J55>=5000,6000,3000) -> 3000 | AA55: =IF($J55>=5000,2650,500) -> 500 | AB55: 650 | AC55: 2500 | AE55: 0 | AG55: 300 | AH55: 2000 | AJ55: =J55 -> 3000 | AK55: =M55 -> 0 | AL55: =P55*J55/12 -> 0 | AM55: =Q55 -> 0 | AN55: =T55*J55/24 -> 125 | AO55: =U55*J55/12 -> 0 | AP55: =V55*J55/24 -> 62.5 | AQ55: =X55*(AJ55+AL55) -> 60 | AR55: =Z55/24 -> 125 | AS55: =AA55/12 -> 41.666667 | AT55: =AB55/12 -> 54.166667 | AU55: =AC55/12 -> 208.33333 | AV55: =AE55*AJ55/36 -> 0 | AW55: =AG55/36 -> 8.3333333 | AX55: =AH55/36 -> 55.555556 | AY55: =SUM(AJ55:AX55) -> 3740.5556
C56: Manual | E56: Traffic | F56: Traffic | G56: Foreman Traffic Signals | H56: 3 | I56: 6600 | J56: 2200 | K56: 3500 | L56: 1400 | M56: 0 | N56: 0 | O56: 0 | P56: 0 | Q56: 150 | R56: 0 | T56: 1 | U56: 0 | V56: 0.5 | X56: 0.02 | Z56: =IF($J56>=5000,6000,3000) -> 3000 | AA56: =IF($J56>=5000,2650,500) -> 500 | AB56: 650 | AC56: 2500 | AE56: 0 | AG56: 300 | AH56: 2000 | AJ56: =J56 -> 2200 | AK56: =M56 -> 0 | AL56: =P56*J56/12 -> 0 | AM56: =Q56 -> 150 | AN56: =T56*J56/24 -> 91.666667 | AO56: =U56*J56/12 -> 0 | AP56: =V56*J56/24 -> 45.833333 | AQ56: =X56*(AJ56+AL56) -> 44 | AR56: =Z56/24 -> 125 | AS56: =AA56/12 -> 41.666667 | AT56: =AB56/12 -> 54.166667 | AU56: =AC56/12 -> 208.33333 | AV56: =AE56*AJ56/36 -> 0 | AW56: =AG56/36 -> 8.3333333 | AX56: =AH56/36 -> 55.555556 | AY56: =SUM(AJ56:AX56) -> 3024.5556
C57: Manual | E57: Transportaion | F57: Transportaion | G57: Foreman Transport | H57: 10 | I57: 10700 | J57: 1070 | K57: 2000 | L57: 800 | M57: 0 | N57: 0 | O57: 0 | P57: 0 | Q57: 150 | R57: 150 | T57: 1 | U57: 0 | V57: 0.5 | X57: 0.02 | Z57: =IF($J57>=5000,6000,3000) -> 3000 | AA57: =IF($J57>=5000,2650,500) -> 500 | AB57: 650 | AC57: 2500 | AE57: 0 | AG57: 300 | AH57: 2000 | AJ57: =J57 -> 1070 | AK57: =M57 -> 0 | AL57: =P57*J57/12 -> 0 | AM57: =Q57 -> 150 | AN57: =T57*J57/24 -> 44.583333 | AO57: =U57*J57/12 -> 0 | AP57: =V57*J57/24 -> 22.291667 | AQ57: =X57*(AJ57+AL57) -> 21.4 | AR57: =Z57/24 -> 125 | AS57: =AA57/12 -> 41.666667 | AT57: =AB57/12 -> 54.166667 | AU57: =AC57/12 -> 208.33333 | AV57: =AE57*AJ57/36 -> 0 | AW57: =AG57/36 -> 8.3333333 | AX57: =AH57/36 -> 55.555556 | AY57: =SUM(AJ57:AX57) -> 1801.3306
C58: Manual | E58: Work Shop | F58: Maintenance | G58: Foreman Workshop | H58: 24 | I58: 66020 | J58: 2750.8333 | K58: 5500 | L58: 2000 | M58: 400 | N58: 0 | O58: 2 | P58: 2 | Q58: 200 | R58: 0 | T58: 1 | U58: 0 | V58: 0.5 | X58: 0.02 | Z58: =IF($J58>=5000,6000,3000) -> 3000 | AA58: =IF($J58>=5000,2650,500) -> 500 | AB58: 650 | AC58: 2500 | AE58: 0 | AG58: 300 | AH58: 2000 | AJ58: =J58 -> 2750.8333 | AK58: =M58 -> 400 | AL58: =P58*J58/12 -> 458.47222 | AM58: =Q58 -> 200 | AN58: =T58*J58/24 -> 114.61806 | AO58: =U58*J58/12 -> 0 | AP58: =V58*J58/24 -> 57.309028 | AQ58: =X58*(AJ58+AL58) -> 64.186111 | AR58: =Z58/24 -> 125 | AS58: =AA58/12 -> 41.666667 | AT58: =AB58/12 -> 54.166667 | AU58: =AC58/12 -> 208.33333 | AV58: =AE58*AJ58/36 -> 0 | AW58: =AG58/36 -> 8.3333333 | AX58: =AH58/36 -> 55.555556 | AY58: =SUM(AJ58:AX58) -> 4538.4743
C59: Manual | E59: Miscelainious | F59: Site | G59: Gardener | H59: 49 | I59: 29340 | J59: 598.77551 | K59: 1100 | L59: 500 | M59: 0 | N59: 0 | O59: 0 | P59: 0 | Q59: 250 | R59: 150 | T59: 1 | U59: 0 | V59: 0.5 | X59: 0.02 | Z59: =IF($J59>=5000,6000,3000) -> 3000 | AA59: =IF($J59>=5000,2650,500) -> 500 | AB59: 650 | AC59: 2500 | AE59: 0 | AG59: 300 | AH59: 2000 | AJ59: =J59 -> 598.77551 | AK59: =M59 -> 0 | AL59: =P59*J59/12 -> 0 | AM59: =Q59 -> 250 | AN59: =T59*J59/24 -> 24.94898 | AO59: =U59*J59/12 -> 0 | AP59: =V59*J59/24 -> 12.47449 | AQ59: =X59*(AJ59+AL59) -> 11.97551 | AR59: =Z59/24 -> 125 | AS59: =AA59/12 -> 41.666667 | AT59: =AB59/12 -> 54.166667 | AU59: =AC59/12 -> 208.33333 | AV59: =AE59*AJ59/36 -> 0 | AW59: =AG59/36 -> 8.3333333 | AX59: =AH59/36 -> 55.555556 | AY59: =SUM(AJ59:AX59) -> 1391.23
... C62: Manual | E62: Miscelainious | F62: Drivers | G62: Heavy Duty Driver | H62: 2 | I62: 1850 | J62: 925 | K62: 950 | L62: 900 | M62: 0 | N62: 0 | O62: 0 | P62: 0 | Q62: 150 | R62: 150 | T62: 1 | U62: 0 | V62: 0.5 | X62: 0.02 | Z62: =IF($J62>=5000,6000,3000) -> 3000 | AA62: =IF($J62>=5000,2650,500) -> 500 | AB62: 650 | AC62: 2500 | AE62: 0 | AG62: 300 | AH62: 2000 | AJ62: =J62 -> 925 | AK62: =M62 -> 0 | AL62: =P62*J62/12 -> 0 | AM62: =Q62 -> 150 | AN62: =T62*J62/24 -> 38.541667 | AO62: =U62*J62/12 -> 0 | AP62: =V62*J62/24 -> 19.270833 | AQ62: =X62*(AJ62+AL62) -> 18.5 | AR62: =Z62/24 -> 125 | AS62: =AA62/12 -> 41.666667 | AT62: =AB62/12 -> 54.166667 | AU62: =AC62/12 -> 208.33333 | AV62: =AE62*AJ62/36 -> 0 | AW62: =AG62/36 -> 8.3333333 | AX62: =AH62/36 -> 55.555556 | AY62: =SUM(AJ62:AX62) -> 1644.3681
C63: Manual | G63: Helper | H63: 34 | I63: 30850 | J63: 907.35294 | K63: 5500 | L63: 550 | M63: 0 | N63: 0 | O63: 0 | P63: 0 | Q63: 250 | R63: 0 | T63: 1 | U63: 0 | V63: 0.5 | X63: 0.02 | Z63: =IF($J63>=5000,6000,3000) -> 3000 | AA63: =IF($J63>=5000,2650,500) -> 500 | AB63: 650 | AC63: 2500 | AE63: 0 | AG63: 300 | AH63: 2000 | AJ63: =J63 -> 907.35294 | AK63: =M63 -> 0 | AL63: =P63*J63/12 -> 0 | AM63: =Q63 -> 250 | AN63: =T63*J63/24 -> 37.806373 | AO63: =U63*J63/12 -> 0 | AP63: =V63*J63/24 -> 18.903186 | AQ63: =X63*(AJ63+AL63) -> 18.147059 | AR63: =Z63/24 -> 125 | AS63: =AA63/12 -> 41.666667 | AT63: =AB63/12 -> 54.166667 | AU63: =AC63/12 -> 208.33333 | AV63: =AE63*AJ63/36 -> 0 | AW63: =AG63/36 -> 8.3333333 | AX63: =AH63/36 -> 55.555556 | AY63: =SUM(AJ63:AX63) -> 1725.2651
C64: Manual | E64: Concrete | F64: Concrete Form | G64: Helper Carpenter | H64: 10 | I64: 7350 | J64: 735 | K64: 850 | L64: 650 | M64: 0 | N64: 0 | O64: 0 | P64: 0 | Q64: 150 | R64: 150 | T64: 1 | U64: 0 | V64: 0.5 | X64: 0.02 | Z64: =IF($J64>=5000,6000,3000) -> 3000 | AA64: =IF($J64>=5000,2650,500) -> 500 | AB64: 650 | AC64: 2500 | AE64: 0 | AG64: 300 | AH64: 2000 | AJ64: =J64 -> 735 | AK64: =M64 -> 0 | AL64: =P64*J64/12 -> 0 | AM64: =Q64 -> 150 | AN64: =T64*J64/24 -> 30.625 | AO64: =U64*J64/12 -> 0 | AP64: =V64*J64/24 -> 15.3125 | AQ64: =X64*(AJ64+AL64) -> 14.7 | AR64: =Z64/24 -> 125 | AS64: =AA64/12 -> 41.666667 | AT64: =AB64/12 -> 54.166667 | AU64: =AC64/12 -> 208.33333 | AV64: =AE64*AJ64/36 -> 0 | AW64: =AG64/36 -> 8.3333333 | AX64: =AH64/36 -> 55.555556 | AY64: =SUM(AJ64:AX64) -> 1438.6931
C65: Manual | E65: Electrical | F65: Electrical | G65: Helper Electrician | H65: 9 | I65: 7440 | J65: 826.66667 | K65: 1355 | L65: 530 | M65: 0 | N65: 0 | O65: 0 | P65: 0 | Q65: 250 | R65: 0 | T65: 1 | U65: 0 | V65: 0.5 | X65: 0.02 | Z65: =IF($J65>=5000,6000,3000) -> 3000 | AA65: =IF($J65>=5000,2650,500) -> 500 | AB65: 650 | AC65: 2500 | AE65: 0 | AG65: 300 | AH65: 2000 | AJ65: =J65 -> 826.66667 | AK65: =M65 -> 0 | AL65: =P65*J65/12 -> 0 | AM65: =Q65 -> 250 | AN65: =T65*J65/24 -> 34.444444 | AO65: =U65*J65/12 -> 0 | AP65: =V65*J65/24 -> 17.222222 | AQ65: =X65*(AJ65+AL65) -> 16.533333 | AR65: =Z65/24 -> 125 | AS65: =AA65/12 -> 41.666667 | AT65: =AB65/12 -> 54.166667 | AU65: =AC65/12 -> 208.33333 | AV65: =AE65*AJ65/36 -> 0 | AW65: =AG65/36 -> 8.3333333 | AX65: =AH65/36 -> 55.555556 | AY65: =SUM(AJ65:AX65) -> 1637.9222
C66: Manual | E66: HVAC | F66: HVAC | G66: Helper HVAC | H66: 1 | I66: 1300 | J66: 1300 | K66: 1300 | L66: 1300 | M66: 0 | N66: 0 | O66: 0 | P66: 0 | Q66: 150 | R66: 150 | T66: 1 | U66: 0 | V66: 0.5 | X66: 0.02 | Z66: =IF($J66>=5000,6000,3000) -> 3000 | AA66: =IF($J66>=5000,2650,500) -> 500 | AB66: 650 | AC66: 2500 | AE66: 0 | AG66: 300 | AH66: 2000 | AJ66: =J66 -> 1300 | AK66: =M66 -> 0 | AL66: =P66*J66/12 -> 0 | AM66: =Q66 -> 150 | AN66: =T66*J66/24 -> 54.166667 | AO66: =U66*J66/12 -> 0 | AP66: =V66*J66/24 -> 27.083333 | AQ66: =X66*(AJ66+AL66) -> 26 | AR66: =Z66/24 -> 125 | AS66: =AA66/12 -> 41.666667 | AT66: =AB66/12 -> 54.166667 | AU66: =AC66/12 -> 208.33333 | AV66: =AE66*AJ66/36 -> 0 | AW66: =AG66/36 -> 8.3333333 | AX66: =AH66/36 -> 55.555556 | AY66: =SUM(AJ66:AX66) -> 2050.3056
C67: Manual | E67: Block Work | F67: Block Work | G67: Helper Mason | H67: 21 | I67: 15091 | J67: 718.61905 | K67: 956 | L67: 550 | M67: 0 | N67: 0 | O67: 0 | P67: 0 | Q67: 250 | R67: 120 | T67: 1 | U67: 0 | V67: 0.5 | X67: 0.02 | Z67: =IF($J67>=5000,6000,3000) -> 3000 | AA67: =IF($J67>=5000,2650,500) -> 500 | AB67: 650 | AC67: 2500 | AE67: 0 | AG67: 300 | AH67: 2000 | AJ67: =J67 -> 718.61905 | AK67: =M67 -> 0 | AL67: =P67*J67/12 -> 0 | AM67: =Q67 -> 250 | AN67: =T67*J67/24 -> 29.94246 | AO67: =U67*J67/12 -> 0 | AP67: =V67*J67/24 -> 14.97123 | AQ67: =X67*(AJ67+AL67) -> 14.372381 | AR67: =Z67/24 -> 125 | AS67: =AA67/12 -> 41.666667 | AT67: =AB67/12 -> 54.166667 | AU67: =AC67/12 -> 208.33333 | AV67: =AE67*AJ67/36 -> 0 | AW67: =AG67/36 -> 8.3333333 | AX67: =AH67/36 -> 55.555556 | AY67: =SUM(AJ67:AX67) -> 1520.9607
C68: Manual | E68: Work Shop | F68: Maintenance | G68: Helper Mechanic | H68: 71 | I68: 77695 | J68: 1094.2958 | K68: 3500 | L68: 700 | M68: 300 | N68: 0 | O68: 0 | P68: 0 | Q68: 200 | R68: 0 | T68: 1 | U68: 0 | V68: 0.5 | X68: 0.02 | Z68: =IF($J68>=5000,6000,3000) -> 3000 | AA68: =IF($J68>=5000,2650,500) -> 500 | AB68: 650 | AC68: 2500 | AE68: 0 | AG68: 300 | AH68: 2000 | AJ68: =J68 -> 1094.2958 | AK68: =M68 -> 300 | AL68: =P68*J68/12 -> 0 | AM68: =Q68 -> 200 | AN68: =T68*J68/24 -> 45.595657 | AO68: =U68*J68/12 -> 0 | AP68: =V68*J68/24 -> 22.797829 | AQ68: =X68*(AJ68+AL68) -> 21.885915 | AR68: =Z68/24 -> 125 | AS68: =AA68/12 -> 41.666667 | AT68: =AB68/12 -> 54.166667 | AU68: =AC68/12 -> 208.33333 | AV68: =AE68*AJ68/36 -> 0 | AW68: =AG68/36 -> 8.3333333 | AX68: =AH68/36 -> 55.555556 | AY68: =SUM(AJ68:AX68) -> 2177.6307
C69: Manual | E69: Finishing | F69: Painting | G69: Helper Painter | H69: 5 | I69: 3250 | J69: 650 | K69: 650 | L69: 650 | M69: 0 | N69: 0 | O69: 0 | P69: 0 | Q69: 150 | R69: 150 | T69: 1 | U69: 0 | V69: 0.5 | X69: 0.02 | Z69: =IF($J69>=5000,6000,3000) -> 3000 | AA69: =IF($J69>=5000,2650,500) -> 500 | AB69: 650 | AC69: 2500 | AE69: 0 | AG69: 300 | AH69: 2000 | AJ69: =J69 -> 650 | AK69: =M69 -> 0 | AL69: =P69*J69/12 -> 0 | AM69: =Q69 -> 150 | AN69: =T69*J69/24 -> 27.083333 | AO69: =U69*J69/12 -> 0 | AP69: =V69*J69/24 -> 13.541667 | AQ69: =X69*(AJ69+AL69) -> 13 | AR69: =Z69/24 -> 125 | AS69: =AA69/12 -> 41.666667 | AT69: =AB69/12 -> 54.166667 | AU69: =AC69/12 -> 208.33333 | AV69: =AE69*AJ69/36 -> 0 | AW69: =AG69/36 -> 8.3333333 | AX69: =AH69/36 -> 55.555556 | AY69: =SUM(AJ69:AX69) -> 1346.6806
C70: Manual | E70: Plumbing | F70: Sewage | G70: Helper Pipe Fitter | H70: 8 | I70: 6000 | J70: 750 | K70: 850 | L70: 650 | M70: 0 | N70: 0 | O70: 0 | P70: 0 | Q70: 150 | R70: 150 | T70: 1 | U70: 0 | V70: 0.5 | X70: 0.02 | Z70: =IF($J70>=5000,6000,3000) -> 3000 | AA70: =IF($J70>=5000,2650,500) -> 500 | AB70: 650 | AC70: 2500 | AE70: 0 | AG70: 300 | AH70: 2000 | AJ70: =J70 -> 750 | AK70: =M70 -> 0 | AL70: =P70*J70/12 -> 0 | AM70: =Q70 -> 150 | AN70: =T70*J70/24 -> 31.25 | AO70: =U70*J70/12 -> 0 | AP70: =V70*J70/24 -> 15.625 | AQ70: =X70*(AJ70+AL70) -> 15 | AR70: =Z70/24 -> 125 | AS70: =AA70/12 -> 41.666667 | AT70: =AB70/12 -> 54.166667 | AU70: =AC70/12 -> 208.33333 | AV70: =AE70*AJ70/36 -> 0 | AW70: =AG70/36 -> 8.3333333 | AX70: =AH70/36 -> 55.555556 | AY70: =SUM(AJ70:AX70) -> 1454.9306
C71: Manual | E71: Concrete | F71: Reinforcement | G71: Helper Steel fixer | H71: 2 | I71: 1500 | J71: 750 | K71: 800 | L71: 700 | M71: 0 | N71: 0 | O71: 0 | P71: 0 | Q71: 150 | R71: 150 | T71: 1 | U71: 0 | V71: 0.5 | X71: 0.02 | Z71: =IF($J71>=5000,6000,3000) -> 3000 | AA71: =IF($J71>=5000,2650,500) -> 500 | AB71: 650 | AC71: 2500 | AE71: 0 | AG71: 300 | AH71: 2000 | AJ71: =J71 -> 750 | AK71: =M71 -> 0 | AL71: =P71*J71/12 -> 0 | AM71: =Q71 -> 150 | AN71: =T71*J71/24 -> 31.25 | AO71: =U71*J71/12 -> 0 | AP71: =V71*J71/24 -> 15.625 | AQ71: =X71*(AJ71+AL71) -> 15 | AR71: =Z71/24 -> 125 | AS71: =AA71/12 -> 41.666667 | AT71: =AB71/12 -> 54.166667 | AU71: =AC71/12 -> 208.33333 | AV71: =AE71*AJ71/36 -> 0 | AW71: =AG71/36 -> 8.3333333 | AX71: =AH71/36 -> 55.555556 | AY71: =SUM(AJ71:AX71) -> 1454.9306
C72: Manual | E72: Miscelainious | F72: Surveying | G72: Helper Surveyor | H72: 8 | I72: 7075 | J72: 884.375 | K72: 1150 | L72: 575 | M72: 0 | N72: 0 | O72: 0 | P72: 0 | Q72: 150 | R72: 150 | T72: 1 | U72: 0 | V72: 0.5 | X72: 0.02 | Z72: =IF($J72>=5000,6000,3000) -> 3000 | AA72: =IF($J72>=5000,2650,500) -> 500 | AB72: 650 | AC72: 2500 | AE72: 0 | AG72: 300 | AH72: 2000 | AJ72: =J72 -> 884.375 | AK72: =M72 -> 0 | AL72: =P72*J72/12 -> 0 | AM72: =Q72 -> 150 | AN72: =T72*J72/24 -> 36.848958 | AO72: =U72*J72/12 -> 0 | AP72: =V72*J72/24 -> 18.424479 | AQ72: =X72*(AJ72+AL72) -> 17.6875 | AR72: =Z72/24 -> 125 | AS72: =AA72/12 -> 41.666667 | AT72: =AB72/12 -> 54.166667 | AU72: =AC72/12 -> 208.33333 | AV72: =AE72*AJ72/36 -> 0 | AW72: =AG72/36 -> 8.3333333 | AX72: =AH72/36 -> 55.555556 | AY72: =SUM(AJ72:AX72) -> 1600.3915
C73: Manual | G73: Helper Technical | H73: 2 | I73: 6000 | J73: 3000 | K73: 3000 | L73: 3000 | M73: 300 | N73: 300 | O73: 0 | P73: 0 | Q73: 0 | R73: 0 | T73: 1 | U73: 0 | V73: 0.5 | X73: 0.02 | Z73: =IF($J73>=5000,6000,3000) -> 3000 | AA73: =IF($J73>=5000,2650,500) -> 500 | AB73: 650 | AC73: 2500 | AE73: 0 | AG73: 300 | AH73: 2000 | AJ73: =J73 -> 3000 | AK73: =M73 -> 300 | AL73: =P73*J73/12 -> 0 | AM73: =Q73 -> 0 | AN73: =T73*J73/24 -> 125 | AO73: =U73*J73/12 -> 0 | AP73: =V73*J73/24 -> 62.5 | AQ73: =X73*(AJ73+AL73) -> 60 | AR73: =Z73/24 -> 125 | AS73: =AA73/12 -> 41.666667 | AT73: =AB73/12 -> 54.166667 | AU73: =AC73/12 -> 208.33333 | AV73: =AE73*AJ73/36 -> 0 | AW73: =AG73/36 -> 8.3333333 | AX73: =AH73/36 -> 55.555556 | AY73: =SUM(AJ73:AX73) -> 4040.5556
C74: Manual | E74: Work Shop | F74: Welding | G74: Helper Welder | H74: 3 | I74: 2200 | J74: 733.33333 | K74: 900 | L74: 650 | M74: 0 | N74: 0 | O74: 0 | P74: 0 | Q74: 150 | R74: 150 | T74: 1 | U74: 0 | V74: 0.5 | X74: 0.02 | Z74: =IF($J74>=5000,6000,3000) -> 3000 | AA74: =IF($J74>=5000,2650,500) -> 500 | AB74: 650 | AC74: 2500 | AE74: 0 | AG74: 300 | AH74: 2000 | AJ74: =J74 -> 733.33333 | AK74: =M74 -> 0 | AL74: =P74*J74/12 -> 0 | AM74: =Q74 -> 150 | AN74: =T74*J74/24 -> 30.555556 | AO74: =U74*J74/12 -> 0 | AP74: =V74*J74/24 -> 15.277778 | AQ74: =X74*(AJ74+AL74) -> 14.666667 | AR74: =Z74/24 -> 125 | AS74: =AA74/12 -> 41.666667 | AT74: =AB74/12 -> 54.166667 | AU74: =AC74/12 -> 208.33333 | AV74: =AE74*AJ74/36 -> 0 | AW74: =AG74/36 -> 8.3333333 | AX74: =AH74/36 -> 55.555556 | AY74: =SUM(AJ74:AX74) -> 1436.8889
C75: Manual | E75: Miscelainious | F75: site | G75: Insect Spray Specialist | H75: 4 | I75: 10045 | J75: 2511.25 | K75: 3500 | L75: 1250 | M75: 0 | N75: 0 | O75: 3 | P75: 3 | Q75: 250 | R75: 0 | T75: 1 | U75: 0 | V75: 0.5 | X75: 0.02 | Z75: =IF($J75>=5000,6000,3000) -> 3000 | AA75: =IF($J75>=5000,2650,500) -> 500 | AB75: 650 | AC75: 2500 | AE75: 0 | AG75: 300 | AH75: 2000 | AJ75: =J75 -> 2511.25 | AK75: =M75 -> 0 | AL75: =P75*J75/12 -> 627.8125 | AM75: =Q75 -> 250 | AN75: =T75*J75/24 -> 104.63542 | AO75: =U75*J75/12 -> 0 | AP75: =V75*J75/24 -> 52.317708 | AQ75: =X75*(AJ75+AL75) -> 62.78125 | AR75: =Z75/24 -> 125 | AS75: =AA75/12 -> 41.666667 | AT75: =AB75/12 -> 54.166667 | AU75: =AC75/12 -> 208.33333 | AV75: =AE75*AJ75/36 -> 0 | AW75: =AG75/36 -> 8.3333333 | AX75: =AH75/36 -> 55.555556 | AY75: =SUM(AJ75:AX75) -> 4101.8524
C76: Manual | E76: HVAC | F76: HVAC | G76: Insulator | H76: 33 | I76: 34850 | J76: 1056.0606 | K76: 1500 | L76: 700 | M76: 0 | N76: 0 | O76: 0 | P76: 0 | Q76: 150 | R76: 150 | T76: 1 | U76: 0 | V76: 0.5 | X76: 0.02 | Z76: =IF($J76>=5000,6000,3000) -> 3000 | AA76: =IF($J76>=5000,2650,500) -> 500 | AB76: 650 | AC76: 2500 | AE76: 0 | AG76: 300 | AH76: 2000 | AJ76: =J76 -> 1056.0606 | AK76: =M76 -> 0 | AL76: =P76*J76/12 -> 0 | AM76: =Q76 -> 150 | AN76: =T76*J76/24 -> 44.002525 | AO76: =U76*J76/12 -> 0 | AP76: =V76*J76/24 -> 22.001263 | AQ76: =X76*(AJ76+AL76) -> 21.121212 | AR76: =Z76/24 -> 125 | AS76: =AA76/12 -> 41.666667 | AT76: =AB76/12 -> 54.166667 | AU76: =AC76/12 -> 208.33333 | AV76: =AE76*AJ76/36 -> 0 | AW76: =AG76/36 -> 8.3333333 | AX76: =AH76/36 -> 55.555556 | AY76: =SUM(AJ76:AX76) -> 1786.2412
C77: Manual | E77: Miscelainious | F77: site | G77: Labour | H77: 1733 | I77: 1111374 | J77: 641.30063 | K77: 5500 | L77: 200 | M77: 300 | N77: 0 | O77: 0 | P77: 0 | Q77: 250 | R77: 0 | T77: 1 | U77: 0 | V77: 0.5 | X77: 0.02 | Z77: =IF($J77>=5000,6000,3000) -> 3000 | AA77: =IF($J77>=5000,2650,500) -> 500 | AB77: 650 | AC77: 2500 | AE77: 0 | AG77: 300 | AH77: 2000 | AJ77: =J77 -> 641.30063 | AK77: =M77 -> 300 | AL77: =P77*J77/12 -> 0 | AM77: =Q77 -> 250 | AN77: =T77*J77/24 -> 26.72086 | AO77: =U77*J77/12 -> 0 | AP77: =V77*J77/24 -> 13.36043 | AQ77: =X77*(AJ77+AL77) -> 12.826013 | AR77: =Z77/24 -> 125 | AS77: =AA77/12 -> 41.666667 | AT77: =AB77/12 -> 54.166667 | AU77: =AC77/12 -> 208.33333 | AV77: =AE77*AJ77/36 -> 0 | AW77: =AG77/36 -> 8.3333333 | AX77: =AH77/36 -> 55.555556 | AY77: =SUM(AJ77:AX77) -> 1737.2635
C78: Manual | E78: Cleaning | F78: Cleaning | G78: Labour Cleaning | H78: 4753 | I78: 1607467 | J78: 338.2005 | K78: 1600 | L78: 200 | M78: 300 | N78: 0 | O78: 0 | P78: 0 | Q78: 250 | R78: 0 | T78: 1 | U78: 0 | V78: 0.5 | X78: 0.02 | Z78: =IF($J78>=5000,6000,3000) -> 3000 | AA78: =IF($J78>=5000,2650,500) -> 500 | AB78: 650 | AC78: 2500 | AE78: 0 | AG78: 300 | AH78: 2000 | AJ78: =J78 -> 338.2005 | AK78: =M78 -> 300 | AL78: =P78*J78/12 -> 0 | AM78: =Q78 -> 250 | AN78: =T78*J78/24 -> 14.091688 | AO78: =U78*J78/12 -> 0 | AP78: =V78*J78/24 -> 7.0458439 | AQ78: =X78*(AJ78+AL78) -> 6.7640101 | AR78: =Z78/24 -> 125 | AS78: =AA78/12 -> 41.666667 | AT78: =AB78/12 -> 54.166667 | AU78: =AC78/12 -> 208.33333 | AV78: =AE78*AJ78/36 -> 0 | AW78: =AG78/36 -> 8.3333333 | AX78: =AH78/36 -> 55.555556 | AY78: =SUM(AJ78:AX78) -> 1409.1576
C79: Manual | E79: Work Shop | F79: Maintenance | G79: Labour Workshop | H79: 1 | I79: 490 | J79: 490 | K79: 490 | L79: 490 | M79: 0 | N79: 0 | O79: 0 | P79: 0 | Q79: 150 | R79: 150 | T79: 1 | U79: 0 | V79: 0.5 | X79: 0.02 | Z79: =IF($J79>=5000,6000,3000) -> 3000 | AA79: =IF($J79>=5000,2650,500) -> 500 | AB79: 650 | AC79: 2500 | AE79: 0 | AG79: 300 | AH79: 2000 | AJ79: =J79 -> 490 | AK79: =M79 -> 0 | AL79: =P79*J79/12 -> 0 | AM79: =Q79 -> 150 | AN79: =T79*J79/24 -> 20.416667 | AO79: =U79*J79/12 -> 0 | AP79: =V79*J79/24 -> 10.208333 | AQ79: =X79*(AJ79+AL79) -> 9.8 | AR79: =Z79/24 -> 125 | AS79: =AA79/12 -> 41.666667 | AT79: =AB79/12 -> 54.166667 | AU79: =AC79/12 -> 208.33333 | AV79: =AE79*AJ79/36 -> 0 | AW79: =AG79/36 -> 8.3333333 | AX79: =AH79/36 -> 55.555556 | AY79: =SUM(AJ79:AX79) -> 1173.4806
C80: Manual | E80: Concrete | F80: Concrete Form | G80: Lead Man Carpenter | H80: 90 | I80: 112625 | J80: 1251.3889 | K80: 1700 | L80: 1000 | M80: 0 | N80: 0 | O80: 0 | P80: 0 | Q80: 150 | R80: 120 | T80: 1 | U80: 0 | V80: 0.5 | X80: 0.02 | Z80: =IF($J80>=5000,6000,3000) -> 3000 | AA80: =IF($J80>=5000,2650,500) -> 500 | AB80: 650 | AC80: 2500 | AE80: 0 | AG80: 300 | AH80: 2000 | AJ80: =J80 -> 1251.3889 | AK80: =M80 -> 0 | AL80: =P80*J80/12 -> 0 | AM80: =Q80 -> 150 | AN80: =T80*J80/24 -> 52.141204 | AO80: =U80*J80/12 -> 0 | AP80: =V80*J80/24 -> 26.070602 | AQ80: =X80*(AJ80+AL80) -> 25.027778 | AR80: =Z80/24 -> 125 | AS80: =AA80/12 -> 41.666667 | AT80: =AB80/12 -> 54.166667 | AU80: =AC80/12 -> 208.33333 | AV80: =AE80*AJ80/36 -> 0 | AW80: =AG80/36 -> 8.3333333 | AX80: =AH80/36 -> 55.555556 | AY80: =SUM(AJ80:AX80) -> 1997.684
C81: Manual | E81: Block Work | F81: Block Work | G81: Lead Man Mason | H81: 55 | I81: 69690 | J81: 1267.0909 | K81: 1650 | L81: 1100 | Q81: 250 | R81: 120 | T81: 1 | U81: 0 | V81: 0.5 | X81: 0.02 | Z81: =IF($J81>=5000,6000,3000) -> 3000 | AA81: =IF($J81>=5000,2650,500) -> 500 | AB81: 650 | AC81: 2500 | AE81: 0 | AG81: 300 | AH81: 2000 | AJ81: =J81 -> 1267.0909 | AK81: =M81 -> 0 | AL81: =P81*J81/12 -> 0 | AM81: =Q81 -> 250 | AN81: =T81*J81/24 -> 52.795455 | AO81: =U81*J81/12 -> 0 | AP81: =V81*J81/24 -> 26.397727 | AQ81: =X81*(AJ81+AL81) -> 25.341818 | AR81: =Z81/24 -> 125 | AS81: =AA81/12 -> 41.666667 | AT81: =AB81/12 -> 54.166667 | AU81: =AC81/12 -> 208.33333 | AV81: =AE81*AJ81/36 -> 0 | AW81: =AG81/36 -> 8.3333333 | AX81: =AH81/36 -> 55.555556 | AY81: =SUM(AJ81:AX81) -> 2114.6815
C82: Manual | E82: Concrete | F82: Reinforcement | G82: Lead Man Steel Fixer | H82: 67 | I82: 81000 | J82: 1208.9552 | K82: 2350 | L82: 800 | M82: 0 | N82: 0 | O82: 0 | P82: 0 | Q82: 150 | R82: 0 | T82: 1 | U82: 0 | V82: 0.5 | X82: 0.02 | Z82: =IF($J82>=5000,6000,3000) -> 3000 | AA82: =IF($J82>=5000,2650,500) -> 500 | AB82: 650 | AC82: 2500 | AE82: 0 | AG82: 300 | AH82: 2000 | AJ82: =J82 -> 1208.9552 | AK82: =M82 -> 0 | AL82: =P82*J82/12 -> 0 | AM82: =Q82 -> 150 | AN82: =T82*J82/24 -> 50.373134 | AO82: =U82*J82/12 -> 0 | AP82: =V82*J82/24 -> 25.186567 | AQ82: =X82*(AJ82+AL82) -> 24.179104 | AR82: =Z82/24 -> 125 | AS82: =AA82/12 -> 41.666667 | AT82: =AB82/12 -> 54.166667 | AU82: =AC82/12 -> 208.33333 | AV82: =AE82*AJ82/36 -> 0 | AW82: =AG82/36 -> 8.3333333 | AX82: =AH82/36 -> 55.555556 | AY82: =SUM(AJ82:AX82) -> 1951.7496
C83: Manual | E83: Miscelainious | F83: Site | G83: Leadman | H83: 36 | I83: 65920 | J83: 1831.1111 | K83: 3000 | L83: 1000 | M83: 300 | N83: 0 | O83: 0 | P83: 0 | Q83: 150 | R83: 0 | T83: 1 | U83: 0 | V83: 0.5 | X83: 0.02 | Z83: =IF($J83>=5000,6000,3000) -> 3000 | AA83: =IF($J83>=5000,2650,500) -> 500 | AB83: 650 | AC83: 2500 | AE83: 0 | AG83: 300 | AH83: 2000 | AJ83: =J83 -> 1831.1111 | AK83: =M83 -> 300 | AL83: =P83*J83/12 -> 0 | AM83: =Q83 -> 150 | AN83: =T83*J83/24 -> 76.296296 | AO83: =U83*J83/12 -> 0 | AP83: =V83*J83/24 -> 38.148148 | AQ83: =X83*(AJ83+AL83) -> 36.622222 | AR83: =Z83/24 -> 125 | AS83: =AA83/12 -> 41.666667 | AT83: =AB83/12 -> 54.166667 | AU83: =AC83/12 -> 208.33333 | AV83: =AE83*AJ83/36 -> 0 | AW83: =AG83/36 -> 8.3333333 | AX83: =AH83/36 -> 55.555556 | AY83: =SUM(AJ83:AX83) -> 2925.2333
C84: Manual | E84: HVAC | F84: HVAC | G84: Leadman Duct | H84: 6 | I84: 9000 | J84: 1500 | K84: 1600 | L84: 1400 | M84: 0 | N84: 0 | O84: 0 | P84: 0 | Q84: 150 | R84: 150 | T84: 1 | U84: 0 | V84: 0.5 | X84: 0.02 | Z84: =IF($J84>=5000,6000,3000) -> 3000 | AA84: =IF($J84>=5000,2650,500) -> 500 | AB84: 650 | AC84: 2500 | AE84: 0 | AG84: 300 | AH84: 2000 | AJ84: =J84 -> 1500 | AK84: =M84 -> 0 | AL84: =P84*J84/12 -> 0 | AM84: =Q84 -> 150 | AN84: =T84*J84/24 -> 62.5 | AO84: =U84*J84/12 -> 0 | AP84: =V84*J84/24 -> 31.25 | AQ84: =X84*(AJ84+AL84) -> 30 | AR84: =Z84/24 -> 125 | AS84: =AA84/12 -> 41.666667 | AT84: =AB84/12 -> 54.166667 | AU84: =AC84/12 -> 208.33333 | AV84: =AE84*AJ84/36 -> 0 | AW84: =AG84/36 -> 8.3333333 | AX84: =AH84/36 -> 55.555556 | AY84: =SUM(AJ84:AX84) -> 2266.8056
C85: Manual | E85: Electrical | F85: Electrical | G85: Leadman Electrician | H85: 3 | I85: 3900 | J85: 1300 | K85: 1400 | L85: 1200 | M85: 0 | N85: 0 | O85: 0 | P85: 0 | Q85: 150 | R85: 150 | T85: 1 | U85: 0 | V85: 0.5 | X85: 0.02 | Z85: =IF($J85>=5000,6000,3000) -> 3000 | AA85: =IF($J85>=5000,2650,500) -> 500 | AB85: 650 | AC85: 2500 | AE85: 0 | AG85: 300 | AH85: 2000 | AJ85: =J85 -> 1300 | AK85: =M85 -> 0 | AL85: =P85*J85/12 -> 0 | AM85: =Q85 -> 150 | AN85: =T85*J85/24 -> 54.166667 | AO85: =U85*J85/12 -> 0 | AP85: =V85*J85/24 -> 27.083333 | AQ85: =X85*(AJ85+AL85) -> 26 | AR85: =Z85/24 -> 125 | AS85: =AA85/12 -> 41.666667 | AT85: =AB85/12 -> 54.166667 | AU85: =AC85/12 -> 208.33333 | AV85: =AE85*AJ85/36 -> 0 | AW85: =AG85/36 -> 8.3333333 | AX85: =AH85/36 -> 55.555556 | AY85: =SUM(AJ85:AX85) -> 2050.3056
C86: Manual | E86: Miscelainious | F86: Site | G86: Leadman Labour | H86: 6 | I86: 6599 | J86: 1099.8333 | K86: 1400 | L86: 820 | M86: 0 | N86: 0 | O86: 0 | P86: 0 | Q86: 150 | R86: 150 | T86: 1 | U86: 0 | V86: 0.5 | X86: 0.02 | Z86: =IF($J86>=5000,6000,3000) -> 3000 | AA86: =IF($J86>=5000,2650,500) -> 500 | AB86: 650 | AC86: 2500 | AE86: 0 | AG86: 300 | AH86: 2000 | AJ86: =J86 -> 1099.8333 | AK86: =M86 -> 0 | AL86: =P86*J86/12 -> 0 | AM86: =Q86 -> 150 | AN86: =T86*J86/24 -> 45.826389 | AO86: =U86*J86/12 -> 0 | AP86: =V86*J86/24 -> 22.913194 | AQ86: =X86*(AJ86+AL86) -> 21.996667 | AR86: =Z86/24 -> 125 | AS86: =AA86/12 -> 41.666667 | AT86: =AB86/12 -> 54.166667 | AU86: =AC86/12 -> 208.33333 | AV86: =AE86*AJ86/36 -> 0 | AW86: =AG86/36 -> 8.3333333 | AX86: =AH86/36 -> 55.555556 | AY86: =SUM(AJ86:AX86) -> 1833.6251
C87: Manual | E87: Finishing | F87: Painting | G87: Leadman Painter | H87: 18 | I87: 22310 | J87: 1239.4444 | K87: 1500 | L87: 900 | M87: 0 | N87: 0 | O87: 0 | P87: 0 | Q87: 150 | R87: 120 | T87: 1 | U87: 0 | V87: 0.5 | X87: 0.02 | Z87: =IF($J87>=5000,6000,3000) -> 3000 | AA87: =IF($J87>=5000,2650,500) -> 500 | AB87: 650 | AC87: 2500 | AE87: 0 | AG87: 300 | AH87: 2000 | AJ87: =J87 -> 1239.4444 | AK87: =M87 -> 0 | AL87: =P87*J87/12 -> 0 | AM87: =Q87 -> 150 | AN87: =T87*J87/24 -> 51.643519 | AO87: =U87*J87/12 -> 0 | AP87: =V87*J87/24 -> 25.821759 | AQ87: =X87*(AJ87+AL87) -> 24.788889 | AR87: =Z87/24 -> 125 | AS87: =AA87/12 -> 41.666667 | AT87: =AB87/12 -> 54.166667 | AU87: =AC87/12 -> 208.33333 | AV87: =AE87*AJ87/36 -> 0 | AW87: =AG87/36 -> 8.3333333 | AX87: =AH87/36 -> 55.555556 | AY87: =SUM(AJ87:AX87) -> 1984.7542
C88: Manual | E88: Plumbing | F88: Building Plumbing | G88: Leadman Plumber | H88: 43 | I88: 61300 | J88: 1425.5814 | K88: 2700 | L88: 1100 | M88: 0 | N88: 0 | O88: 0 | P88: 0 | Q88: 200 | R88: 0 | T88: 1 | U88: 0 | V88: 0.5 | X88: 0.02 | Z88: =IF($J88>=5000,6000,3000) -> 3000 | AA88: =IF($J88>=5000,2650,500) -> 500 | AB88: 650 | AC88: 2500 | AE88: 0 | AG88: 300 | AH88: 2000 | AJ88: =J88 -> 1425.5814 | AK88: =M88 -> 0 | AL88: =P88*J88/12 -> 0 | AM88: =Q88 -> 200 | AN88: =T88*J88/24 -> 59.399225 | AO88: =U88*J88/12 -> 0 | AP88: =V88*J88/24 -> 29.699612 | AQ88: =X88*(AJ88+AL88) -> 28.511628 | AR88: =Z88/24 -> 125 | AS88: =AA88/12 -> 41.666667 | AT88: =AB88/12 -> 54.166667 | AU88: =AC88/12 -> 208.33333 | AV88: =AE88*AJ88/36 -> 0 | AW88: =AG88/36 -> 8.3333333 | AX88: =AH88/36 -> 55.555556 | AY88: =SUM(AJ88:AX88) -> 2236.2474
C89: Manual | E89: Work Shop | F89: Welding | G89: Leadman Welder | H89: 1 | I89: 1450 | J89: 1450 | K89: 1450 | L89: 1450 | M89: 0 | N89: 0 | O89: 0 | P89: 0 | Q89: 150 | R89: 150 | T89: 1 | U89: 0 | V89: 0.5 | X89: 0.02 | Z89: =IF($J89>=5000,6000,3000) -> 3000 | AA89: =IF($J89>=5000,2650,500) -> 500 | AB89: 650 | AC89: 2500 | AE89: 0 | AG89: 300 | AH89: 2000 | AJ89: =J89 -> 1450 | AK89: =M89 -> 0 | AL89: =P89*J89/12 -> 0 | AM89: =Q89 -> 150 | AN89: =T89*J89/24 -> 60.416667 | AO89: =U89*J89/12 -> 0 | AP89: =V89*J89/24 -> 30.208333 | AQ89: =X89*(AJ89+AL89) -> 29 | AR89: =Z89/24 -> 125 | AS89: =AA89/12 -> 41.666667 | AT89: =AB89/12 -> 54.166667 | AU89: =AC89/12 -> 208.33333 | AV89: =AE89*AJ89/36 -> 0 | AW89: =AG89/36 -> 8.3333333 | AX89: =AH89/36 -> 55.555556 | AY89: =SUM(AJ89:AX89) -> 2212.6806
C90: Manual | E90: Work Shop | F90: Maintenance | G90: Maintenance Superintendent | H90: 1 | I90: 3200 | J90: 3200 | K90: 3200 | L90: 3200 | M90: 300 | N90: 300 | O90: 0 | P90: 0 | Q90: 0 | R90: 0 | T90: 1 | U90: 0 | V90: 0.5 | X90: 0.02 | Z90: =IF($J90>=5000,6000,3000) -> 3000 | AA90: =IF($J90>=5000,2650,500) -> 500 | AB90: 650 | AC90: 2500 | AE90: 0 | AG90: 300 | AH90: 2000 | AJ90: =J90 -> 3200 | AK90: =M90 -> 300 | AL90: =P90*J90/12 -> 0 | AM90: =Q90 -> 0 | AN90: =T90*J90/24 -> 133.33333 | AO90: =U90*J90/12 -> 0 | AP90: =V90*J90/24 -> 66.666667 | AQ90: =X90*(AJ90+AL90) -> 64 | AR90: =Z90/24 -> 125 | AS90: =AA90/12 -> 41.666667 | AT90: =AB90/12 -> 54.166667 | AU90: =AC90/12 -> 208.33333 | AV90: =AE90*AJ90/36 -> 0 | AW90: =AG90/36 -> 8.3333333 | AX90: =AH90/36 -> 55.555556 | AY90: =SUM(AJ90:AX90) -> 4257.0556
C91: Manual | E91: Block Work | F91: Block Work | G91: Mason | H91: 705 | I91: 653955 | J91: 927.59574 | K91: 3200 | L91: 550 | M91: 0 | N91: 0 | O91: 0 | P91: 0 | Q91: 250 | R91: 0 | T91: 1 | U91: 0 | V91: 0.5 | X91: 0.02 | Z91: =IF($J91>=5000,6000,3000) -> 3000 | AA91: =IF($J91>=5000,2650,500) -> 500 | AB91: 650 | AC91: 2500 | AE91: 0 | AG91: 300 | AH91: 2000 | AJ91: =J91 -> 927.59574 | AK91: =M91 -> 0 | AL91: =P91*J91/12 -> 0 | AM91: =Q91 -> 250 | AN91: =T91*J91/24 -> 38.649823 | AO91: =U91*J91/12 -> 0 | AP91: =V91*J91/24 -> 19.324911 | AQ91: =X91*(AJ91+AL91) -> 18.551915 | AR91: =Z91/24 -> 125 | AS91: =AA91/12 -> 41.666667 | AT91: =AB91/12 -> 54.166667 | AU91: =AC91/12 -> 208.33333 | AV91: =AE91*AJ91/36 -> 0 | AW91: =AG91/36 -> 8.3333333 | AX91: =AH91/36 -> 55.555556 | AY91: =SUM(AJ91:AX91) -> 1747.1779
C92: Manual | E92: Work Shop | F92: Maintenance | G92: Mechanic | H92: 22 | I92: 49350 | J92: 2243.1818 | K92: 4500 | L92: 800 | M92: 300 | N92: 0 | O92: 0 | P92: 0 | Q92: 150 | R92: 0 | T92: 1 | U92: 0 | V92: 0.5 | X92: 0.02 | Z92: =IF($J92>=5000,6000,3000) -> 3000 | AA92: =IF($J92>=5000,2650,500) -> 500 | AB92: 650 | AC92: 2500 | AE92: 0 | AG92: 300 | AH92: 2000 | AJ92: =J92 -> 2243.1818 | AK92: =M92 -> 300 | AL92: =P92*J92/12 -> 0 | AM92: =Q92 -> 150 | AN92: =T92*J92/24 -> 93.465909 | AO92: =U92*J92/12 -> 0 | AP92: =V92*J92/24 -> 46.732955 | AQ92: =X92*(AJ92+AL92) -> 44.863636 | AR92: =Z92/24 -> 125 | AS92: =AA92/12 -> 41.666667 | AT92: =AB92/12 -> 54.166667 | AU92: =AC92/12 -> 208.33333 | AV92: =AE92*AJ92/36 -> 0 | AW92: =AG92/36 -> 8.3333333 | AX92: =AH92/36 -> 55.555556 | AY92: =SUM(AJ92:AX92) -> 3371.2999
C93: Manual | E93: Work Shop | F93: Maintenance | G93: Mechanic Auto | H93: 7 | I93: 10800 | J93: 1542.8571 | K93: 3000 | L93: 900 | M93: 300 | N93: 0 | O93: 0 | P93: 0 | Q93: 150 | R93: 0 | T93: 1 | U93: 0 | V93: 0.5 | X93: 0.02 | Z93: =IF($J93>=5000,6000,3000) -> 3000 | AA93: =IF($J93>=5000,2650,500) -> 500 | AB93: 650 | AC93: 2500 | AE93: 0 | AG93: 300 | AH93: 2000 | AJ93: =J93 -> 1542.8571 | AK93: =M93 -> 300 | AL93: =P93*J93/12 -> 0 | AM93: =Q93 -> 150 | AN93: =T93*J93/24 -> 64.285714 | AO93: =U93*J93/12 -> 0 | AP93: =V93*J93/24 -> 32.142857 | AQ93: =X93*(AJ93+AL93) -> 30.857143 | AR93: =Z93/24 -> 125 | AS93: =AA93/12 -> 41.666667 | AT93: =AB93/12 -> 54.166667 | AU93: =AC93/12 -> 208.33333 | AV93: =AE93*AJ93/36 -> 0 | AW93: =AG93/36 -> 8.3333333 | AX93: =AH93/36 -> 55.555556 | AY93: =SUM(AJ93:AX93) -> 2613.1984
... C103: Manual | E103: IT | F103: Network | G103: Network Technician | H103: 2 | I103: 5366 | J103: 2683 | K103: 3366 | L103: 2000 | M103: 400 | N103: 300 | O103: 2 | P103: 2 | Q103: 200 | R103: 0 | T103: 1 | U103: 0 | V103: 0.5 | X103: 0.02 | Z103: =IF($J103>=5000,6000,3000) -> 3000 | AA103: =IF($J103>=5000,2650,500) -> 500 | AB103: 650 | AC103: 2500 | AE103: 0 | AG103: 300 | AH103: 2000 | AJ103: =J103 -> 2683 | AK103: =M103 -> 400 | AL103: =P103*J103/12 -> 447.16667 | AM103: =Q103 -> 200 | AN103: =T103*J103/24 -> 111.79167 | AO103: =U103*J103/12 -> 0 | AP103: =V103*J103/24 -> 55.895833 | AQ103: =X103*(AJ103+AL103) -> 62.603333 | AR103: =Z103/24 -> 125 | AS103: =AA103/12 -> 41.666667 | AT103: =AB103/12 -> 54.166667 | AU103: =AC103/12 -> 208.33333 | AV103: =AE103*AJ103/36 -> 0 | AW103: =AG103/36 -> 8.3333333 | AX103: =AH103/36 -> 55.555556 | AY103: =SUM(AJ103:AX103) -> 4453.5131
C104: Manual | D104: cleaning | E104: Work Shop | F104: Maintenance | G104: Oilman | H104: 49 | I104: 49325 | J104: 1006.6327 | K104: 4500 | L104: 460 | Q104: 150 | R104: 0 | T104: 1 | U104: 0 | V104: 0.5 | X104: 0.02 | Z104: =IF($J104>=5000,6000,3000) -> 3000 | AA104: =IF($J104>=5000,2650,500) -> 500 | AB104: 650 | AC104: 2500 | AE104: 0 | AG104: 300 | AH104: 2000 | AJ104: =J104 -> 1006.6327 | AK104: =M104 -> 0 | AL104: =P104*J104/12 -> 0 | AM104: =Q104 -> 150 | AN104: =T104*J104/24 -> 41.943027 | AO104: =U104*J104/12 -> 0 | AP104: =V104*J104/24 -> 20.971514 | AQ104: =X104*(AJ104+AL104) -> 20.132653 | AR104: =Z104/24 -> 125 | AS104: =AA104/12 -> 41.666667 | AT104: =AB104/12 -> 54.166667 | AU104: =AC104/12 -> 208.33333 | AV104: =AE104*AJ104/36 -> 0 | AW104: =AG104/36 -> 8.3333333 | AX104: =AH104/36 -> 55.555556 | AY104: =SUM(AJ104:AX104) -> 1732.7354
C105: Manual | E105: Equipment | F105: Equipment | G105: Operator | H105: 37 | I105: 83770 | J105: 2264.0541 | K105: 11000 | L105: 550 | M105: 800 | N105: 0 | O105: 0 | P105: 0 | Q105: 250 | R105: 0 | T105: 1 | U105: 0 | V105: 0.5 | X105: 0.02 | Z105: =IF($J105>=5000,6000,3000) -> 3000 | AA105: =IF($J105>=5000,2650,500) -> 500 | AB105: 650 | AC105: 2500 | AE105: 0 | AG105: 300 | AH105: 2000 | AJ105: =J105 -> 2264.0541 | AK105: =M105 -> 800 | AL105: =P105*J105/12 -> 0 | AM105: =Q105 -> 250 | AN105: =T105*J105/24 -> 94.335586 | AO105: =U105*J105/12 -> 0 | AP105: =V105*J105/24 -> 47.167793 | AQ105: =X105*(AJ105+AL105) -> 45.281081 | AR105: =Z105/24 -> 125 | AS105: =AA105/12 -> 41.666667 | AT105: =AB105/12 -> 54.166667 | AU105: =AC105/12 -> 208.33333 | AV105: =AE105*AJ105/36 -> 0 | AW105: =AG105/36 -> 8.3333333 | AX105: =AH105/36 -> 55.555556 | AY105: =SUM(AJ105:AX105) -> 3993.8941
C106: Manual | E106: Equipment | F106: Equipment | G106: Operator - Concrete Pump | H106: 5 | I106: 8400 | J106: 1680 | K106: 1800 | L106: 1500 | M106: 0 | N106: 0 | O106: 0 | P106: 0 | Q106: 150 | R106: 150 | T106: 1 | U106: 0 | V106: 0.5 | X106: 0.02 | Z106: =IF($J106>=5000,6000,3000) -> 3000 | AA106: =IF($J106>=5000,2650,500) -> 500 | AB106: 650 | AC106: 2500 | AE106: 0 | AG106: 300 | AH106: 2000 | AJ106: =J106 -> 1680 | AK106: =M106 -> 0 | AL106: =P106*J106/12 -> 0 | AM106: =Q106 -> 150 | AN106: =T106*J106/24 -> 70 | AO106: =U106*J106/12 -> 0 | AP106: =V106*J106/24 -> 35 | AQ106: =X106*(AJ106+AL106) -> 33.6 | AR106: =Z106/24 -> 125 | AS106: =AA106/12 -> 41.666667 | AT106: =AB106/12 -> 54.166667 | AU106: =AC106/12 -> 208.33333 | AV106: =AE106*AJ106/36 -> 0 | AW106: =AG106/36 -> 8.3333333 | AX106: =AH106/36 -> 55.555556 | AY106: =SUM(AJ106:AX106) -> 2461.6556
C107: Manual | E107: Equipment | F107: Equipment | G107: Operator Asphalt | H107: 10 | I107: 19320 | J107: 1932 | K107: 2500 | L107: 1000 | M107: 0 | N107: 0 | O107: 0 | P107: 0 | Q107: 200 | R107: 0 | T107: 1 | U107: 0 | V107: 0.5 | X107: 0.02 | Z107: =IF($J107>=5000,6000,3000) -> 3000 | AA107: =IF($J107>=5000,2650,500) -> 500 | AB107: 650 | AC107: 2500 | AE107: 0 | AG107: 300 | AH107: 2000 | AJ107: =J107 -> 1932 | AK107: =M107 -> 0 | AL107: =P107*J107/12 -> 0 | AM107: =Q107 -> 200 | AN107: =T107*J107/24 -> 80.5 | AO107: =U107*J107/12 -> 0 | AP107: =V107*J107/24 -> 40.25 | AQ107: =X107*(AJ107+AL107) -> 38.64 | AR107: =Z107/24 -> 125 | AS107: =AA107/12 -> 41.666667 | AT107: =AB107/12 -> 54.166667 | AU107: =AC107/12 -> 208.33333 | AV107: =AE107*AJ107/36 -> 0 | AW107: =AG107/36 -> 8.3333333 | AX107: =AH107/36 -> 55.555556 | AY107: =SUM(AJ107:AX107) -> 2784.4456
C108: Manual | E108: Equipment | F108: Equipment | G108: Operator Backhoe | H108: 38 | I108: 45100 | J108: 1186.8421 | K108: 1200 | L108: 1000 | M108: 0 | N108: 0 | O108: 0 | P108: 0 | Q108: 200 | R108: 0 | T108: 1 | U108: 0 | V108: 0.5 | X108: 0.02 | Z108: =IF($J108>=5000,6000,3000) -> 3000 | AA108: =IF($J108>=5000,2650,500) -> 500 | AB108: 650 | AC108: 2500 | AE108: 0 | AG108: 300 | AH108: 2000 | AJ108: =J108 -> 1186.8421 | AK108: =M108 -> 0 | AL108: =P108*J108/12 -> 0 | AM108: =Q108 -> 200 | AN108: =T108*J108/24 -> 49.451754 | AO108: =U108*J108/12 -> 0 | AP108: =V108*J108/24 -> 24.725877 | AQ108: =X108*(AJ108+AL108) -> 23.736842 | AR108: =Z108/24 -> 125 | AS108: =AA108/12 -> 41.666667 | AT108: =AB108/12 -> 54.166667 | AU108: =AC108/12 -> 208.33333 | AV108: =AE108*AJ108/36 -> 0 | AW108: =AG108/36 -> 8.3333333 | AX108: =AH108/36 -> 55.555556 | AY108: =SUM(AJ108:AX108) -> 1977.8121
C109: Manual | D109: Batch Plant | E109: Equipment | F109: Equipment | G109: Operator Batching Plant | H109: 10 | I109: 25500 | J109: 2550 | K109: 3000 | L109: 1500 | M109: 300 | N109: 0 | O109: 2 | P109: 2 | Q109: 150 | R109: 0 | T109: 1 | U109: 0 | V109: 0.5 | X109: 0.02 | Z109: =IF($J109>=5000,6000,3000) -> 3000 | AA109: =IF($J109>=5000,2650,500) -> 500 | AB109: 650 | AC109: 2500 | AE109: 0 | AG109: 300 | AH109: 2000 | AJ109: =J109 -> 2550 | AK109: =M109 -> 300 | AL109: =P109*J109/12 -> 425 | AM109: =Q109 -> 150 | AN109: =T109*J109/24 -> 106.25 | AO109: =U109*J109/12 -> 0 | AP109: =V109*J109/24 -> 53.125 | AQ109: =X109*(AJ109+AL109) -> 59.5 | AR109: =Z109/24 -> 125 | AS109: =AA109/12 -> 41.666667 | AT109: =AB109/12 -> 54.166667 | AU109: =AC109/12 -> 208.33333 | AV109: =AE109*AJ109/36 -> 0 | AW109: =AG109/36 -> 8.3333333 | AX109: =AH109/36 -> 55.555556 | AY109: =SUM(AJ109:AX109) -> 4136.9306
C110: Manual | E110: Equipment | F110: Equipment | G110: Operator Bobcat | H110: 58 | I110: 38075 | J110: 667.98246 | K110: 1100 | L110: 300 | M110: 0 | N110: 0 | O110: 0 | P110: 0 | Q110: 150 | R110: 120 | T110: 1 | U110: 0 | V110: 0.5 | X110: 0.02 | Z110: =IF($J110>=5000,6000,3000) -> 3000 | AA110: =IF($J110>=5000,2650,500) -> 500 | AB110: 650 | AC110: 2500 | AE110: 0 | AG110: 300 | AH110: 2000 | AJ110: =J110 -> 667.98246 | AK110: =M110 -> 0 | AL110: =P110*J110/12 -> 0 | AM110: =Q110 -> 150 | AN110: =T110*J110/24 -> 27.832602 | AO110: =U110*J110/12 -> 0 | AP110: =V110*J110/24 -> 13.916301 | AQ110: =X110*(AJ110+AL110) -> 13.359649 | AR110: =Z110/24 -> 125 | AS110: =AA110/12 -> 41.666667 | AT110: =AB110/12 -> 54.166667 | AU110: =AC110/12 -> 208.33333 | AV110: =AE110*AJ110/36 -> 0 | AW110: =AG110/36 -> 8.3333333 | AX110: =AH110/36 -> 55.555556 | AY110: =SUM(AJ110:AX110) -> 1366.1466
C111: Manual | E111: Equipment | F111: Equipment | G111: Operator Crane | H111: 53 | I111: 74785 | J111: 1411.0377 | K111: 2185 | L111: 1200 | M111: 0 | N111: 0 | O111: 0 | P111: 0 | Q111: 200 | R111: 150 | T111: 1 | U111: 0 | V111: 0.5 | X111: 0.02 | Z111: =IF($J111>=5000,6000,3000) -> 3000 | AA111: =IF($J111>=5000,2650,500) -> 500 | AB111: 650 | AC111: 2500 | AE111: 0 | AG111: 300 | AH111: 2000 | AJ111: =J111 -> 1411.0377 | AK111: =M111 -> 0 | AL111: =P111*J111/12 -> 0 | AM111: =Q111 -> 200 | AN111: =T111*J111/24 -> 58.793239 | AO111: =U111*J111/12 -> 0 | AP111: =V111*J111/24 -> 29.396619 | AQ111: =X111*(AJ111+AL111) -> 28.220755 | AR111: =Z111/24 -> 125 | AS111: =AA111/12 -> 41.666667 | AT111: =AB111/12 -> 54.166667 | AU111: =AC111/12 -> 208.33333 | AV111: =AE111*AJ111/36 -> 0 | AW111: =AG111/36 -> 8.3333333 | AX111: =AH111/36 -> 55.555556 | AY111: =SUM(AJ111:AX111) -> 2220.5039
C112: Manual | D112: Batch Plant | E112: Equipment | F112: Equipment | G112: Operator Dozer | H112: 93 | I112: 124185 | J112: 1335.3226 | K112: 2100 | L112: 750 | M112: 0 | N112: 0 | O112: 0 | P112: 0 | Q112: 200 | R112: 0 | T112: 1 | U112: 0 | V112: 0.5 | X112: 0.02 | Z112: =IF($J112>=5000,6000,3000) -> 3000 | AA112: =IF($J112>=5000,2650,500) -> 500 | AB112: 650 | AC112: 2500 | AE112: 0 | AG112: 300 | AH112: 2000 | AJ112: =J112 -> 1335.3226 | AK112: =M112 -> 0 | AL112: =P112*J112/12 -> 0 | AM112: =Q112 -> 200 | AN112: =T112*J112/24 -> 55.638441 | AO112: =U112*J112/12 -> 0 | AP112: =V112*J112/24 -> 27.81922 | AQ112: =X112*(AJ112+AL112) -> 26.706452 | AR112: =Z112/24 -> 125 | AS112: =AA112/12 -> 41.666667 | AT112: =AB112/12 -> 54.166667 | AU112: =AC112/12 -> 208.33333 | AV112: =AE112*AJ112/36 -> 0 | AW112: =AG112/36 -> 8.3333333 | AX112: =AH112/36 -> 55.555556 | AY112: =SUM(AJ112:AX112) -> 2138.5422
C113: Manual | E113: Equipment | F113: Equipment | G113: Operator Equipment | H113: 16 | I113: 46850 | J113: 2928.125 | K113: 4500 | L113: 1000 | M113: 300 | N113: 0 | O113: 0 | P113: 0 | Q113: 150 | R113: 0 | T113: 1 | U113: 0 | V113: 0.5 | X113: 0.02 | Z113: =IF($J113>=5000,6000,3000) -> 3000 | AA113: =IF($J113>=5000,2650,500) -> 500 | AB113: 650 | AC113: 2500 | AE113: 0 | AG113: 300 | AH113: 2000 | AJ113: =J113 -> 2928.125 | AK113: =M113 -> 300 | AL113: =P113*J113/12 -> 0 | AM113: =Q113 -> 150 | AN113: =T113*J113/24 -> 122.00521 | AO113: =U113*J113/12 -> 0 | AP113: =V113*J113/24 -> 61.002604 | AQ113: =X113*(AJ113+AL113) -> 58.5625 | AR113: =Z113/24 -> 125 | AS113: =AA113/12 -> 41.666667 | AT113: =AB113/12 -> 54.166667 | AU113: =AC113/12 -> 208.33333 | AV113: =AE113*AJ113/36 -> 0 | AW113: =AG113/36 -> 8.3333333 | AX113: =AH113/36 -> 55.555556 | AY113: =SUM(AJ113:AX113) -> 4112.7509
C114: Manual | E114: Equipment | F114: Equipment | G114: Operator Excavator | H114: 235 | I114: 288050 | J114: 1225.7447 | K114: 2000 | L114: 850 | M114: 0 | N114: 0 | O114: 0 | P114: 0 | Q114: 200 | R114: 0 | T114: 1 | U114: 0 | V114: 0.5 | X114: 0.02 | Z114: =IF($J114>=5000,6000,3000) -> 3000 | AA114: =IF($J114>=5000,2650,500) -> 500 | AB114: 650 | AC114: 2500 | AE114: 0 | AG114: 300 | AH114: 2000 | AJ114: =J114 -> 1225.7447 | AK114: =M114 -> 0 | AL114: =P114*J114/12 -> 0 | AM114: =Q114 -> 200 | AN114: =T114*J114/24 -> 51.072695 | AO114: =U114*J114/12 -> 0 | AP114: =V114*J114/24 -> 25.536348 | AQ114: =X114*(AJ114+AL114) -> 24.514894 | AR114: =Z114/24 -> 125 | AS114: =AA114/12 -> 41.666667 | AT114: =AB114/12 -> 54.166667 | AU114: =AC114/12 -> 208.33333 | AV114: =AE114*AJ114/36 -> 0 | AW114: =AG114/36 -> 8.3333333 | AX114: =AH114/36 -> 55.555556 | AY114: =SUM(AJ114:AX114) -> 2019.9242
C115: Manual | E115: Equipment | F115: Equipment | G115: Operator Forklift | H115: 4 | I115: 5250 | J115: 1312.5 | K115: 1600 | L115: 1000 | M115: 0 | N115: 0 | O115: 0 | P115: 0 | Q115: 200 | R115: 150 | T115: 1 | U115: 0 | V115: 0.5 | X115: 0.02 | Z115: =IF($J115>=5000,6000,3000) -> 3000 | AA115: =IF($J115>=5000,2650,500) -> 500 | AB115: 650 | AC115: 2500 | AE115: 0 | AG115: 300 | AH115: 2000 | AJ115: =J115 -> 1312.5 | AK115: =M115 -> 0 | AL115: =P115*J115/12 -> 0 | AM115: =Q115 -> 200 | AN115: =T115*J115/24 -> 54.6875 | AO115: =U115*J115/12 -> 0 | AP115: =V115*J115/24 -> 27.34375 | AQ115: =X115*(AJ115+AL115) -> 26.25 | AR115: =Z115/24 -> 125 | AS115: =AA115/12 -> 41.666667 | AT115: =AB115/12 -> 54.166667 | AU115: =AC115/12 -> 208.33333 | AV115: =AE115*AJ115/36 -> 0 | AW115: =AG115/36 -> 8.3333333 | AX115: =AH115/36 -> 55.555556 | AY115: =SUM(AJ115:AX115) -> 2113.8368
C116: Manual | E116: Equipment | F116: Equipment | G116: Operator Generator | H116: 8 | I116: 9590 | J116: 1198.75 | K116: 1500 | L116: 990 | M116: 0 | N116: 0 | O116: 0 | P116: 0 | Q116: 150 | R116: 150 | T116: 1 | U116: 0 | V116: 0.5 | X116: 0.02 | Z116: =IF($J116>=5000,6000,3000) -> 3000 | AA116: =IF($J116>=5000,2650,500) -> 500 | AB116: 650 | AC116: 2500 | AE116: 0 | AG116: 300 | AH116: 2000 | AJ116: =J116 -> 1198.75 | AK116: =M116 -> 0 | AL116: =P116*J116/12 -> 0 | AM116: =Q116 -> 150 | AN116: =T116*J116/24 -> 49.947917 | AO116: =U116*J116/12 -> 0 | AP116: =V116*J116/24 -> 24.973958 | AQ116: =X116*(AJ116+AL116) -> 23.975 | AR116: =Z116/24 -> 125 | AS116: =AA116/12 -> 41.666667 | AT116: =AB116/12 -> 54.166667 | AU116: =AC116/12 -> 208.33333 | AV116: =AE116*AJ116/36 -> 0 | AW116: =AG116/36 -> 8.3333333 | AX116: =AH116/36 -> 55.555556 | AY116: =SUM(AJ116:AX116) -> 1940.7024
C117: Manual | E117: Equipment | F117: Equipment | G117: Operator Grader | H117: 57 | I117: 100050 | J117: 1755.2632 | K117: 3100 | L117: 1100 | M117: 0 | N117: 0 | O117: 0 | P117: 0 | Q117: 200 | R117: 0 | T117: 1 | U117: 0 | V117: 0.5 | X117: 0.02 | Z117: =IF($J117>=5000,6000,3000) -> 3000 | AA117: =IF($J117>=5000,2650,500) -> 500 | AB117: 650 | AC117: 2500 | AE117: 0 | AG117: 300 | AH117: 2000 | AJ117: =J117 -> 1755.2632 | AK117: =M117 -> 0 | AL117: =P117*J117/12 -> 0 | AM117: =Q117 -> 200 | AN117: =T117*J117/24 -> 73.135965 | AO117: =U117*J117/12 -> 0 | AP117: =V117*J117/24 -> 36.567982 | AQ117: =X117*(AJ117+AL117) -> 35.105263 | AR117: =Z117/24 -> 125 | AS117: =AA117/12 -> 41.666667 | AT117: =AB117/12 -> 54.166667 | AU117: =AC117/12 -> 208.33333 | AV117: =AE117*AJ117/36 -> 0 | AW117: =AG117/36 -> 8.3333333 | AX117: =AH117/36 -> 55.555556 | AY117: =SUM(AJ117:AX117) -> 2593.1279
C118: Manual | E118: Equipment | F118: Equipment | G118: Operator- Grader (Finishing) | H118: 1 | I118: 2800 | J118: 2800 | K118: 2800 | L118: 2800 | M118: 0 | N118: 0 | O118: 0 | P118: 0 | Q118: 0 | R118: 0 | T118: 1 | U118: 0 | V118: 0.5 | X118: 0.02 | Z118: =IF($J118>=5000,6000,3000) -> 3000 | AA118: =IF($J118>=5000,2650,500) -> 500 | AB118: 650 | AC118: 2500 | AE118: 0 | AG118: 300 | AH118: 2000 | AJ118: =J118 -> 2800 | AK118: =M118 -> 0 | AL118: =P118*J118/12 -> 0 | AM118: =Q118 -> 0 | AN118: =T118*J118/24 -> 116.66667 | AO118: =U118*J118/12 -> 0 | AP118: =V118*J118/24 -> 58.333333 | AQ118: =X118*(AJ118+AL118) -> 56 | AR118: =Z118/24 -> 125 | AS118: =AA118/12 -> 41.666667 | AT118: =AB118/12 -> 54.166667 | AU118: =AC118/12 -> 208.33333 | AV118: =AE118*AJ118/36 -> 0 | AW118: =AG118/36 -> 8.3333333 | AX118: =AH118/36 -> 55.555556 | AY118: =SUM(AJ118:AX118) -> 3524.0556
C119: Manual | E119: Equipment | F119: Equipment | G119: Operator Heavy Equipment | H119: 14 | I119: 16150 | J119: 1153.5714 | K119: 2400 | L119: 800 | M119: 0 | N119: 0 | O119: 0 | P119: 0 | Q119: 150 | R119: 150 | T119: 1 | U119: 0 | V119: 0.5 | X119: 0.02 | Z119: =IF($J119>=5000,6000,3000) -> 3000 | AA119: =IF($J119>=5000,2650,500) -> 500 | AB119: 650 | AC119: 2500 | AE119: 0 | AG119: 300 | AH119: 2000 | AJ119: =J119 -> 1153.5714 | AK119: =M119 -> 0 | AL119: =P119*J119/12 -> 0 | AM119: =Q119 -> 150 | AN119: =T119*J119/24 -> 48.065476 | AO119: =U119*J119/12 -> 0 | AP119: =V119*J119/24 -> 24.032738 | AQ119: =X119*(AJ119+AL119) -> 23.071429 | AR119: =Z119/24 -> 125 | AS119: =AA119/12 -> 41.666667 | AT119: =AB119/12 -> 54.166667 | AU119: =AC119/12 -> 208.33333 | AV119: =AE119*AJ119/36 -> 0 | AW119: =AG119/36 -> 8.3333333 | AX119: =AH119/36 -> 55.555556 | AY119: =SUM(AJ119:AX119) -> 1891.7966
C120: Manual | E120: Equipment | F120: Equipment | G120: Operator Jack Hammer | H120: 4 | I120: 4800 | J120: 1200 | K120: 1200 | L120: 1200 | M120: 0 | N120: 0 | O120: 0 | P120: 0 | Q120: 200 | R120: 150 | T120: 1 | U120: 0 | V120: 0.5 | X120: 0.02 | Z120: =IF($J120>=5000,6000,3000) -> 3000 | AA120: =IF($J120>=5000,2650,500) -> 500 | AB120: 650 | AC120: 2500 | AE120: 0 | AG120: 300 | AH120: 2000 | AJ120: =J120 -> 1200 | AK120: =M120 -> 0 | AL120: =P120*J120/12 -> 0 | AM120: =Q120 -> 200 | AN120: =T120*J120/24 -> 50 | AO120: =U120*J120/12 -> 0 | AP120: =V120*J120/24 -> 25 | AQ120: =X120*(AJ120+AL120) -> 24 | AR120: =Z120/24 -> 125 | AS120: =AA120/12 -> 41.666667 | AT120: =AB120/12 -> 54.166667 | AU120: =AC120/12 -> 208.33333 | AV120: =AE120*AJ120/36 -> 0 | AW120: =AG120/36 -> 8.3333333 | AX120: =AH120/36 -> 55.555556 | AY120: =SUM(AJ120:AX120) -> 1992.0556
C121: Manual | E121: Equipment | F121: Equipment | G121: Operator loader | H121: 217 | I121: 259351 | J121: 1195.1659 | K121: 1700 | L121: 600 | M121: 0 | N121: 0 | O121: 0 | P121: 0 | Q121: 250 | R121: 0 | T121: 1 | U121: 0 | V121: 0.5 | X121: 0.02 | Z121: =IF($J121>=5000,6000,3000) -> 3000 | AA121: =IF($J121>=5000,2650,500) -> 500 | AB121: 650 | AC121: 2500 | AE121: 0 | AG121: 300 | AH121: 2000 | AJ121: =J121 -> 1195.1659 | AK121: =M121 -> 0 | AL121: =P121*J121/12 -> 0 | AM121: =Q121 -> 250 | AN121: =T121*J121/24 -> 49.798579 | AO121: =U121*J121/12 -> 0 | AP121: =V121*J121/24 -> 24.89929 | AQ121: =X121*(AJ121+AL121) -> 23.903318 | AR121: =Z121/24 -> 125 | AS121: =AA121/12 -> 41.666667 | AT121: =AB121/12 -> 54.166667 | AU121: =AC121/12 -> 208.33333 | AV121: =AE121*AJ121/36 -> 0 | AW121: =AG121/36 -> 8.3333333 | AX121: =AH121/36 -> 55.555556 | AY121: =SUM(AJ121:AX121) -> 2036.8226
...

Sheet Activity List CSI
C2: Activity list | D2: 1 | E2: 2 | F2: 3 | G2: 4 | H2: 5 | I2: 6 | J2: 7
C3: Old Activity Code | D3: Activity Code | E3: Activity description | F3: Div. | G3: Division Description | H3: Sub Division | I3: Extension | J3: Sub Division Description
A4: =COUNTIF($D$4:$D$146,D4) -> 1 | B4: Excavation Work for Sandy Soil | C4: 0201 | D4: =H4&"-"&I4 -> 02300-01 | E4: Excavation Work for Sandy Soil | F4: 02 | G4: EarthWork | H4: 02300 | I4: 01 | J4: Earthwork
A5: =COUNTIF($D$4:$D$146,D5) -> 1 | B5: Excavation Work for Clay | C5: 0202 | D5: =H5&"-"&I5 -> 02300-02 | E5: Excavation Work for Clay | F5: 02 | G5: EarthWork | H5: 02300 | I5: 02 | J5: Earthwork
A6: =COUNTIF($D$4:$D$146,D6) -> 1 | B6: Excavation Work for Rocky Soil | C6: 0203 | D6: =H6&"-"&I6 -> 02300-03 | E6: Excavation Work for Rocky Soil | F6: 02 | G6: EarthWork | H6: 02300 | I6: 03 | J6: Earthwork
A7: =COUNTIF($D$4:$D$146,D7) -> 1 | B7: Excavation Work for Sandy Soil Including Disposal | C7: 0204 | D7: =H7&"-"&I7 -> 02300-04 | E7: Excavation Work for Sandy Soil Including Disposal | F7: 02 | G7: EarthWork | H7: 02300 | I7: 04 | J7: Earthwork
A8: =COUNTIF($D$4:$D$146,D8) -> 1 | B8: Excavation Work for Clay Including Disposal | C8: 0205 | D8: =H8&"-"&I8 -> 02300-05 | E8: Excavation Work for Clay Including Disposal | F8: 02 | G8: EarthWork | H8: 02300 | I8: 05 | J8: Earthwork
A9: =COUNTIF($D$4:$D$146,D9) -> 1 | B9: Excavation Work for Rocky Soil Including Disposal | C9: 0206 | D9: =H9&"-"&I9 -> 02300-06 | E9: Excavation Work for Rocky Soil Including Disposal | F9: 02 | G9: EarthWork | H9: 02300 | I9: 06 | J9: Earthwork
A10: =COUNTIF($D$4:$D$146,D10) -> 1 | B10: Dewatering Work | C10: 0207 | D10: =H10&"-"&I10 -> 02100-01 | E10: Dewatering Work | F10: 02 | G10: EarthWork | H10: 02100 | I10: 01 | J10: Site Remediation
A11: =COUNTIF($D$4:$D$146,D11) -> 1 | B11: Shoring System | C11: 0208 | D11: =H11&"-"&I11 -> 02300-07 | E11: Shoring System | F11: 02 | G11: EarthWork | H11: 02300 | I11: 07 | J11: Earthwork
A12: =COUNTIF($D$4:$D$146,D12) -> 1 | B12: Backfilling Work For Open Area with Excavated Material Including Compaction | C12: 0209 | D12: =H12&"-"&I12 -> 02300-08 | E12: Backfilling Work For Open Area with Excavated Material Including Compaction | F12: 02 | G12: EarthWork | H12: 02300 | I12: 08 | J12: Earthwork
A13: =COUNTIF($D$4:$D$146,D13) -> 1 | B13: Backfilling Work For Open Area with Imported Material Including Compaction | C13: 0210 | D13: =H13&"-"&I13 -> 02300-09 | E13: Backfilling Work For Open Area with Imported Material Including Compaction | F13: 02 | G13: EarthWork | H13: 02300 | I13: 09 | J13: Earthwork
A14: =COUNTIF($D$4:$D$146,D14) -> 1 | B14: Backfilling Work For Trenches with Excavated Material Including Compaction | C14: 0211 | D14: =H14&"-"&I14 -> 02300-10 | E14: Backfilling Work For Trenches with Excavated Material Including Compaction | F14: 02 | G14: EarthWork | H14: 02300 | I14: 10 | J14: Earthwork
A15: =COUNTIF($D$4:$D$146,D15) -> 1 | B15: Backfilling Work For Trenches with Imported Material Including Compaction | C15: 0212 | D15: =H15&"-"&I15 -> 02300-11 | E15: Backfilling Work For Trenches with Imported Material Including Compaction | F15: 02 | G15: EarthWork | H15: 02300 | I15: 11 | J15: Earthwork
... A35: =COUNTIF($D$4:$D$146,D35) -> 1 | B35: Marking Work | C35: 0232 | D35: =H35&"-"&I35 -> 09900-04 | E35: Marking Work | F35: 02 | G35: EarthWork | H35: 09900 | I35: 04 | J35: Paints & Coatings
A36: =COUNTIF($D$4:$D$146,D36) -> 1 | B36: Installing Newgersy Barriers | C36: 0233 | D36: =H36&"-"&I36 -> 02700-10 | E36: Installing Newgersy Barriers | F36: 02 | G36: EarthWork | H36: 02700 | I36: 10 | J36: Bases, Ballast,Pavement & Appurtenances
A37: =COUNTIF($D$4:$D$146,D37) -> 1 | B37: Installing Sign Boards | C37: 0234 | D37: =H37&"-"&I37 -> 10100-02 | E37: Installing Sign Boards | F37: 02 | G37: EarthWork | H37: 10100 | I37: 02 | J37: Visual Display Boards
A38: =COUNTIF($D$4:$D$146,D38) -> 1 | B38: Installing Road Rails | C38: 0235 | D38: =H38&"-"&I38 -> 05650-01 | E38: Installing Road Rails | F38: 02 | G38: EarthWork | H38: 05650 | I38: 01 | J38: Railroad Track & Accessories
A39: =COUNTIF($D$4:$D$146,D39) -> 1 | B39: Removing Obstacles | C39: 0237 | D39: =H39&"-"&I39 -> 02200-01 | E39: Removing Obstacles | F39: 02 | G39: EarthWork | H39: 02200 | I39: 01 | J39: Site Prepartion
A40: =COUNTIF($D$4:$D$146,D40) -> 1 | B40: Clearing and Grubbing | C40: 0238 | D40: =H40&"-"&I40 -> 02200-02 | E40: Clearing and Grubbing | F40: 02 | G40: EarthWork | H40: 02200 | I40: 02 | J40: Site Prepartion
A41: =COUNTIF($D$4:$D$146,D41) -> 1 | B41: Diversion of Telephone Cables | C41: 0239 | D41: =H41&"-"&I41 -> 02500-01 | E41: Diversion of Telephone Cables | F41: 02 | G41: EarthWork | H41: 02500 | I41: 01 | J41: Utility Services
A42: =COUNTIF($D$4:$D$146,D42) -> 1 | B42: Diversion of Low Voltage Cables | C42: 0240 | D42: =H42&"-"&I42 -> 02500-02 | E42: Diversion of Low Voltage Cables | F42: 02 | G42: EarthWork | H42: 02500 | I42: 02 | J42: Utility Services
A43: =COUNTIF($D$4:$D$146,D43) -> 1 | B43: Diversion of High Voltage Cables | C43: 0241 | D43: =H43&"-"&I43 -> 02500-03 | E43: Diversion of High Voltage Cables | F43: 02 | G43: EarthWork | H43: 02500 | I43: 03 | J43: Utility Services
A44: =COUNTIF($D$4:$D$146,D44) -> 1 | B44: Diversion of Traffic | C44: 0242 | D44: =H44&"-"&I44 -> 02500-04 | E44: Diversion of Traffic | F44: 02 | G44: EarthWork | H44: 02500 | I44: 04 | J44: Utility Services
A45: =COUNTIF($D$4:$D$146,D45) -> 1 | B45: Diversion of Flood Water | C45: 0243 | D45: =H45&"-"&I45 -> 02500-05 | E45: Diversion of Flood Water | F45: 02 | G45: EarthWork | H45: 02500 | I45: 05 | J45: Utility Services
A46: =COUNTIF($D$4:$D$146,D46) -> 1 | B46: Diversion of Drinking Water | C46: 0244 | D46: =H46&"-"&I46 -> 02500-06 | E46: Diversion of Drinking Water | F46: 02 | G46: EarthWork | H46: 02500 | I46: 06 | J46: Utility Services
A47: =COUNTIF($D$4:$D$146,D47) -> 1 | B47: Removal of Concrete Building Including Blocks | C47: 0245 | D47: =H47&"-"&I47 -> 02200-03 | E47: Removal of Concrete Building Including Blocks | F47: 02 | G47: EarthWork | H47: 02200 | I47: 03 | J47: Site Prepartion
A48: =COUNTIF($D$4:$D$146,D48) -> 1 | B48: Removal of Septic Tanks | C48: 0247 | D48: =H48&"-"&I48 -> 02200-04 | E48: Removal of Septic Tanks | F48: 02 | G48: EarthWork | H48: 02200 | I48: 04 | J48: Site Prepartion
... A146: =COUNTIF($D$4:$D$146,D146) -> 1 | B146: Electrical Work | C146: 1601 | D146: =H146&"-"&I146 -> 16050-01 | E146: Electrical Work | F146: 16 | G146: ElectricalWork | H146: 16050 | I146: 01 | J146: Basic Electrical Materials and Methods

Sheet Resource Unique List 
G2: Unique List For Resources
C3: Resource Code | D3: Resource Category | E3: Resource Description | F3: UOM | G3: Resource Main Code | H3: Ext | I3: Ext Description | J3: Rate
C4: =G4&"-"&H4 -> 02100105-001 | D4: 1 | E4: Antitermite Material | F4: Litre | G4: 02100105 | H4: 001
C5: =G5&"-"&H5 -> 02300105-001 | D5: 1 | E5: Backfillig Material | F5: M3 | G5: 02300105 | H5: 001
C6: =G6&"-"&H6 -> 02700105-001 | D6: 1 | E6: Asphalt | F6: M3 | G6: 02700105 | H6: 001
C7: =G7&"-"&H7 -> 02700110-001 | D7: 1 | E7: Sub-Grade Material | F7: M3 | G7: 02700110 | H7: 001
C8: =G8&"-"&H8 -> 02700115-001 | D8: 1 | E8: Sub-Base Material | F8: M3 | G8: 02700115 | H8: 001
C9: =G9&"-"&H9 -> 02700120-001 | D9: 1 | E9: Base Material | F9: M3 | G9: 02700120 | H9: 001
C10: =G10&"-"&H10 -> 02700125-001 | D10: 1 | E10: New gersy material | F10: L.M | G10: 02700125 | H10: 001
C11: =G11&"-"&H11 -> 02700130-001 | D11: 1 | E11: MC Material | F11: Litre | G11: 02700130 | H11: 001
C12: =G12&"-"&H12 -> 02700135-001 | D12: 1 | E12: RC Material | F12: Litre | G12: 02700135 | H12: 001
C13: =G13&"-"&H13 -> 02700140-001 | D13: 1 | E13: Concrete Tiles | F13: M2 | G13: 02700140 | H13: 001
C14: =G14&"-"&H14 -> 02700145-001 | D14: 1 | E14: Interlock Tiles | F14: M2 | G14: 02700145 | H14: 001
C15: =G15&"-"&H15 -> 03300105-001 | D15: 1 | E15: Concrete Chemicals | F15: Litre | G15: 03300105 | H15: 001
... C132: =G132&"-"&H132 -> 09600220-001 | D132: 2 | E132: Epoxy Painting Sub-Contractor | F132: LS | G132: 09600220 | H132: 001
C133: =G133&"-"&H133 -> 03300305-001 | D133: 3 | E133: Carpentary Crew | F133: MH | G133: 03300305 | H133: 001 | J133: 10.123602
C134: =G134&"-"&H134 -> 15200315-001 | D134: 3 | E134: Ex. Plumping (Manhole) | F134: MH | G134: 15200315 | H134: 001 | J134: 9.4675938
C135: =G135&"-"&H135 -> 02700310-001 | D135: 3 | E135: Asphalt Workers Crew | F135: MH | G135: 02700310 | H135: 001 | J135: 14.265691
C136: =G136&"-"&H136 -> 02300315-001 | D136: 3 | E136: Ex. Plumping (Pipes) | F136: MH | G136: 02300315 | H136: 001 | J136: 10.573304
C137: =G137&"-"&H137 -> 02300320-001 | D137: 3 | E137: General Workers Crew | F137: MH | G137: 02300320 | H137: 001 | J137: 8.3745532
C138: =G138&"-"&H138 -> 04200305-001 | D138: 3 | E138: Block Work Crew | F138: MH | G138: 04200305 | H138: 001 | J138: 8.4582914
C139: =G139&"-"&H139 -> 02100305-001 | D139: 3 | E139: Dewatering Crew | F139: MH | G139: 02100305 | H139: 001 | J139: 11.020056
C140: =G140&"-"&H140 -> 09200305-001 | D140: 3 | E140: Plastering Work Crew | F140: MH | G140: 09200305 | H140: 001 | J140: 8.9983698
C141: =G141&"-"&H141 -> 15200310-001 | D141: 3 | E141: Sewage (Manhole) | F141: MH | G141: 15200310 | H141: 001 | J141: 8.7146181
C142: =G142&"-"&H142 -> 09300305-001 | D142: 3 | E142: Tile Fixing Crew | F142: MH | G142: 09300305 | H142: 001 | J142: 9.2877564
C143: =G143&"-"&H143 -> 03400305-001 | D143: 3 | E143: Precast Concrete Crew | F143: MH | G143: 03400305 | H143: 001 | J143: 10.389741
C144: =G144&"-"&H144 -> 02700305-001 | D144: 3 | E144: Surveying Crew | F144: MH | G144: 02700305 | H144: 001 | J144: 21.151771
... C151: =G151&"-"&H151 -> 09900305-001 | D151: 3 | E151: Painting Crew | F151: MH | G151: 09900305 | H151: 001 | J151: 9.649638
C152: =G152&"-"&H152 -> 02700425-001 | D152: 4 | E152: Ashphalt Finisher | F152: EH | G152: 02700425 | H152: 001 | I152: Normal | J152: 30.851047
C153: =G153&"-"&H153 -> 02700425-002 | D153: 4 | E153: Ashphalt Finisher | F153: EH | G153: 02700425 | H153: 002 | I153: Big | J153: 70.132348
C154: =G154&"-"&H154 -> 02700410-001 | D154: 4 | E154: Asphalt Compactor | F154: EH | G154: 02700410 | H154: 001 | I154: Single Drum | J154: 17.841963
C155: =G155&"-"&H155 -> 02700410-002 | D155: 4 | E155: Asphalt Compactor | F155: EH | G155: 02700410 | H155: 002 | I155: Double Dum | J155: 36.107463
C156: =G156&"-"&H156 -> 02700440-001 | D156: 4 | E156: Asphalt Cutter | F156: EH | G156: 02700440 | H156: 001 | I156: Normal | J156: 11.643363
C157: =G157&"-"&H157 -> 02300450-001 | D157: 4 | E157: Bobcat | F157: EH | G157: 02300450 | H157: 001 | I157: Big | J157: 27.469935
C158: =G158&"-"&H158 -> 02300450-002 | D158: 4 | E158: Bobcat | F158: EH | G158: 02300450 | H158: 002 | I158: Small | J158: 16.169469
C159: =G159&"-"&H159 -> 03400405-001 | D159: 4 | E159: Crane | F159: EH | G159: 03400405 | H159: 001 | I159: Telescope | J159: 46.643058
C160: =G160&"-"&H160 -> 03400405-002 | D160: 4 | E160: Crane | F160: EH | G160: 03400405 | H160: 002 | I160: Tower | J160: 87.557706
C161: =G161&"-"&H161 -> 02100405-001 | D161: 4 | E161: De-Watering Pump | F161: EH | G161: 02100405 | H161: 001 | I161: Normal | J161: 14.548931
C162: =G162&"-"&H162 -> 02200405-001 | D162: 4 | E162: Dozer | F162: EH | G162: 02200405 | H162: 001 | I162: Crawler | J162: 126.52665
C163: =G163&"-"&H163 -> 02200405-002 | D163: 4 | E163: Dozer | F163: EH | G163: 02200405 | H163: 002 | I163: Wheel | J163: 52.864196
... C187: =G187&"-"&H187 -> 02300425-001 | D187: 4 | E187: Water Tanker | F187: EH | G187: 02300425 | H187: 001 | I187: Normal | J187: 32.57975

Sheet Mat. List CSI
G1: 3 | H1: 4 | J1: 7
D2: Code System For Materials
D3: Old Activity Code | E3: Activity Code | F3: Activity description | G3: Div | H3: Division Description | I3: Sub Division | J3: Sub Division Description | K3: Resource Description | L3: Resource Order | M3: Resource Main Code | N3: Resource Main Code Mod.
D4: 0210 | E4: =VLOOKUP(F4,'Activity List CSI'!$B$4:$D$146,3,0) -> 02300-09 | F4: Backfilling Work For Open Area with Imported Material Including Compaction | G4: =VLOOKUP($E4,'Activity List CSI'!$D$4:$J$146,'Mat. List CSI'!G$1,0) -> 02 | H4: =VLOOKUP($E4,'Activity List CSI'!$D$4:$J$146,'Mat. List CSI'!H$1,0) -> EarthWork | I4: =VLOOKUP(D4,'Activity List CSI'!$C$4:$H$146,6,0) -> 02300 | J4: =VLOOKUP($E4,'Activity List CSI'!$D$4:$J$146,'Mat. List CSI'!J$1,0) -> Earthwork | K4: Backfillig Material | L4: 105 | M4: =I4&L4 -> 02300105 | N4: =M4 -> 02300105
D5: 0210 | E5: =VLOOKUP(F5,'Activity List CSI'!$B$4:$D$146,3,0) -> 02300-09 | F5: Backfilling Work For Open Area with Imported Material Including Compaction | G5: =VLOOKUP($E5,'Activity List CSI'!$D$4:$J$146,'Mat. List CSI'!G$1,0) -> 02 | H5: =VLOOKUP($E5,'Activity List CSI'!$D$4:$J$146,'Mat. List CSI'!H$1,0) -> EarthWork | I5: =VLOOKUP(D5,'Activity List CSI'!$C$4:$H$146,6,0) -> 02300 | J5: =VLOOKUP($E5,'Activity List CSI'!$D$4:$J$146,'Mat. List CSI'!J$1,0) -> Earthwork | K5: Backfillig Material | L5: 105 | M5: =I5&L5 -> 02300105 | N5: =M5 -> 02300105
D6: 0212 | E6: =VLOOKUP(F6,'Activity List CSI'!$B$4:$D$146,3,0) -> 02300-11 | F6: Backfilling Work For Trenches with Imported Material Including Compaction | G6: =VLOOKUP($E6,'Activity List CSI'!$D$4:$J$146,'Mat. List CSI'!G$1,0) -> 02 | H6: =VLOOKUP($E6,'Activity List CSI'!$D$4:$J$146,'Mat. List CSI'!H$1,0) -> EarthWork | I6: =VLOOKUP(D6,'Activity List CSI'!$C$4:$H$146,6,0) -> 02300 | J6: =VLOOKUP($E6,'Activity List CSI'!$D$4:$J$146,'Mat. List CSI'!J$1,0) -> Earthwork | K6: Backfillig Material | L6: 105 | M6: =I6&L6 -> 02300105 | N6: =M6 -> 02300105
D7: 0212 | E7: =VLOOKUP(F7,'Activity List CSI'!$B$4:$D$146,3,0) -> 02300-11 | F7: Backfilling Work For Trenches with Imported Material Including Compaction | G7: =VLOOKUP($E7,'Activity List CSI'!$D$4:$J$146,'Mat. List CSI'!G$1,0) -> 02 | H7: =VLOOKUP($E7,'Activity List CSI'!$D$4:$J$146,'Mat. List CSI'!H$1,0) -> EarthWork | I7: =VLOOKUP(D7,'Activity List CSI'!$C$4:$H$146,6,0) -> 02300 | J7: =VLOOKUP($E7,'Activity List CSI'!$D$4:$J$146,'Mat. List CSI'!J$1,0) -> Earthwork | K7: Backfillig Material | L7: 105 | M7: =I7&L7 -> 02300105 | N7: =M7 -> 02300105
D8: 0214 | E8: =VLOOKUP(F8,'Activity List CSI'!$B$4:$D$146,3,0) -> 02300-13 | F8: Backfilling Work between Footings with Imported Material Including Compaction | G8: =VLOOKUP($E8,'Activity List CSI'!$D$4:$J$146,'Mat. List CSI'!G$1,0) -> 02 | H8: =VLOOKUP($E8,'Activity List CSI'!$D$4:$J$146,'Mat. List CSI'!H$1,0) -> EarthWork | I8: =VLOOKUP(D8,'Activity List CSI'!$C$4:$H$146,6,0) -> 02300 | J8: =VLOOKUP($E8,'Activity List CSI'!$D$4:$J$146,'Mat. List CSI'!J$1,0) -> Earthwork | K8: Backfillig Material | L8: 105 | M8: =I8&L8 -> 02300105 | N8: =M8 -> 02300105
D9: 0214 | E9: =VLOOKUP(F9,'Activity List CSI'!$B$4:$D$146,3,0) -> 02300-13 | F9: Backfilling Work between Footings with Imported Material Including Compaction | G9: =VLOOKUP($E9,'Activity List CSI'!$D$4:$J$146,'Mat. List CSI'!G$1,0) -> 02 | H9: =VLOOKUP($E9,'Activity List CSI'!$D$4:$J$146,'Mat. List CSI'!H$1,0) -> EarthWork | I9: =VLOOKUP(D9,'Activity List CSI'!$C$4:$H$146,6,0) -> 02300 | J9: =VLOOKUP($E9,'Activity List CSI'!$D$4:$J$146,'Mat. List CSI'!J$1,0) -> Earthwork | K9: Backfillig Material | L9: 105 | M9: =I9&L9 -> 02300105 | N9: =M9 -> 02300105
D10: 0215 | E10: =VLOOKUP(F10,'Activity List CSI'!$B$4:$D$146,3,0) -> 02300-14 | F10: Soil Replacement Work including Compaction | G10: =VLOOKUP($E10,'Activity List CSI'!$D$4:$J$146,'Mat. List CSI'!G$1,0) -> 02 | H10: =VLOOKUP($E10,'Activity List CSI'!$D$4:$J$146,'Mat. List CSI'!H$1,0) -> EarthWork | I10: =VLOOKUP(D10,'Activity List CSI'!$C$4:$H$146,6,0) -> 02300 | J10: =VLOOKUP($E10,'Activity List CSI'!$D$4:$J$146,'Mat. List CSI'!J$1,0) -> Earthwork | K10: Backfillig Material | L10: 105 | M10: =I10&L10 -> 02300105 | N10: =M10 -> 02300105
D11: 0215 | E11: =VLOOKUP(F11,'Activity List CSI'!$B$4:$D$146,3,0) -> 02300-14 | F11: Soil Replacement Work including Compaction | G11: =VLOOKUP($E11,'Activity List CSI'!$D$4:$J$146,'Mat. List CSI'!G$1,0) -> 02 | H11: =VLOOKUP($E11,'Activity List CSI'!$D$4:$J$146,'Mat. List CSI'!H$1,0) -> EarthWork | I11: =VLOOKUP(D11,'Activity List CSI'!$C$4:$H$146,6,0) -> 02300 | J11: =VLOOKUP($E11,'Activity List CSI'!$D$4:$J$146,'Mat. List CSI'!J$1,0) -> Earthwork | K11: Backfillig Material | L11: 105 | M11: =I11&L11 -> 02300105 | N11: =M11 -> 02300105
D12: 0221 | E12: =VLOOKUP(F12,'Activity List CSI'!$B$4:$D$146,3,0) -> 02300-20 | F12: Drainage Layer Under Slab On Grade Work | G12: =VLOOKUP($E12,'Activity List CSI'!$D$4:$J$146,'Mat. List CSI'!G$1,0) -> 02 | H12: =VLOOKUP($E12,'Activity List CSI'!$D$4:$J$146,'Mat. List CSI'!H$1,0) -> EarthWork | I12: =VLOOKUP(D12,'Activity List CSI'!$C$4:$H$146,6,0) -> 02300 | J12: =VLOOKUP($E12,'Activity List CSI'!$D$4:$J$146,'Mat. List CSI'!J$1,0) -> Earthwork | K12: UPVC Pipes | L12: 130 | M12: =I12&L12 -> 02300130 | N12: 15100130
D13: 0221 | E13: =VLOOKUP(F13,'Activity List CSI'!$B$4:$D$146,3,0) -> 02300-20 | F13: Drainage Layer Under Slab On Grade Work | G13: =VLOOKUP($E13,'Activity List CSI'!$D$4:$J$146,'Mat. List CSI'!G$1,0) -> 02 | H13: =VLOOKUP($E13,'Activity List CSI'!$D$4:$J$146,'Mat. List CSI'!H$1,0) -> EarthWork | I13: =VLOOKUP(D13,'Activity List CSI'!$C$4:$H$146,6,0) -> 02300 | J13: =VLOOKUP($E13,'Activity List CSI'!$D$4:$J$146,'Mat. List CSI'!J$1,0) -> Earthwork | K13: UPVC Pipes | L13: 130 | M13: =I13&L13 -> 02300130 | N13: 15100130
D14: 0222 | E14: =VLOOKUP(F14,'Activity List CSI'!$B$4:$D$146,3,0) -> 02100-02 | F14: Application Of Soil Treatment For Termite Control | G14: =VLOOKUP($E14,'Activity List CSI'!$D$4:$J$146,'Mat. List CSI'!G$1,0) -> 02 | H14: =VLOOKUP($E14,'Activity List CSI'!$D$4:$J$146,'Mat. List CSI'!H$1,0) -> EarthWork | I14: =VLOOKUP(D14,'Activity List CSI'!$C$4:$H$146,6,0) -> 02100 | J14: =VLOOKUP($E14,'Activity List CSI'!$D$4:$J$146,'Mat. List CSI'!J$1,0) -> Site Remediation | K14: Antitermite Material | L14: 105 | M14: =I14&L14 -> 02100105 | N14: =M14 -> 02100105
D15: 0225 | E15: =VLOOKUP(F15,'Activity List CSI'!$B$4:$D$146,3,0) -> 02700-03 | F15: Subgrade Work | G15: =VLOOKUP($E15,'Activity List CSI'!$D$4:$J$146,'Mat. List CSI'!G$1,0) -> 02 | H15: =VLOOKUP($E15,'Activity List CSI'!$D$4:$J$146,'Mat. List CSI'!H$1,0) -> EarthWork | I15: =VLOOKUP(D15,'Activity List CSI'!$C$4:$H$146,6,0) -> 02700 | J15: =VLOOKUP($E15,'Activity List CSI'!$D$4:$J$146,'Mat. List CSI'!J$1,0) -> Bases, Ballast,Pavement & Appurtenances | K15: Sub-Grade Material | L15: 110 | M15: =I15&L15 -> 02700110 | N15: =M15 -> 02700110
D16: 0225 | E16: =VLOOKUP(F16,'Activity List CSI'!$B$4:$D$146,3,0) -> 02700-03 | F16: Subgrade Work | G16: =VLOOKUP($E16,'Activity List CSI'!$D$4:$J$146,'Mat. List CSI'!G$1,0) -> 02 | H16: =VLOOKUP($E16,'Activity List CSI'!$D$4:$J$146,'Mat. List CSI'!H$1,0) -> EarthWork | I16: =VLOOKUP(D16,'Activity List CSI'!$C$4:$H$146,6,0) -> 02700 | J16: =VLOOKUP($E16,'Activity List CSI'!$D$4:$J$146,'Mat. List CSI'!J$1,0) -> Bases, Ballast,Pavement & Appurtenances | K16: Sub-Grade Material | L16: 110 | M16: =I16&L16 -> 02700110 | N16: =M16 -> 02700110
D17: 0226 | E17: =VLOOKUP(F17,'Activity List CSI'!$B$4:$D$146,3,0) -> 02700-04 | F17: Subbase Work | G17: =VLOOKUP($E17,'Activity List CSI'!$D$4:$J$146,'Mat. List CSI'!G$1,0) -> 02 | H17: =VLOOKUP($E17,'Activity List CSI'!$D$4:$J$146,'Mat. List CSI'!H$1,0) -> EarthWork | I17: =VLOOKUP(D17,'Activity List CSI'!$C$4:$H$146,6,0) -> 02700 | J17: =VLOOKUP($E17,'Activity List CSI'!$D$4:$J$146,'Mat. List CSI'!J$1,0) -> Bases, Ballast,Pavement & Appurtenances | K17: Sub-Base Material | L17: 115 | M17: =I17&L17 -> 02700115 | N17: =M17 -> 02700115
D18: 0226 | E18: =VLOOKUP(F18,'Activity List CSI'!$B$4:$D$146,3,0) -> 02700-04 | F18: Subbase Work | G18: =VLOOKUP($E18,'Activity List CSI'!$D$4:$J$146,'Mat. List CSI'!G$1,0) -> 02 | H18: =VLOOKUP($E18,'Activity List CSI'!$D$4:$J$146,'Mat. List CSI'!H$1,0) -> EarthWork | I18: =VLOOKUP(D18,'Activity List CSI'!$C$4:$H$146,6,0) -> 02700 | J18: =VLOOKUP($E18,'Activity List CSI'!$D$4:$J$146,'Mat. List CSI'!J$1,0) -> Bases, Ballast,Pavement & Appurtenances | K18: Sub-Base Material | L18: 115 | M18: =I18&L18 -> 02700115 | N18: =M18 -> 02700115
D19: 0227 | E19: =VLOOKUP(F19,'Activity List CSI'!$B$4:$D$146,3,0) -> 02700-05 | F19: Road Base Work (WBM) | G19: =VLOOKUP($E19,'Activity List CSI'!$D$4:$J$146,'Mat. List CSI'!G$1,0) -> 02 | H19: =VLOOKUP($E19,'Activity List CSI'!$D$4:$J$146,'Mat. List CSI'!H$1,0) -> EarthWork | I19: =VLOOKUP(D19,'Activity List CSI'!$C$4:$H$146,6,0) -> 02700 | J19: =VLOOKUP($E19,'Activity List CSI'!$D$4:$J$146,'Mat. List CSI'!J$1,0) -> Bases, Ballast,Pavement & Appurtenances | K19: Base Material | L19: 120 | M19: =I19&L19 -> 02700120 | N19: =M19 -> 02700120
D20: 0227 | E20: =VLOOKUP(F20,'Activity List CSI'!$B$4:$D$146,3,0) -> 02700-05 | F20: Road Base Work (WBM) | G20: =VLOOKUP($E20,'Activity List CSI'!$D$4:$J$146,'Mat. List CSI'!G$1,0) -> 02 | H20: =VLOOKUP($E20,'Activity List CSI'!$D$4:$J$146,'Mat. List CSI'!H$1,0) -> EarthWork | I20: =VLOOKUP(D20,'Activity List CSI'!$C$4:$H$146,6,0) -> 02700 | J20: =VLOOKUP($E20,'Activity List CSI'!$D$4:$J$146,'Mat. List CSI'!J$1,0) -> Bases, Ballast,Pavement & Appurtenances | K20: Base Material | L20: 120 | M20: =I20&L20 -> 02700120 | N20: =M20 -> 02700120
D21: 0228 | E21: =VLOOKUP(F21,'Activity List CSI'!$B$4:$D$146,3,0) -> 02700-06 | F21: Prime Coat (MC1) Work | G21: =VLOOKUP($E21,'Activity List CSI'!$D$4:$J$146,'Mat. List CSI'!G$1,0) -> 02 | H21: =VLOOKUP($E21,'Activity List CSI'!$D$4:$J$146,'Mat. List CSI'!H$1,0) -> EarthWork | I21: =VLOOKUP(D21,'Activity List CSI'!$C$4:$H$146,6,0) -> 02700 | J21: =VLOOKUP($E21,'Activity List CSI'!$D$4:$J$146,'Mat. List CSI'!J$1,0) -> Bases, Ballast,Pavement & Appurtenances | K21: MC Material | L21: 130 | M21: =I21&L21 -> 02700130 | N21: =M21 -> 02700130
D22: 0228 | E22: =VLOOKUP(F22,'Activity List CSI'!$B$4:$D$146,3,0) -> 02700-06 | F22: Prime Coat (MC1) Work | G22: =VLOOKUP($E22,'Activity List CSI'!$D$4:$J$146,'Mat. List CSI'!G$1,0) -> 02 | H22: =VLOOKUP($E22,'Activity List CSI'!$D$4:$J$146,'Mat. List CSI'!H$1,0) -> EarthWork | I22: =VLOOKUP(D22,'Activity List CSI'!$C$4:$H$146,6,0) -> 02700 | J22: =VLOOKUP($E22,'Activity List CSI'!$D$4:$J$146,'Mat. List CSI'!J$1,0) -> Bases, Ballast,Pavement & Appurtenances | K22: MC Material | L22: 130 | M22: =I22&L22 -> 02700130 | N22: =M22 -> 02700130
D23: 0229 | E23: =VLOOKUP(F23,'Activity List CSI'!$B$4:$D$146,3,0) -> 02700-07 | F23: Base Coarse Work | G23: =VLOOKUP($E23,'Activity List CSI'!$D$4:$J$146,'Mat. List CSI'!G$1,0) -> 02 | H23: =VLOOKUP($E23,'Activity List CSI'!$D$4:$J$146,'Mat. List CSI'!H$1,0) -> EarthWork | I23: =VLOOKUP(D23,'Activity List CSI'!$C$4:$H$146,6,0) -> 02700 | J23: =VLOOKUP($E23,'Activity List CSI'!$D$4:$J$146,'Mat. List CSI'!J$1,0) -> Bases, Ballast,Pavement & Appurtenances | K23: Asphalt | L23: 105 | M23: =I23&L23 -> 02700105 | N23: =M23 -> 02700105
D24: 0229 | E24: =VLOOKUP(F24,'Activity List CSI'!$B$4:$D$146,3,0) -> 02700-07 | F24: Base Coarse Work | G24: =VLOOKUP($E24,'Activity List CSI'!$D$4:$J$146,'Mat. List CSI'!G$1,0) -> 02 | H24: =VLOOKUP($E24,'Activity List CSI'!$D$4:$J$146,'Mat. List CSI'!H$1,0) -> EarthWork | I24: =VLOOKUP(D24,'Activity List CSI'!$C$4:$H$146,6,0) -> 02700 | J24: =VLOOKUP($E24,'Activity List CSI'!$D$4:$J$146,'Mat. List CSI'!J$1,0) -> Bases, Ballast,Pavement & Appurtenances | K24: Asphalt | L24: 105 | M24: =I24&L24 -> 02700105 | N24: =M24 -> 02700105
D25: 0230 | E25: =VLOOKUP(F25,'Activity List CSI'!$B$4:$D$146,3,0) -> 02700-08 | F25: Tack Coat (RC )Work | G25: =VLOOKUP($E25,'Activity List CSI'!$D$4:$J$146,'Mat. List CSI'!G$1,0) -> 02 | H25: =VLOOKUP($E25,'Activity List CSI'!$D$4:$J$146,'Mat. List CSI'!H$1,0) -> EarthWork | I25: =VLOOKUP(D25,'Activity List CSI'!$C$4:$H$146,6,0) -> 02700 | J25: =VLOOKUP($E25,'Activity List CSI'!$D$4:$J$146,'Mat. List CSI'!J$1,0) -> Bases, Ballast,Pavement & Appurtenances | K25: RC Material | L25: 135 | M25: =I25&L25 -> 02700135 | N25: =M25 -> 02700135
... D143: 0401 | E143: =VLOOKUP(F143,'Activity List CSI'!$B$4:$D$146,3,0) -> 04200-01 | F143: Block Work | G143: =VLOOKUP($E143,'Activity List CSI'!$D$4:$J$146,'Mat. List CSI'!G$1,0) -> 04 | H143: =VLOOKUP($E143,'Activity List CSI'!$D$4:$J$146,'Mat. List CSI'!H$1,0) -> BlockWork | I143: =VLOOKUP(D143,'Activity List CSI'!$C$4:$H$146,6,0) -> 04200 | J143: =VLOOKUP($E143,'Activity List CSI'!$D$4:$J$146,'Mat. List CSI'!J$1,0) -> Masonary Units | K143: Block Accessories | L143: 125 | M143: =I143&L143 -> 04200125 | N143: =M143 -> 04200125
D144: 0401 | E144: =VLOOKUP(F144,'Activity List CSI'!$B$4:$D$146,3,0) -> 04200-01 | F144: Block Work | G144: =VLOOKUP($E144,'Activity List CSI'!$D$4:$J$146,'Mat. List CSI'!G$1,0) -> 04 | H144: =VLOOKUP($E144,'Activity List CSI'!$D$4:$J$146,'Mat. List CSI'!H$1,0) -> BlockWork | I144: =VLOOKUP(D144,'Activity List CSI'!$C$4:$H$146,6,0) -> 04200 | J144: =VLOOKUP($E144,'Activity List CSI'!$D$4:$J$146,'Mat. List CSI'!J$1,0) -> Masonary Units | K144: Cement | L144: 105 | M144: =I144&L144 -> 04200105 | N144: 09200105
D145: 0401 | E145: =VLOOKUP(F145,'Activity List CSI'!$B$4:$D$146,3,0) -> 04200-01 | F145: Block Work | G145: =VLOOKUP($E145,'Activity List CSI'!$D$4:$J$146,'Mat. List CSI'!G$1,0) -> 04 | H145: =VLOOKUP($E145,'Activity List CSI'!$D$4:$J$146,'Mat. List CSI'!H$1,0) -> BlockWork | I145: =VLOOKUP(D145,'Activity List CSI'!$C$4:$H$146,6,0) -> 04200 | J145: =VLOOKUP($E145,'Activity List CSI'!$D$4:$J$146,'Mat. List CSI'!J$1,0) -> Masonary Units | K145: Sand | L145: 110 | M145: =I145&L145 -> 04200110 | N145: =M145 -> 04200110
D146: 0401 | E146: =VLOOKUP(F146,'Activity List CSI'!$B$4:$D$146,3,0) -> 04200-01 | F146: Block Work | G146: =VLOOKUP($E146,'Activity List CSI'!$D$4:$J$146,'Mat. List CSI'!G$1,0) -> 04 | H146: =VLOOKUP($E146,'Activity List CSI'!$D$4:$J$146,'Mat. List CSI'!H$1,0) -> BlockWork | I146: =VLOOKUP(D146,'Activity List CSI'!$C$4:$H$146,6,0) -> 04200 | J146: =VLOOKUP($E146,'Activity List CSI'!$D$4:$J$146,'Mat. List CSI'!J$1,0) -> Masonary Units | K146: Solid Blocks | L146: 115 | M146: =I146&L146 -> 04200115 | N146: =M146 -> 04200115
D147: 0401 | E147: =VLOOKUP(F147,'Activity List CSI'!$B$4:$D$146,3,0) -> 04200-01 | F147: Block Work | G147: =VLOOKUP($E147,'Activity List CSI'!$D$4:$J$146,'Mat. List CSI'!G$1,0) -> 04 | H147: =VLOOKUP($E147,'Activity List CSI'!$D$4:$J$146,'Mat. List CSI'!H$1,0) -> BlockWork | I147: =VLOOKUP(D147,'Activity List CSI'!$C$4:$H$146,6,0) -> 04200 | J147: =VLOOKUP($E147,'Activity List CSI'!$D$4:$J$146,'Mat. List CSI'!J$1,0) -> Masonary Units | K147: Block Accessories | L147: 125 | M147: =I147&L147 -> 04200125 | N147: =M147 -> 04200125
D148: 0401 | E148: =VLOOKUP(F148,'Activity List CSI'!$B$4:$D$146,3,0) -> 04200-01 | F148: Block Work | G148: =VLOOKUP($E148,'Activity List CSI'!$D$4:$J$146,'Mat. List CSI'!G$1,0) -> 04 | H148: =VLOOKUP($E148,'Activity List CSI'!$D$4:$J$146,'Mat. List CSI'!H$1,0) -> BlockWork | I148: =VLOOKUP(D148,'Activity List CSI'!$C$4:$H$146,6,0) -> 04200 | J148: =VLOOKUP($E148,'Activity List CSI'!$D$4:$J$146,'Mat. List CSI'!J$1,0) -> Masonary Units | K148: Cement | L148: 105 | M148: =I148&L148 -> 04200105 | N148: 09200105
D149: 0401 | E149: =VLOOKUP(F149,'Activity List CSI'!$B$4:$D$146,3,0) -> 04200-01 | F149: Block Work | G149: =VLOOKUP($E149,'Activity List CSI'!$D$4:$J$146,'Mat. List CSI'!G$1,0) -> 04 | H149: =VLOOKUP($E149,'Activity List CSI'!$D$4:$J$146,'Mat. List CSI'!H$1,0) -> BlockWork | I149: =VLOOKUP(D149,'Activity List CSI'!$C$4:$H$146,6,0) -> 04200 | J149: =VLOOKUP($E149,'Activity List CSI'!$D$4:$J$146,'Mat. List CSI'!J$1,0) -> Masonary Units | K149: Sand | L149: 110 | M149: =I149&L149 -> 04200110 | N149: =M149 -> 04200110
D150: 0402 | E150: =VLOOKUP(F150,'Activity List CSI'!$B$4:$D$146,3,0) -> 04200-02 | F150: Brick Work | G150: =VLOOKUP($E150,'Activity List CSI'!$D$4:$J$146,'Mat. List CSI'!G$1,0) -> 04 | H150: =VLOOKUP($E150,'Activity List CSI'!$D$4:$J$146,'Mat. List CSI'!H$1,0) -> BlockWork | I150: =VLOOKUP(D150,'Activity List CSI'!$C$4:$H$146,6,0) -> 04200 | J150: =VLOOKUP($E150,'Activity List CSI'!$D$4:$J$146,'Mat. List CSI'!J$1,0) -> Masonary Units | K150: Solid Blocks | L150: 115 | M150: =I150&L150 -> 04200115 | N150: =M150 -> 04200115
D151: 0402 | E151: =VLOOKUP(F151,'Activity List CSI'!$B$4:$D$146,3,0) -> 04200-02 | F151: Brick Work | G151: =VLOOKUP($E151,'Activity List CSI'!$D$4:$J$146,'Mat. List CSI'!G$1,0) -> 04 | H151: =VLOOKUP($E151,'Activity List CSI'!$D$4:$J$146,'Mat. List CSI'!H$1,0) -> BlockWork | I151: =VLOOKUP(D151,'Activity List CSI'!$C$4:$H$146,6,0) -> 04200 | J151: =VLOOKUP($E151,'Activity List CSI'!$D$4:$J$146,'Mat. List CSI'!J$1,0) -> Masonary Units | K151: Block Accessories | L151: 125 | M151: =I151&L151 -> 04200125 | N151: =M151 -> 04200125
D152: 0402 | E152: =VLOOKUP(F152,'Activity List CSI'!$B$4:$D$146,3,0) -> 04200-02 | F152: Brick Work | G152: =VLOOKUP($E152,'Activity List CSI'!$D$4:$J$146,'Mat. List CSI'!G$1,0) -> 04 | H152: =VLOOKUP($E152,'Activity List CSI'!$D$4:$J$146,'Mat. List CSI'!H$1,0) -> BlockWork | I152: =VLOOKUP(D152,'Activity List CSI'!$C$4:$H$146,6,0) -> 04200 | J152: =VLOOKUP($E152,'Activity List CSI'!$D$4:$J$146,'Mat. List CSI'!J$1,0) -> Masonary Units | K152: Cement | L152: 105 | M152: =I152&L152 -> 04200105 | N152: 09200105
D153: 0402 | E153: =VLOOKUP(F153,'Activity List CSI'!$B$4:$D$146,3,0) -> 04200-02 | F153: Brick Work | G153: =VLOOKUP($E153,'Activity List CSI'!$D$4:$J$146,'Mat. List CSI'!G$1,0) -> 04 | H153: =VLOOKUP($E153,'Activity List CSI'!$D$4:$J$146,'Mat. List CSI'!H$1,0) -> BlockWork | I153: =VLOOKUP(D153,'Activity List CSI'!$C$4:$H$146,6,0) -> 04200 | J153: =VLOOKUP($E153,'Activity List CSI'!$D$4:$J$146,'Mat. List CSI'!J$1,0) -> Masonary Units | K153: Sand | L153: 110 | M153: =I153&L153 -> 04200110 | N153: =M153 -> 04200110
D154: 0402 | E154: =VLOOKUP(F154,'Activity List CSI'!$B$4:$D$146,3,0) -> 04200-02 | F154: Brick Work | G154: =VLOOKUP($E154,'Activity List CSI'!$D$4:$J$146,'Mat. List CSI'!G$1,0) -> 04 | H154: =VLOOKUP($E154,'Activity List CSI'!$D$4:$J$146,'Mat. List CSI'!H$1,0) -> BlockWork | I154: =VLOOKUP(D154,'Activity List CSI'!$C$4:$H$146,6,0) -> 04200 | J154: =VLOOKUP($E154,'Activity List CSI'!$D$4:$J$146,'Mat. List CSI'!J$1,0) -> Masonary Units | K154: Solid Blocks | L154: 115 | M154: =I154&L154 -> 04200115 | N154: =M154 -> 04200115
D155: 0402 | E155: =VLOOKUP(F155,'Activity List CSI'!$B$4:$D$146,3,0) -> 04200-02 | F155: Brick Work | G155: =VLOOKUP($E155,'Activity List CSI'!$D$4:$J$146,'Mat. List CSI'!G$1,0) -> 04 | H155: =VLOOKUP($E155,'Activity List CSI'!$D$4:$J$146,'Mat. List CSI'!H$1,0) -> BlockWork | I155: =VLOOKUP(D155,'Activity List CSI'!$C$4:$H$146,6,0) -> 04200 | J155: =VLOOKUP($E155,'Activity List CSI'!$D$4:$J$146,'Mat. List CSI'!J$1,0) -> Masonary Units | K155: Block Accessories | L155: 125 | M155: =I155&L155 -> 04200125 | N155: =M155 -> 04200125
D156: 0402 | E156: =VLOOKUP(F156,'Activity List CSI'!$B$4:$D$146,3,0) -> 04200-02 | F156: Brick Work | G156: =VLOOKUP($E156,'Activity List CSI'!$D$4:$J$146,'Mat. List CSI'!G$1,0) -> 04 | H156: =VLOOKUP($E156,'Activity List CSI'!$D$4:$J$146,'Mat. List CSI'!H$1,0) -> BlockWork | I156: =VLOOKUP(D156,'Activity List CSI'!$C$4:$H$146,6,0) -> 04200 | J156: =VLOOKUP($E156,'Activity List CSI'!$D$4:$J$146,'Mat. List CSI'!J$1,0) -> Masonary Units | K156: Cement | L156: 105 | M156: =I156&L156 -> 04200105 | N156: 09200105
D157: 0402 | E157: =VLOOKUP(F157,'Activity List CSI'!$B$4:$D$146,3,0) -> 04200-02 | F157: Brick Work | G157: =VLOOKUP($E157,'Activity List CSI'!$D$4:$J$146,'Mat. List CSI'!G$1,0) -> 04 | H157: =VLOOKUP($E157,'Activity List CSI'!$D$4:$J$146,'Mat. List CSI'!H$1,0) -> BlockWork | I157: =VLOOKUP(D157,'Activity List CSI'!$C$4:$H$146,6,0) -> 04200 | J157: =VLOOKUP($E157,'Activity List CSI'!$D$4:$J$146,'Mat. List CSI'!J$1,0) -> Masonary Units | K157: Sand | L157: 110 | M157: =I157&L157 -> 04200110 | N157: =M157 -> 04200110
D158: 0403 | E158: =VLOOKUP(F158,'Activity List CSI'!$B$4:$D$146,3,0) -> 04400-01 | F158: Riprap Work | G158: =VLOOKUP($E158,'Activity List CSI'!$D$4:$J$146,'Mat. List CSI'!G$1,0) -> 04 | H158: =VLOOKUP($E158,'Activity List CSI'!$D$4:$J$146,'Mat. List CSI'!H$1,0) -> BlockWork | I158: =VLOOKUP(D158,'Activity List CSI'!$C$4:$H$146,6,0) -> 04400 | J158: =VLOOKUP($E158,'Activity List CSI'!$D$4:$J$146,'Mat. List CSI'!J$1,0) -> Stone | K158: Stone brick | L158: 105 | M158: =I158&L158 -> 04400105 | N158: =M158 -> 04400105
D159: 0403 | E159: =VLOOKUP(F159,'Activity List CSI'!$B$4:$D$146,3,0) -> 04400-01 | F159: Riprap Work | G159: =VLOOKUP($E159,'Activity List CSI'!$D$4:$J$146,'Mat. List CSI'!G$1,0) -> 04 | H159: =VLOOKUP($E159,'Activity List CSI'!$D$4:$J$146,'Mat. List CSI'!H$1,0) -> BlockWork | I159: =VLOOKUP(D159,'Activity List CSI'!$C$4:$H$146,6,0) -> 04400 | J159: =VLOOKUP($E159,'Activity List CSI'!$D$4:$J$146,'Mat. List CSI'!J$1,0) -> Stone | K159: Stone brick | L159: 105 | M159: =I159&L159 -> 04400105 | N159: =M159 -> 04400105
D160: 0701 | E160: =VLOOKUP(F160,'Activity List CSI'!$B$4:$D$146,3,0) -> 07100-01 | F160: Bituminous Dam proofing Work | G160: =VLOOKUP($E160,'Activity List CSI'!$D$4:$J$146,'Mat. List CSI'!G$1,0) -> 07 | H160: =VLOOKUP($E160,'Activity List CSI'!$D$4:$J$146,'Mat. List CSI'!H$1,0) -> Insulation | I160: =VLOOKUP(D160,'Activity List CSI'!$C$4:$H$146,6,0) -> 07100 | J160: =VLOOKUP($E160,'Activity List CSI'!$D$4:$J$146,'Mat. List CSI'!J$1,0) -> Damproofing & Waterproofing | K160: Bituminous | L160: 105 | M160: =I160&L160 -> 07100105 | N160: =M160 -> 07100105
D161: 0701 | E161: =VLOOKUP(F161,'Activity List CSI'!$B$4:$D$146,3,0) -> 07100-01 | F161: Bituminous Dam proofing Work | G161: =VLOOKUP($E161,'Activity List CSI'!$D$4:$J$146,'Mat. List CSI'!G$1,0) -> 07 | H161: =VLOOKUP($E161,'Activity List CSI'!$D$4:$J$146,'Mat. List CSI'!H$1,0) -> Insulation | I161: =VLOOKUP(D161,'Activity List CSI'!$C$4:$H$146,6,0) -> 07100 | J161: =VLOOKUP($E161,'Activity List CSI'!$D$4:$J$146,'Mat. List CSI'!J$1,0) -> Damproofing & Waterproofing | K161: Bituminous | L161: 105 | M161: =I161&L161 -> 07100105 | N161: =M161 -> 07100105
D162: 0702 | E162: =VLOOKUP(F162,'Activity List CSI'!$B$4:$D$146,3,0) -> 07100-02 | F162: Membrane Waterproofing | G162: =VLOOKUP($E162,'Activity List CSI'!$D$4:$J$146,'Mat. List CSI'!G$1,0) -> 07 | H162: =VLOOKUP($E162,'Activity List CSI'!$D$4:$J$146,'Mat. List CSI'!H$1,0) -> Insulation | I162: =VLOOKUP(D162,'Activity List CSI'!$C$4:$H$146,6,0) -> 07100 | J162: =VLOOKUP($E162,'Activity List CSI'!$D$4:$J$146,'Mat. List CSI'!J$1,0) -> Damproofing & Waterproofing | K162: Bituminous Membrane | L162: 110 | M162: =I162&L162 -> 07100110 | N162: =M162 -> 07100110
D163: 0702 | E163: =VLOOKUP(F163,'Activity List CSI'!$B$4:$D$146,3,0) -> 07100-02 | F163: Membrane Waterproofing | G163: =VLOOKUP($E163,'Activity List CSI'!$D$4:$J$146,'Mat. List CSI'!G$1,0) -> 07 | H163: =VLOOKUP($E163,'Activity List CSI'!$D$4:$J$146,'Mat. List CSI'!H$1,0) -> Insulation | I163: =VLOOKUP(D163,'Activity List CSI'!$C$4:$H$146,6,0) -> 07100 | J163: =VLOOKUP($E163,'Activity List CSI'!$D$4:$J$146,'Mat. List CSI'!J$1,0) -> Damproofing & Waterproofing | K163: Bituminous Membrane | L163: 110 | M163: =I163&L163 -> 07100110 | N163: =M163 -> 07100110
D164: 0703 | E164: =VLOOKUP(F164,'Activity List CSI'!$B$4:$D$146,3,0) -> 07100-03 | F164: Vabour Barriers | G164: =VLOOKUP($E164,'Activity List CSI'!$D$4:$J$146,'Mat. List CSI'!G$1,0) -> 07 | H164: =VLOOKUP($E164,'Activity List CSI'!$D$4:$J$146,'Mat. List CSI'!H$1,0) -> Insulation | I164: =VLOOKUP(D164,'Activity List CSI'!$C$4:$H$146,6,0) -> 07100 | J164: =VLOOKUP($E164,'Activity List CSI'!$D$4:$J$146,'Mat. List CSI'!J$1,0) -> Damproofing & Waterproofing | K164: Polly Ethilline Sheets | L164: 115 | M164: =I164&L164 -> 07100115 | N164: =M164 -> 07100115
D165: 0703 | E165: =VLOOKUP(F165,'Activity List CSI'!$B$4:$D$146,3,0) -> 07100-03 | F165: Vabour Barriers | G165: =VLOOKUP($E165,'Activity List CSI'!$D$4:$J$146,'Mat. List CSI'!G$1,0) -> 07 | H165: =VLOOKUP($E165,'Activity List CSI'!$D$4:$J$146,'Mat. List CSI'!H$1,0) -> Insulation | I165: =VLOOKUP(D165,'Activity List CSI'!$C$4:$H$146,6,0) -> 07100 | J165: =VLOOKUP($E165,'Activity List CSI'!$D$4:$J$146,'Mat. List CSI'!J$1,0) -> Damproofing & Waterproofing | K165: Polly Ethilline Sheets | L165: 115 | M165: =I165&L165 -> 07100115 | N165: =M165 -> 07100115
D166: 0704 | E166: =VLOOKUP(F166,'Activity List CSI'!$B$4:$D$146,3,0) -> 07100-04 | F166: Walls Vabour Retarders | G166: =VLOOKUP($E166,'Activity List CSI'!$D$4:$J$146,'Mat. List CSI'!G$1,0) -> 07 | H166: =VLOOKUP($E166,'Activity List CSI'!$D$4:$J$146,'Mat. List CSI'!H$1,0) -> Insulation | I166: =VLOOKUP(D166,'Activity List CSI'!$C$4:$H$146,6,0) -> 07100 | J166: =VLOOKUP($E166,'Activity List CSI'!$D$4:$J$146,'Mat. List CSI'!J$1,0) -> Damproofing & Waterproofing | K166: Polly Ethilline Sheets | L166: 115 | M166: =I166&L166 -> 07100115 | N166: =M166 -> 07100115
D167: 0704 | E167: =VLOOKUP(F167,'Activity List CSI'!$B$4:$D$146,3,0) -> 07100-04 | F167: Walls Vabour Retarders | G167: =VLOOKUP($E167,'Activity List CSI'!$D$4:$J$146,'Mat. List CSI'!G$1,0) -> 07 | H167: =VLOOKUP($E167,'Activity List CSI'!$D$4:$J$146,'Mat. List CSI'!H$1,0) -> Insulation | I167: =VLOOKUP(D167,'Activity List CSI'!$C$4:$H$146,6,0) -> 07100 | J167: =VLOOKUP($E167,'Activity List CSI'!$D$4:$J$146,'Mat. List CSI'!J$1,0) -> Damproofing & Waterproofing | K167: Polly Ethilline Sheets | L167: 115 | M167: =I167&L167 -> 07100115 | N167: =M167 -> 07100115
D168: 0705 | E168: =VLOOKUP(F168,'Activity List CSI'!$B$4:$D$146,3,0) -> 07200-01 | F168: Rigid Thermal Insulation | G168: =VLOOKUP($E168,'Activity List CSI'!$D$4:$J$146,'Mat. List CSI'!G$1,0) -> 07 | H168: =VLOOKUP($E168,'Activity List CSI'!$D$4:$J$146,'Mat. List CSI'!H$1,0) -> Insulation | I168: =VLOOKUP(D168,'Activity List CSI'!$C$4:$H$146,6,0) -> 07200 | J168: =VLOOKUP($E168,'Activity List CSI'!$D$4:$J$146,'Mat. List CSI'!J$1,0) -> Thermal Protection | K168: Soild Thermal Insulation | L168: 110 | M168: =I168&L168 -> 07200110 | N168: =M168 -> 07200110
D169: 0705 | E169: =VLOOKUP(F169,'Activity List CSI'!$B$4:$D$146,3,0) -> 07200-01 | F169: Rigid Thermal Insulation | G169: =VLOOKUP($E169,'Activity List CSI'!$D$4:$J$146,'Mat. List CSI'!G$1,0) -> 07 | H169: =VLOOKUP($E169,'Activity List CSI'!$D$4:$J$146,'Mat. List CSI'!H$1,0) -> Insulation | I169: =VLOOKUP(D169,'Activity List CSI'!$C$4:$H$146,6,0) -> 07200 | J169: =VLOOKUP($E169,'Activity List CSI'!$D$4:$J$146,'Mat. List CSI'!J$1,0) -> Thermal Protection | K169: Soild Thermal Insulation | L169: 110 | M169: =I169&L169 -> 07200110 | N169: =M169 -> 07200110
D170: 0706 | E170: =VLOOKUP(F170,'Activity List CSI'!$B$4:$D$146,3,0) -> 07400-01 | F170: Roofing System | G170: =VLOOKUP($E170,'Activity List CSI'!$D$4:$J$146,'Mat. List CSI'!G$1,0) -> 07 | H170: =VLOOKUP($E170,'Activity List CSI'!$D$4:$J$146,'Mat. List CSI'!H$1,0) -> Insulation | I170: =VLOOKUP(D170,'Activity List CSI'!$C$4:$H$146,6,0) -> 07400 | J170: =VLOOKUP($E170,'Activity List CSI'!$D$4:$J$146,'Mat. List CSI'!J$1,0) -> Roofing & Siding Panels | K170: Bituminous | L170: 105 | M170: =I170&L170 -> 07400105 | N170: =M161 -> 07100105
D171: 0706 | E171: =VLOOKUP(F171,'Activity List CSI'!$B$4:$D$146,3,0) -> 07400-01 | F171: Roofing System | G171: =VLOOKUP($E171,'Activity List CSI'!$D$4:$J$146,'Mat. List CSI'!G$1,0) -> 07 | H171: =VLOOKUP($E171,'Activity List CSI'!$D$4:$J$146,'Mat. List CSI'!H$1,0) -> Insulation | I171: =VLOOKUP(D171,'Activity List CSI'!$C$4:$H$146,6,0) -> 07400 | J171: =VLOOKUP($E171,'Activity List CSI'!$D$4:$J$146,'Mat. List CSI'!J$1,0) -> Roofing & Siding Panels | K171: Bituminous Membrane | L171: 110 | M171: =I171&L171 -> 07400110 | N171: =M163 -> 07100110
D172: 0706 | E172: =VLOOKUP(F172,'Activity List CSI'!$B$4:$D$146,3,0) -> 07400-01 | F172: Roofing System | G172: =VLOOKUP($E172,'Activity List CSI'!$D$4:$J$146,'Mat. List CSI'!G$1,0) -> 07 | H172: =VLOOKUP($E172,'Activity List CSI'!$D$4:$J$146,'Mat. List CSI'!H$1,0) -> Insulation | I172: =VLOOKUP(D172,'Activity List CSI'!$C$4:$H$146,6,0) -> 07400 | J172: =VLOOKUP($E172,'Activity List CSI'!$D$4:$J$146,'Mat. List CSI'!J$1,0) -> Roofing & Siding Panels | K172: Soild Thermal Insulation | L172: 110 | M172: =I172&L172 -> 07400110 | N172: 07200110
D173: 0706 | E173: =VLOOKUP(F173,'Activity List CSI'!$B$4:$D$146,3,0) -> 07400-01 | F173: Roofing System | G173: =VLOOKUP($E173,'Activity List CSI'!$D$4:$J$146,'Mat. List CSI'!G$1,0) -> 07 | H173: =VLOOKUP($E173,'Activity List CSI'!$D$4:$J$146,'Mat. List CSI'!H$1,0) -> Insulation | I173: =VLOOKUP(D173,'Activity List CSI'!$C$4:$H$146,6,0) -> 07400 | J173: =VLOOKUP($E173,'Activity List CSI'!$D$4:$J$146,'Mat. List CSI'!J$1,0) -> Roofing & Siding Panels | K173: Bituminous | L173: 105 | M173: =I173&L173 -> 07400105 | N173: =M161 -> 07100105
D174: 0706 | E174: =VLOOKUP(F174,'Activity List CSI'!$B$4:$D$146,3,0) -> 07400-01 | F174: Roofing System | G174: =VLOOKUP($E174,'Activity List CSI'!$D$4:$J$146,'Mat. List CSI'!G$1,0) -> 07 | H174: =VLOOKUP($E174,'Activity List CSI'!$D$4:$J$146,'Mat. List CSI'!H$1,0) -> Insulation | I174: =VLOOKUP(D174,'Activity List CSI'!$C$4:$H$146,6,0) -> 07400 | J174: =VLOOKUP($E174,'Activity List CSI'!$D$4:$J$146,'Mat. List CSI'!J$1,0) -> Roofing & Siding Panels | K174: Bituminous Membrane | L174: 110 | M174: =I174&L174 -> 07400110 | N174: =M162 -> 07100110
D175: 0706 | E175: =VLOOKUP(F175,'Activity List CSI'!$B$4:$D$146,3,0) -> 07400-01 | F175: Roofing System | G175: =VLOOKUP($E175,'Activity List CSI'!$D$4:$J$146,'Mat. List CSI'!G$1,0) -> 07 | H175: =VLOOKUP($E175,'Activity List CSI'!$D$4:$J$146,'Mat. List CSI'!H$1,0) -> Insulation | I175: =VLOOKUP(D175,'Activity List CSI'!$C$4:$H$146,6,0) -> 07400 | J175: =VLOOKUP($E175,'Activity List CSI'!$D$4:$J$146,'Mat. List CSI'!J$1,0) -> Roofing & Siding Panels | K175: Soild Thermal Insulation | L175: 110 | M175: =I175&L175 -> 07400110 | N175: 07200110
D176: 0709 | E176: =VLOOKUP(F176,'Activity List CSI'!$B$4:$D$146,3,0) -> 07200-03 | F176: Foam Concrete Work | G176: =VLOOKUP($E176,'Activity List CSI'!$D$4:$J$146,'Mat. List CSI'!G$1,0) -> 07 | H176: =VLOOKUP($E176,'Activity List CSI'!$D$4:$J$146,'Mat. List CSI'!H$1,0) -> Insulation | I176: =VLOOKUP(D176,'Activity List CSI'!$C$4:$H$146,6,0) -> 07200 | J176: =VLOOKUP($E176,'Activity List CSI'!$D$4:$J$146,'Mat. List CSI'!J$1,0) -> Thermal Protection | K176: Foamy Concrete | L176: 105 | M176: =I176&L176 -> 07200105 | N176: =M176 -> 07200105
D177: 0901 | E177: =VLOOKUP(F177,'Activity List CSI'!$B$4:$D$146,3,0) -> 09600-01 | F177: Epoxy Painting For Flooring | G177: =VLOOKUP($E177,'Activity List CSI'!$D$4:$J$146,'Mat. List CSI'!G$1,0) -> 09 | H177: =VLOOKUP($E177,'Activity List CSI'!$D$4:$J$146,'Mat. List CSI'!H$1,0) -> Finishing | I177: =VLOOKUP(D177,'Activity List CSI'!$C$4:$H$146,6,0) -> 09600 | J177: =VLOOKUP($E177,'Activity List CSI'!$D$4:$J$146,'Mat. List CSI'!J$1,0) -> Flooring | K177: Epoxy Paint Material | L177: 105 | M177: =I177&L177 -> 09600105 | N177: =M177 -> 09600105
D178: 0901 | E178: =VLOOKUP(F178,'Activity List CSI'!$B$4:$D$146,3,0) -> 09600-01 | F178: Epoxy Painting For Flooring | G178: =VLOOKUP($E178,'Activity List CSI'!$D$4:$J$146,'Mat. List CSI'!G$1,0) -> 09 | H178: =VLOOKUP($E178,'Activity List CSI'!$D$4:$J$146,'Mat. List CSI'!H$1,0) -> Finishing | I178: =VLOOKUP(D178,'Activity List CSI'!$C$4:$H$146,6,0) -> 09600 | J178: =VLOOKUP($E178,'Activity List CSI'!$D$4:$J$146,'Mat. List CSI'!J$1,0) -> Flooring | K178: Epoxy Paint Material | L178: 105 | M178: =I178&L178 -> 09600105 | N178: =M178 -> 09600105
D179: 0902 | E179: =VLOOKUP(F179,'Activity List CSI'!$B$4:$D$146,3,0) -> 09600-02 | F179: Carpet | G179: =VLOOKUP($E179,'Activity List CSI'!$D$4:$J$146,'Mat. List CSI'!G$1,0) -> 09 | H179: =VLOOKUP($E179,'Activity List CSI'!$D$4:$J$146,'Mat. List CSI'!H$1,0) -> Finishing | I179: =VLOOKUP(D179,'Activity List CSI'!$C$4:$H$146,6,0) -> 09600 | J179: =VLOOKUP($E179,'Activity List CSI'!$D$4:$J$146,'Mat. List CSI'!J$1,0) -> Flooring | K179: Cement | L179: 105 | M179: =I179&L179 -> 09600105 | N179: 09200105
D180: 0902 | E180: =VLOOKUP(F180,'Activity List CSI'!$B$4:$D$146,3,0) -> 09600-02 | F180: Carpet | G180: =VLOOKUP($E180,'Activity List CSI'!$D$4:$J$146,'Mat. List CSI'!G$1,0) -> 09 | H180: =VLOOKUP($E180,'Activity List CSI'!$D$4:$J$146,'Mat. List CSI'!H$1,0) -> Finishing | I180: =VLOOKUP(D180,'Activity List CSI'!$C$4:$H$146,6,0) -> 09600 | J180: =VLOOKUP($E180,'Activity List CSI'!$D$4:$J$146,'Mat. List CSI'!J$1,0) -> Flooring | K180: Sand | L180: 110 | M180: =I180&L180 -> 09600110 | N180: 04200110
D181: 0902 | E181: =VLOOKUP(F181,'Activity List CSI'!$B$4:$D$146,3,0) -> 09600-02 | F181: Carpet | G181: =VLOOKUP($E181,'Activity List CSI'!$D$4:$J$146,'Mat. List CSI'!G$1,0) -> 09 | H181: =VLOOKUP($E181,'Activity List CSI'!$D$4:$J$146,'Mat. List CSI'!H$1,0) -> Finishing | I181: =VLOOKUP(D181,'Activity List CSI'!$C$4:$H$146,6,0) -> 09600 | J181: =VLOOKUP($E181,'Activity List CSI'!$D$4:$J$146,'Mat. List CSI'!J$1,0) -> Flooring | K181: Carpet Tiles | L181: 110 | M181: =I181&L181 -> 09600110 | N181: =M181 -> 09600110
D182: 0902 | E182: =VLOOKUP(F182,'Activity List CSI'!$B$4:$D$146,3,0) -> 09600-02 | F182: Carpet | G182: =VLOOKUP($E182,'Activity List CSI'!$D$4:$J$146,'Mat. List CSI'!G$1,0) -> 09 | H182: =VLOOKUP($E182,'Activity List CSI'!$D$4:$J$146,'Mat. List CSI'!H$1,0) -> Finishing | I182: =VLOOKUP(D182,'Activity List CSI'!$C$4:$H$146,6,0) -> 09600 | J182: =VLOOKUP($E182,'Activity List CSI'!$D$4:$J$146,'Mat. List CSI'!J$1,0) -> Flooring | K182: Cement | L182: 105 | M182: =I182&L182 -> 09600105 | N182: 09200105
D183: 0902 | E183: =VLOOKUP(F183,'Activity List CSI'!$B$4:$D$146,3,0) -> 09600-02 | F183: Carpet | G183: =VLOOKUP($E183,'Activity List CSI'!$D$4:$J$146,'Mat. List CSI'!G$1,0) -> 09 | H183: =VLOOKUP($E183,'Activity List CSI'!$D$4:$J$146,'Mat. List CSI'!H$1,0) -> Finishing | I183: =VLOOKUP(D183,'Activity List CSI'!$C$4:$H$146,6,0) -> 09600 | J183: =VLOOKUP($E183,'Activity List CSI'!$D$4:$J$146,'Mat. List CSI'!J$1,0) -> Flooring | K183: Sand | L183: 110 | M183: =I183&L183 -> 09600110 | N183: 04200110
D184: 0902 | E184: =VLOOKUP(F184,'Activity List CSI'!$B$4:$D$146,3,0) -> 09600-02 | F184: Carpet | G184: =VLOOKUP($E184,'Activity List CSI'!$D$4:$J$146,'Mat. List CSI'!G$1,0) -> 09 | H184: =VLOOKUP($E184,'Activity List CSI'!$D$4:$J$146,'Mat. List CSI'!H$1,0) -> Finishing | I184: =VLOOKUP(D184,'Activity List CSI'!$C$4:$H$146,6,0) -> 09600 | J184: =VLOOKUP($E184,'Activity List CSI'!$D$4:$J$146,'Mat. List CSI'!J$1,0) -> Flooring | K184: Carpet Tiles | L184: 110 | M184: =I184&L184 -> 09600110 | N184: =M184 -> 09600110
D185: 0903 | E185: =VLOOKUP(F185,'Activity List CSI'!$B$4:$D$146,3,0) -> 09600-03 | F185: Ceramic Tiles | G185: =VLOOKUP($E185,'Activity List CSI'!$D$4:$J$146,'Mat. List CSI'!G$1,0) -> 09 | H185: =VLOOKUP($E185,'Activity List CSI'!$D$4:$J$146,'Mat. List CSI'!H$1,0) -> Finishing | I185: =VLOOKUP(D185,'Activity List CSI'!$C$4:$H$146,6,0) -> 09600 | J185: =VLOOKUP($E185,'Activity List CSI'!$D$4:$J$146,'Mat. List CSI'!J$1,0) -> Flooring | K185: Cement | L185: 105 | M185: =I185&L185 -> 09600105 | N185: 09200105
D186: 0903 | E186: =VLOOKUP(F186,'Activity List CSI'!$B$4:$D$146,3,0) -> 09600-03 | F186: Ceramic Tiles | G186: =VLOOKUP($E186,'Activity List CSI'!$D$4:$J$146,'Mat. List CSI'!G$1,0) -> 09 | H186: =VLOOKUP($E186,'Activity List CSI'!$D$4:$J$146,'Mat. List CSI'!H$1,0) -> Finishing | I186: =VLOOKUP(D186,'Activity List CSI'!$C$4:$H$146,6,0) -> 09600 | J186: =VLOOKUP($E186,'Activity List CSI'!$D$4:$J$146,'Mat. List CSI'!J$1,0) -> Flooring | K186: Sand | L186: 110 | M186: =I186&L186 -> 09600110 | N186: 04200110
D187: 0903 | E187: =VLOOKUP(F187,'Activity List CSI'!$B$4:$D$146,3,0) -> 09600-03 | F187: Ceramic Tiles | G187: =VLOOKUP($E187,'Activity List CSI'!$D$4:$J$146,'Mat. List CSI'!G$1,0) -> 09 | H187: =VLOOKUP($E187,'Activity List CSI'!$D$4:$J$146,'Mat. List CSI'!H$1,0) -> Finishing | I187: =VLOOKUP(D187,'Activity List CSI'!$C$4:$H$146,6,0) -> 09600 | J187: =VLOOKUP($E187,'Activity List CSI'!$D$4:$J$146,'Mat. List CSI'!J$1,0) -> Flooring | K187: Ceramic Tiles | L187: 130 | M187: =I187&L187 -> 09600130 | N187: =M187 -> 09600130
D188: 0903 | E188: =VLOOKUP(F188,'Activity List CSI'!$B$4:$D$146,3,0) -> 09600-03 | F188: Ceramic Tiles | G188: =VLOOKUP($E188,'Activity List CSI'!$D$4:$J$146,'Mat. List CSI'!G$1,0) -> 09 | H188: =VLOOKUP($E188,'Activity List CSI'!$D$4:$J$146,'Mat. List CSI'!H$1,0) -> Finishing | I188: =VLOOKUP(D188,'Activity List CSI'!$C$4:$H$146,6,0) -> 09600 | J188: =VLOOKUP($E188,'Activity List CSI'!$D$4:$J$146,'Mat. List CSI'!J$1,0) -> Flooring | K188: Cement | L188: 105 | M188: =I188&L188 -> 09600105 | N188: 09200105
D189: 0903 | E189: =VLOOKUP(F189,'Activity List CSI'!$B$4:$D$146,3,0) -> 09600-03 | F189: Ceramic Tiles | G189: =VLOOKUP($E189,'Activity List CSI'!$D$4:$J$146,'Mat. List CSI'!G$1,0) -> 09 | H189: =VLOOKUP($E189,'Activity List CSI'!$D$4:$J$146,'Mat. List CSI'!H$1,0) -> Finishing | I189: =VLOOKUP(D189,'Activity List CSI'!$C$4:$H$146,6,0) -> 09600 | J189: =VLOOKUP($E189,'Activity List CSI'!$D$4:$J$146,'Mat. List CSI'!J$1,0) -> Flooring | K189: Sand | L189: 110 | M189: =I189&L189 -> 09600110 | N189: 04200110
D190: 0903 | E190: =VLOOKUP(F190,'Activity List CSI'!$B$4:$D$146,3,0) -> 09600-03 | F190: Ceramic Tiles | G190: =VLOOKUP($E190,'Activity List CSI'!$D$4:$J$146,'Mat. List CSI'!G$1,0) -> 09 | H190: =VLOOKUP($E190,'Activity List CSI'!$D$4:$J$146,'Mat. List CSI'!H$1,0) -> Finishing | I190: =VLOOKUP(D190,'Activity List CSI'!$C$4:$H$146,6,0) -> 09600 | J190: =VLOOKUP($E190,'Activity List CSI'!$D$4:$J$146,'Mat. List CSI'!J$1,0) -> Flooring | K190: Ceramic Tiles | L190: 130 | M190: =I190&L190 -> 09600130 | N190: =M190 -> 09600130
D191: 0904 | E191: =VLOOKUP(F191,'Activity List CSI'!$B$4:$D$146,3,0) -> 09600-04 | F191: Marble Tiles | G191: =VLOOKUP($E191,'Activity List CSI'!$D$4:$J$146,'Mat. List CSI'!G$1,0) -> 09 | H191: =VLOOKUP($E191,'Activity List CSI'!$D$4:$J$146,'Mat. List CSI'!H$1,0) -> Finishing | I191: =VLOOKUP(D191,'Activity List CSI'!$C$4:$H$146,6,0) -> 09600 | J191: =VLOOKUP($E191,'Activity List CSI'!$D$4:$J$146,'Mat. List CSI'!J$1,0) -> Flooring | K191: Cement | L191: 105 | M191: =I191&L191 -> 09600105 | N191: 09200105
D192: 0904 | E192: =VLOOKUP(F192,'Activity List CSI'!$B$4:$D$146,3,0) -> 09600-04 | F192: Marble Tiles | G192: =VLOOKUP($E192,'Activity List CSI'!$D$4:$J$146,'Mat. List CSI'!G$1,0) -> 09 | H192: =VLOOKUP($E192,'Activity List CSI'!$D$4:$J$146,'Mat. List CSI'!H$1,0) -> Finishing | I192: =VLOOKUP(D192,'Activity List CSI'!$C$4:$H$146,6,0) -> 09600 | J192: =VLOOKUP($E192,'Activity List CSI'!$D$4:$J$146,'Mat. List CSI'!J$1,0) -> Flooring | K192: Sand | L192: 110 | M192: =I192&L192 -> 09600110 | N192: 04200110
D193: 0904 | E193: =VLOOKUP(F193,'Activity List CSI'!$B$4:$D$146,3,0) -> 09600-04 | F193: Marble Tiles | G193: =VLOOKUP($E193,'Activity List CSI'!$D$4:$J$146,'Mat. List CSI'!G$1,0) -> 09 | H193: =VLOOKUP($E193,'Activity List CSI'!$D$4:$J$146,'Mat. List CSI'!H$1,0) -> Finishing | I193: =VLOOKUP(D193,'Activity List CSI'!$C$4:$H$146,6,0) -> 09600 | J193: =VLOOKUP($E193,'Activity List CSI'!$D$4:$J$146,'Mat. List CSI'!J$1,0) -> Flooring | K193: Marble | L193: 160 | M193: =I193&L193 -> 09600160 | N193: =M193 -> 09600160
D194: 0904 | E194: =VLOOKUP(F194,'Activity List CSI'!$B$4:$D$146,3,0) -> 09600-04 | F194: Marble Tiles | G194: =VLOOKUP($E194,'Activity List CSI'!$D$4:$J$146,'Mat. List CSI'!G$1,0) -> 09 | H194: =VLOOKUP($E194,'Activity List CSI'!$D$4:$J$146,'Mat. List CSI'!H$1,0) -> Finishing | I194: =VLOOKUP(D194,'Activity List CSI'!$C$4:$H$146,6,0) -> 09600 | J194: =VLOOKUP($E194,'Activity List CSI'!$D$4:$J$146,'Mat. List CSI'!J$1,0) -> Flooring | K194: Cement | L194: 105 | M194: =I194&L194 -> 09600105 | N194: 09200105
D195: 0904 | E195: =VLOOKUP(F195,'Activity List CSI'!$B$4:$D$146,3,0) -> 09600-04 | F195: Marble Tiles | G195: =VLOOKUP($E195,'Activity List CSI'!$D$4:$J$146,'Mat. List CSI'!G$1,0) -> 09 | H195: =VLOOKUP($E195,'Activity List CSI'!$D$4:$J$146,'Mat. List CSI'!H$1,0) -> Finishing | I195: =VLOOKUP(D195,'Activity List CSI'!$C$4:$H$146,6,0) -> 09600 | J195: =VLOOKUP($E195,'Activity List CSI'!$D$4:$J$146,'Mat. List CSI'!J$1,0) -> Flooring | K195: Sand | L195: 110 | M195: =I195&L195 -> 09600110 | N195: 04200110
D196: 0904 | E196: =VLOOKUP(F196,'Activity List CSI'!$B$4:$D$146,3,0) -> 09600-04 | F196: Marble Tiles | G196: =VLOOKUP($E196,'Activity List CSI'!$D$4:$J$146,'Mat. List CSI'!G$1,0) -> 09 | H196: =VLOOKUP($E196,'Activity List CSI'!$D$4:$J$146,'Mat. List CSI'!H$1,0) -> Finishing | I196: =VLOOKUP(D196,'Activity List CSI'!$C$4:$H$146,6,0) -> 09600 | J196: =VLOOKUP($E196,'Activity List CSI'!$D$4:$J$146,'Mat. List CSI'!J$1,0) -> Flooring | K196: Marble | L196: 160 | M196: =I196&L196 -> 09600160 | N196: =M196 -> 09600160
D197: 0905 | E197: =VLOOKUP(F197,'Activity List CSI'!$B$4:$D$146,3,0) -> 09600-05 | F197: Wooden Flooring | G197: =VLOOKUP($E197,'Activity List CSI'!$D$4:$J$146,'Mat. List CSI'!G$1,0) -> 09 | H197: =VLOOKUP($E197,'Activity List CSI'!$D$4:$J$146,'Mat. List CSI'!H$1,0) -> Finishing | I197: =VLOOKUP(D197,'Activity List CSI'!$C$4:$H$146,6,0) -> 09600 | J197: =VLOOKUP($E197,'Activity List CSI'!$D$4:$J$146,'Mat. List CSI'!J$1,0) -> Flooring | K197: Wooden Flooring | L197: 170 | M197: =I197&L197 -> 09600170 | N197: =M197 -> 09600170
D198: 0905 | E198: =VLOOKUP(F198,'Activity List CSI'!$B$4:$D$146,3,0) -> 09600-05 | F198: Wooden Flooring | G198: =VLOOKUP($E198,'Activity List CSI'!$D$4:$J$146,'Mat. List CSI'!G$1,0) -> 09 | H198: =VLOOKUP($E198,'Activity List CSI'!$D$4:$J$146,'Mat. List CSI'!H$1,0) -> Finishing | I198: =VLOOKUP(D198,'Activity List CSI'!$C$4:$H$146,6,0) -> 09600 | J198: =VLOOKUP($E198,'Activity List CSI'!$D$4:$J$146,'Mat. List CSI'!J$1,0) -> Flooring | K198: Wooden Flooring | L198: 170 | M198: =I198&L198 -> 09600170 | N198: =M198 -> 09600170
D199: 0906 | E199: =VLOOKUP(F199,'Activity List CSI'!$B$4:$D$146,3,0) -> 09300-01 | F199: Cementious Tiles | G199: =VLOOKUP($E199,'Activity List CSI'!$D$4:$J$146,'Mat. List CSI'!G$1,0) -> 09 | H199: =VLOOKUP($E199,'Activity List CSI'!$D$4:$J$146,'Mat. List CSI'!H$1,0) -> Finishing | I199: =VLOOKUP(D199,'Activity List CSI'!$C$4:$H$146,6,0) -> 09300 | J199: =VLOOKUP($E199,'Activity List CSI'!$D$4:$J$146,'Mat. List CSI'!J$1,0) -> Tile | K199: Cement | L199: 105 | M199: =I199&L199 -> 09300105 | N199: 09200105
D200: 0906 | E200: =VLOOKUP(F200,'Activity List CSI'!$B$4:$D$146,3,0) -> 09300-01 | F200: Cementious Tiles | G200: =VLOOKUP($E200,'Activity List CSI'!$D$4:$J$146,'Mat. List CSI'!G$1,0) -> 09 | H200: =VLOOKUP($E200,'Activity List CSI'!$D$4:$J$146,'Mat. List CSI'!H$1,0) -> Finishing | I200: =VLOOKUP(D200,'Activity List CSI'!$C$4:$H$146,6,0) -> 09300 | J200: =VLOOKUP($E200,'Activity List CSI'!$D$4:$J$146,'Mat. List CSI'!J$1,0) -> Tile | K200: Sand | L200: 110 | M200: =I200&L200 -> 09300110 | N200: 04200110
D201: 0906 | E201: =VLOOKUP(F201,'Activity List CSI'!$B$4:$D$146,3,0) -> 09300-01 | F201: Cementious Tiles | G201: =VLOOKUP($E201,'Activity List CSI'!$D$4:$J$146,'Mat. List CSI'!G$1,0) -> 09 | H201: =VLOOKUP($E201,'Activity List CSI'!$D$4:$J$146,'Mat. List CSI'!H$1,0) -> Finishing | I201: =VLOOKUP(D201,'Activity List CSI'!$C$4:$H$146,6,0) -> 09300 | J201: =VLOOKUP($E201,'Activity List CSI'!$D$4:$J$146,'Mat. List CSI'!J$1,0) -> Tile | K201: Cementic Tiles | L201: 105 | M201: =I201&L201 -> 09300105 | N201: =M201 -> 09300105
D202: 0906 | E202: =VLOOKUP(F202,'Activity List CSI'!$B$4:$D$146,3,0) -> 09300-01 | F202: Cementious Tiles | G202: =VLOOKUP($E202,'Activity List CSI'!$D$4:$J$146,'Mat. List CSI'!G$1,0) -> 09 | H202: =VLOOKUP($E202,'Activity List CSI'!$D$4:$J$146,'Mat. List CSI'!H$1,0) -> Finishing | I202: =VLOOKUP(D202,'Activity List CSI'!$C$4:$H$146,6,0) -> 09300 | J202: =VLOOKUP($E202,'Activity List CSI'!$D$4:$J$146,'Mat. List CSI'!J$1,0) -> Tile | K202: Cement | L202: 105 | M202: =I202&L202 -> 09300105 | N202: 09200105
D203: 0906 | E203: =VLOOKUP(F203,'Activity List CSI'!$B$4:$D$146,3,0) -> 09300-01 | F203: Cementious Tiles | G203: =VLOOKUP($E203,'Activity List CSI'!$D$4:$J$146,'Mat. List CSI'!G$1,0) -> 09 | H203: =VLOOKUP($E203,'Activity List CSI'!$D$4:$J$146,'Mat. List CSI'!H$1,0) -> Finishing | I203: =VLOOKUP(D203,'Activity List CSI'!$C$4:$H$146,6,0) -> 09300 | J203: =VLOOKUP($E203,'Activity List CSI'!$D$4:$J$146,'Mat. List CSI'!J$1,0) -> Tile | K203: Sand | L203: 110 | M203: =I203&L203 -> 09300110 | N203: 04200110
D204: 0906 | E204: =VLOOKUP(F204,'Activity List CSI'!$B$4:$D$146,3,0) -> 09300-01 | F204: Cementious Tiles | G204: =VLOOKUP($E204,'Activity List CSI'!$D$4:$J$146,'Mat. List CSI'!G$1,0) -> 09 | H204: =VLOOKUP($E204,'Activity List CSI'!$D$4:$J$146,'Mat. List CSI'!H$1,0) -> Finishing | I204: =VLOOKUP(D204,'Activity List CSI'!$C$4:$H$146,6,0) -> 09300 | J204: =VLOOKUP($E204,'Activity List CSI'!$D$4:$J$146,'Mat. List CSI'!J$1,0) -> Tile | K204: Cementic Tiles | L204: 105 | M204: =I204&L204 -> 09300105 | N204: =M204 -> 09300105
D205: 0907 | E205: =VLOOKUP(F205,'Activity List CSI'!$B$4:$D$146,3,0) -> 09300-02 | F205: Vinil Tiles | G205: =VLOOKUP($E205,'Activity List CSI'!$D$4:$J$146,'Mat. List CSI'!G$1,0) -> 09 | H205: =VLOOKUP($E205,'Activity List CSI'!$D$4:$J$146,'Mat. List CSI'!H$1,0) -> Finishing | I205: =VLOOKUP(D205,'Activity List CSI'!$C$4:$H$146,6,0) -> 09300 | J205: =VLOOKUP($E205,'Activity List CSI'!$D$4:$J$146,'Mat. List CSI'!J$1,0) -> Tile | K205: Cement | L205: 105 | M205: =I205&L205 -> 09300105 | N205: 09200105
D206: 0907 | E206: =VLOOKUP(F206,'Activity List CSI'!$B$4:$D$146,3,0) -> 09300-02 | F206: Vinil Tiles | G206: =VLOOKUP($E206,'Activity List CSI'!$D$4:$J$146,'Mat. List CSI'!G$1,0) -> 09 | H206: =VLOOKUP($E206,'Activity List CSI'!$D$4:$J$146,'Mat. List CSI'!H$1,0) -> Finishing | I206: =VLOOKUP(D206,'Activity List CSI'!$C$4:$H$146,6,0) -> 09300 | J206: =VLOOKUP($E206,'Activity List CSI'!$D$4:$J$146,'Mat. List CSI'!J$1,0) -> Tile | K206: Sand | L206: 110 | M206: =I206&L206 -> 09300110 | N206: 04200110
D207: 0907 | E207: =VLOOKUP(F207,'Activity List CSI'!$B$4:$D$146,3,0) -> 09300-02 | F207: Vinil Tiles | G207: =VLOOKUP($E207,'Activity List CSI'!$D$4:$J$146,'Mat. List CSI'!G$1,0) -> 09 | H207: =VLOOKUP($E207,'Activity List CSI'!$D$4:$J$146,'Mat. List CSI'!H$1,0) -> Finishing | I207: =VLOOKUP(D207,'Activity List CSI'!$C$4:$H$146,6,0) -> 09300 | J207: =VLOOKUP($E207,'Activity List CSI'!$D$4:$J$146,'Mat. List CSI'!J$1,0) -> Tile | K207: Vinile Flooring | L207: 175 | M207: =I207&L207 -> 09300175 | N207: =M207 -> 09300175
D208: 0907 | E208: =VLOOKUP(F208,'Activity List CSI'!$B$4:$D$146,3,0) -> 09300-02 | F208: Vinil Tiles | G208: =VLOOKUP($E208,'Activity List CSI'!$D$4:$J$146,'Mat. List CSI'!G$1,0) -> 09 | H208: =VLOOKUP($E208,'Activity List CSI'!$D$4:$J$146,'Mat. List CSI'!H$1,0) -> Finishing | I208: =VLOOKUP(D208,'Activity List CSI'!$C$4:$H$146,6,0) -> 09300 | J208: =VLOOKUP($E208,'Activity List CSI'!$D$4:$J$146,'Mat. List CSI'!J$1,0) -> Tile | K208: Cement | L208: 105 | M208: =I208&L208 -> 09300105 | N208: 09200105
D209: 0907 | E209: =VLOOKUP(F209,'Activity List CSI'!$B$4:$D$146,3,0) -> 09300-02 | F209: Vinil Tiles | G209: =VLOOKUP($E209,'Activity List CSI'!$D$4:$J$146,'Mat. List CSI'!G$1,0) -> 09 | H209: =VLOOKUP($E209,'Activity List CSI'!$D$4:$J$146,'Mat. List CSI'!H$1,0) -> Finishing | I209: =VLOOKUP(D209,'Activity List CSI'!$C$4:$H$146,6,0) -> 09300 | J209: =VLOOKUP($E209,'Activity List CSI'!$D$4:$J$146,'Mat. List CSI'!J$1,0) -> Tile | K209: Sand | L209: 110 | M209: =I209&L209 -> 09300110 | N209: 04200110
D210: 0907 | E210: =VLOOKUP(F210,'Activity List CSI'!$B$4:$D$146,3,0) -> 09300-02 | F210: Vinil Tiles | G210: =VLOOKUP($E210,'Activity List CSI'!$D$4:$J$146,'Mat. List CSI'!G$1,0) -> 09 | H210: =VLOOKUP($E210,'Activity List CSI'!$D$4:$J$146,'Mat. List CSI'!H$1,0) -> Finishing | I210: =VLOOKUP(D210,'Activity List CSI'!$C$4:$H$146,6,0) -> 09300 | J210: =VLOOKUP($E210,'Activity List CSI'!$D$4:$J$146,'Mat. List CSI'!J$1,0) -> Tile | K210: Vinile Flooring | L210: 175 | M210: =I210&L210 -> 09300175 | N210: =M210 -> 09300175
D211: 0908 | E211: =VLOOKUP(F211,'Activity List CSI'!$B$4:$D$146,3,0) -> 09300-03 | F211: Marble Skirting | G211: =VLOOKUP($E211,'Activity List CSI'!$D$4:$J$146,'Mat. List CSI'!G$1,0) -> 09 | H211: =VLOOKUP($E211,'Activity List CSI'!$D$4:$J$146,'Mat. List CSI'!H$1,0) -> Finishing | I211: =VLOOKUP(D211,'Activity List CSI'!$C$4:$H$146,6,0) -> 09300 | J211: =VLOOKUP($E211,'Activity List CSI'!$D$4:$J$146,'Mat. List CSI'!J$1,0) -> Tile | K211: Cement | L211: 105 | M211: =I211&L211 -> 09300105 | N211: 09200105
D212: 0908 | E212: =VLOOKUP(F212,'Activity List CSI'!$B$4:$D$146,3,0) -> 09300-03 | F212: Marble Skirting | G212: =VLOOKUP($E212,'Activity List CSI'!$D$4:$J$146,'Mat. List CSI'!G$1,0) -> 09 | H212: =VLOOKUP($E212,'Activity List CSI'!$D$4:$J$146,'Mat. List CSI'!H$1,0) -> Finishing | I212: =VLOOKUP(D212,'Activity List CSI'!$C$4:$H$146,6,0) -> 09300 | J212: =VLOOKUP($E212,'Activity List CSI'!$D$4:$J$146,'Mat. List CSI'!J$1,0) -> Tile | K212: Sand | L212: 110 | M212: =I212&L212 -> 09300110 | N212: 04200110
D213: 0908 | E213: =VLOOKUP(F213,'Activity List CSI'!$B$4:$D$146,3,0) -> 09300-03 | F213: Marble Skirting | G213: =VLOOKUP($E213,'Activity List CSI'!$D$4:$J$146,'Mat. List CSI'!G$1,0) -> 09 | H213: =VLOOKUP($E213,'Activity List CSI'!$D$4:$J$146,'Mat. List CSI'!H$1,0) -> Finishing | I213: =VLOOKUP(D213,'Activity List CSI'!$C$4:$H$146,6,0) -> 09300 | J213: =VLOOKUP($E213,'Activity List CSI'!$D$4:$J$146,'Mat. List CSI'!J$1,0) -> Tile | K213: Marble | L213: 160 | M213: =I213&L213 -> 09300160 | N213: 09600160
D214: 0908 | E214: =VLOOKUP(F214,'Activity List CSI'!$B$4:$D$146,3,0) -> 09300-03 | F214: Marble Skirting | G214: =VLOOKUP($E214,'Activity List CSI'!$D$4:$J$146,'Mat. List CSI'!G$1,0) -> 09 | H214: =VLOOKUP($E214,'Activity List CSI'!$D$4:$J$146,'Mat. List CSI'!H$1,0) -> Finishing | I214: =VLOOKUP(D214,'Activity List CSI'!$C$4:$H$146,6,0) -> 09300 | J214: =VLOOKUP($E214,'Activity List CSI'!$D$4:$J$146,'Mat. List CSI'!J$1,0) -> Tile | K214: Cement | L214: 105 | M214: =I214&L214 -> 09300105 | N214: 09200105
D215: 0908 | E215: =VLOOKUP(F215,'Activity List CSI'!$B$4:$D$146,3,0) -> 09300-03 | F215: Marble Skirting | G215: =VLOOKUP($E215,'Activity List CSI'!$D$4:$J$146,'Mat. List CSI'!G$1,0) -> 09 | H215: =VLOOKUP($E215,'Activity List CSI'!$D$4:$J$146,'Mat. List CSI'!H$1,0) -> Finishing | I215: =VLOOKUP(D215,'Activity List CSI'!$C$4:$H$146,6,0) -> 09300 | J215: =VLOOKUP($E215,'Activity List CSI'!$D$4:$J$146,'Mat. List CSI'!J$1,0) -> Tile | K215: Sand | L215: 110 | M215: =I215&L215 -> 09300110 | N215: 04200110
D216: 0908 | E216: =VLOOKUP(F216,'Activity List CSI'!$B$4:$D$146,3,0) -> 09300-03 | F216: Marble Skirting | G216: =VLOOKUP($E216,'Activity List CSI'!$D$4:$J$146,'Mat. List CSI'!G$1,0) -> 09 | H216: =VLOOKUP($E216,'Activity List CSI'!$D$4:$J$146,'Mat. List CSI'!H$1,0) -> Finishing | I216: =VLOOKUP(D216,'Activity List CSI'!$C$4:$H$146,6,0) -> 09300 | J216: =VLOOKUP($E216,'Activity List CSI'!$D$4:$J$146,'Mat. List CSI'!J$1,0) -> Tile | K216: Marble | L216: 160 | M216: =I216&L216 -> 09300160 | N216: 09600160
D217: 0909 | E217: =VLOOKUP(F217,'Activity List CSI'!$B$4:$D$146,3,0) -> 09300-04 | F217: Wooden Skirting | G217: =VLOOKUP($E217,'Activity List CSI'!$D$4:$J$146,'Mat. List CSI'!G$1,0) -> 09 | H217: =VLOOKUP($E217,'Activity List CSI'!$D$4:$J$146,'Mat. List CSI'!H$1,0) -> Finishing | I217: =VLOOKUP(D217,'Activity List CSI'!$C$4:$H$146,6,0) -> 09300 | J217: =VLOOKUP($E217,'Activity List CSI'!$D$4:$J$146,'Mat. List CSI'!J$1,0) -> Tile | K217: Wooden Flooring | L217: 170 | M217: =I217&L217 -> 09300170 | N217: 09600170
...

Sheet Material Unique List
C2: Unique List For Material
C3: Material List | D3: Resource Main Code | E3: UOM | F3: Resource Category
C4: Antitermite Material | D4: =VLOOKUP(C4,'Mat. List CSI'!$K$4:$N$401,4,0) -> 02100105 | E4: Litre | F4: M
C5: Backfillig Material | D5: =VLOOKUP(C5,'Mat. List CSI'!$K$4:$N$401,4,0) -> 02300105 | E5: M3 | F5: M
C6: Asphalt | D6: =VLOOKUP(C6,'Mat. List CSI'!$K$4:$N$401,4,0) -> 02700105 | E6: M3 | F6: M
C7: Sub-Grade Material | D7: =VLOOKUP(C7,'Mat. List CSI'!$K$4:$N$401,4,0) -> 02700110 | E7: M3 | F7: M
C8: Sub-Base Material | D8: =VLOOKUP(C8,'Mat. List CSI'!$K$4:$N$401,4,0) -> 02700115 | E8: M3 | F8: M
C9: Base Material | D9: =VLOOKUP(C9,'Mat. List CSI'!$K$4:$N$401,4,0) -> 02700120 | E9: M3 | F9: M
C10: New gersy material | D10: =VLOOKUP(C10,'Mat. List CSI'!$K$4:$N$401,4,0) -> 02700125 | E10: L.M | F10: M
C11: MC Material | D11: =VLOOKUP(C11,'Mat. List CSI'!$K$4:$N$401,4,0) -> 02700130 | E11: Litre | F11: M
C12: RC Material | D12: =VLOOKUP(C12,'Mat. List CSI'!$K$4:$N$401,4,0) -> 02700135 | E12: Litre | F12: M
C13: Concrete Tiles | D13: =VLOOKUP(C13,'Mat. List CSI'!$K$4:$N$401,4,0) -> 02700140 | E13: M2 | F13: M
C14: Interlock Tiles | D14: =VLOOKUP(C14,'Mat. List CSI'!$K$4:$N$401,4,0) -> 02700145 | E14: M2 | F14: M
C15: Concrete Chemicals | D15: =VLOOKUP(C15,'Mat. List CSI'!$K$4:$N$401,4,0) -> 03300105 | E15: Litre | F15: M
... C73: Plumbing Fixtures | D73: =VLOOKUP(C73,'Mat. List CSI'!$K$4:$N$401,4,0) -> 15400105 | E73: EA | F73: M

Sheet Manpower List
B3: Coding System For Manual Manpower DataBase
B4: Div. Code | C4: Div Description | D4: CSI Code | E4: CSI Description | F4: Organization Position | G4: Resource Order | H4: Manpower Main Code | J4: Basic | K4: Transportation | L4: Housing | M4: Food Allowance | N4: Vacation Pay | O4: Bonus | P4: EOS Benefits | Q4: GOSI | R4: Air tickets | S4: medical | T4: Iqama Cost | U4: Work Permits | V4: Recruitment expenses | W4: Relocation allowance | X4: Visa cost | Y4: Total
B5: 01 | C5: General Requirement | D5: 01400 | E5: Quality Requirements | F5: Assistant Lab Technician | G5: 005 | H5: =D5&G5 -> 01400005 | J5: ='Manual Manpower Database'!AJ5 -> 1590 | K5: ='Manual Manpower Database'!AK5 -> 0 | L5: ='Manual Manpower Database'!AL5 -> 0 | M5: ='Manual Manpower Database'!AM5 -> 150 | N5: ='Manual Manpower Database'!AN5 -> 66.25 | O5: ='Manual Manpower Database'!AO5 -> 0 | P5: ='Manual Manpower Database'!AP5 -> 33.125 | Q5: ='Manual Manpower Database'!AQ5 -> 31.8 | ... X5: ='Manual Manpower Database'!AX5 -> 55.555556 | Y5: =SUM(J5:X5) -> 2364.2306
B6: 01 | C6: General Requirement | D6: 01500 | E6: Temporary facilities & Controls | F6: Assistant Store Keeper | G6: 003 | H6: =D6&G6 -> 01500003 | J6: ='Manual Manpower Database'!AJ6 -> 1083.7 | K6: ='Manual Manpower Database'!AK6 -> 0 | L6: ='Manual Manpower Database'!AL6 -> 0 | M6: ='Manual Manpower Database'!AM6 -> 200 | N6: ='Manual Manpower Database'!AN6 -> 45.154167 | O6: ='Manual Manpower Database'!AO6 -> 0 | P6: ='Manual Manpower Database'!AP6 -> 22.577083 | Q6: ='Manual Manpower Database'!AQ6 -> 21.674 | ... X6: ='Manual Manpower Database'!AX6 -> 55.555556 | Y6: =SUM(J6:X6) -> 1866.1608
B7: 01 | C7: General Requirement | D7: 01700 | E7: Execution Requirements | F7: Assistant Surveyor | G7: 003 | H7: =D7&G7 -> 01700003 | J7: ='Manual Manpower Database'!AJ7 -> 2170.5556 | K7: ='Manual Manpower Database'!AK7 -> 300 | L7: ='Manual Manpower Database'!AL7 -> 0 | M7: ='Manual Manpower Database'!AM7 -> 150 | N7: ='Manual Manpower Database'!AN7 -> 90.439815 | O7: ='Manual Manpower Database'!AO7 -> 0 | P7: ='Manual Manpower Database'!AP7 -> 45.219907 | Q7: ='Manual Manpower Database'!AQ7 -> 43.411111 | ... X7: ='Manual Manpower Database'!AX7 -> 55.555556 | Y7: =SUM(J7:X7) -> 3292.6819
B8: 02 | C8: Site Construction | D8: 02900 | E8: Planting | F8: Batching Plant Maintenance Supervisor | G8: 005 | H8: =D8&G8 -> 02900005 | J8: ='Manual Manpower Database'!AJ8 -> 4000 | K8: ='Manual Manpower Database'!AK8 -> 400 | L8: ='Manual Manpower Database'!AL8 -> 666.66667 | M8: ='Manual Manpower Database'!AM8 -> 0 | N8: ='Manual Manpower Database'!AN8 -> 166.66667 | O8: ='Manual Manpower Database'!AO8 -> 0 | P8: ='Manual Manpower Database'!AP8 -> 83.333333 | Q8: ='Manual Manpower Database'!AQ8 -> 93.333333 | ... X8: ='Manual Manpower Database'!AX8 -> 55.555556 | Y8: =SUM(J8:X8) -> 5903.0556
B9: 01 | C9: General Requirement | D9: 01800 | E9: Facility Operation | F9: Body Repairman | G9: 005 | H9: =D9&G9 -> 01800005 | J9: ='Manual Manpower Database'!AJ9 -> 1095 | K9: ='Manual Manpower Database'!AK9 -> 0 | L9: ='Manual Manpower Database'!AL9 -> 0 | M9: ='Manual Manpower Database'!AM9 -> 150 | N9: ='Manual Manpower Database'!AN9 -> 45.625 | O9: ='Manual Manpower Database'!AO9 -> 0 | P9: ='Manual Manpower Database'!AP9 -> 22.8125 | Q9: ='Manual Manpower Database'!AQ9 -> 21.9 | ... X9: ='Manual Manpower Database'!AX9 -> 55.555556 | Y9: =SUM(J9:X9) -> 1828.3931
B10: 01 | C10: General Requirement | D10: 01500 | E10: Temporary facilities & Controls | F10: Car Parking Attendant | G10: 006 | H10: =D10&G10 -> 01500006 | J10: ='Manual Manpower Database'!AJ10 -> 678.14286 | K10: ='Manual Manpower Database'!AK10 -> 0 | L10: ='Manual Manpower Database'!AL10 -> 0 | M10: ='Manual Manpower Database'!AM10 -> 150 | N10: ='Manual Manpower Database'!AN10 -> 28.255952 | O10: ='Manual Manpower Database'!AO10 -> 0 | P10: ='Manual Manpower Database'!AP10 -> 14.127976 | Q10: ='Manual Manpower Database'!AQ10 -> 13.562857 | ... X10: ='Manual Manpower Database'!AX10 -> 55.555556 | Y10: =SUM(J10:X10) -> 1377.1452
B11: 09 | C11: Finishing | D11: 03300 | E11: Cast in Place Concrete | F11: Carpenter Finishing | G11: 005 | H11: =D11&G11 -> 03300005 | J11: ='Manual Manpower Database'!AJ11 -> 983.10811 | K11: ='Manual Manpower Database'!AK11 -> 0 | L11: ='Manual Manpower Database'!AL11 -> 0 | M11: ='Manual Manpower Database'!AM11 -> 150 | N11: ='Manual Manpower Database'!AN11 -> 40.962838 | O11: ='Manual Manpower Database'!AO11 -> 0 | P11: ='Manual Manpower Database'!AP11 -> 20.481419 | Q11: ='Manual Manpower Database'!AQ11 -> 19.662162 | ... X11: ='Manual Manpower Database'!AX11 -> 55.555556 | Y11: =SUM(J11:X11) -> 1707.2701
B12: 03 | C12: Concrete | D12: 03300 | E12: Cast in Place Concrete | F12: Carpenter Shuttering | G12: 010 | H12: =D12&G12 -> 03300010 | J12: ='Manual Manpower Database'!AJ12 -> 894.07113 | K12: ='Manual Manpower Database'!AK12 -> 0 | L12: ='Manual Manpower Database'!AL12 -> 0 | M12: ='Manual Manpower Database'!AM12 -> 250 | N12: ='Manual Manpower Database'!AN12 -> 37.252964 | O12: ='Manual Manpower Database'!AO12 -> 0 | P12: ='Manual Manpower Database'!AP12 -> 18.626482 | Q12: ='Manual Manpower Database'!AQ12 -> 17.881423 | ... X12: ='Manual Manpower Database'!AX12 -> 55.555556 | Y12: =SUM(J12:X12) -> 1710.8875
B13: 16 | C13: Electrical | D13: 16700 | E13: Communications | F13: Computer Technician | G13: 005 | H13: =D13&G13 -> 16700005 | J13: ='Manual Manpower Database'!AJ13 -> 4121.4286 | K13: ='Manual Manpower Database'!AK13 -> 400 | L13: ='Manual Manpower Database'!AL13 -> 0 | M13: ='Manual Manpower Database'!AM13 -> 0 | N13: ='Manual Manpower Database'!AN13 -> 171.72619 | O13: ='Manual Manpower Database'!AO13 -> 0 | P13: ='Manual Manpower Database'!AP13 -> 85.863095 | Q13: ='Manual Manpower Database'!AQ13 -> 82.428571 | ... X13: ='Manual Manpower Database'!AX13 -> 55.555556 | Y13: =SUM(J13:X13) -> 5354.502
B14: 01 | C14: General Requirement | D14: 01500 | E14: Temporary facilities & Controls | F14: Cook | G14: 009 | H14: =D14&G14 -> 01500009 | J14: ='Manual Manpower Database'!AJ14 -> 1090.7143 | K14: ='Manual Manpower Database'!AK14 -> 0 | L14: ='Manual Manpower Database'!AL14 -> 0 | M14: ='Manual Manpower Database'!AM14 -> 150 | N14: ='Manual Manpower Database'!AN14 -> 45.446429 | O14: ='Manual Manpower Database'!AO14 -> 0 | P14: ='Manual Manpower Database'!AP14 -> 22.723214 | Q14: ='Manual Manpower Database'!AQ14 -> 21.814286 | ... X14: ='Manual Manpower Database'!AX14 -> 55.555556 | Y14: =SUM(J14:X14) -> 1823.7538
B15: 02 | C15: Site Construction | D15: 02900 | E15: Planting | F15: Crusher Operator | G15: 010 | H15: =D15&G15 -> 02900010 | J15: ='Manual Manpower Database'!AJ15 -> 1122.9167 | K15: ='Manual Manpower Database'!AK15 -> 0 | L15: ='Manual Manpower Database'!AL15 -> 0 | M15: ='Manual Manpower Database'!AM15 -> 200 | N15: ='Manual Manpower Database'!AN15 -> 46.788194 | O15: ='Manual Manpower Database'!AO15 -> 0 | P15: ='Manual Manpower Database'!AP15 -> 23.394097 | Q15: ='Manual Manpower Database'!AQ15 -> 22.458333 | ... X15: ='Manual Manpower Database'!AX15 -> 55.555556 | Y15: =SUM(J15:X15) -> 1908.6128
B16: 02 | C16: Site Construction | D16: 02900 | E16: Planting | F16: Crusher Technician | G16: 015 | H16: =D16&G16 -> 02900015 | J16: ='Manual Manpower Database'!AJ16 -> 1333.3333 | K16: ='Manual Manpower Database'!AK16 -> 0 | L16: ='Manual Manpower Database'!AL16 -> 0 | M16: ='Manual Manpower Database'!AM16 -> 200 | N16: ='Manual Manpower Database'!AN16 -> 55.555556 | O16: ='Manual Manpower Database'!AO16 -> 0 | P16: ='Manual Manpower Database'!AP16 -> 27.777778 | Q16: ='Manual Manpower Database'!AQ16 -> 26.666667 | ... X16: ='Manual Manpower Database'!AX16 -> 55.555556 | Y16: =SUM(J16:X16) -> 2136.3889
B17: 02 | C17: Site Construction | D17: 02900 | E17: Planting | F17: Cutter | G17: 020 | H17: =D17&G17 -> 02900020 | J17: ='Manual Manpower Database'!AJ17 -> 615.83333 | K17: ='Manual Manpower Database'!AK17 -> 0 | L17: ='Manual Manpower Database'!AL17 -> 0 | M17: ='Manual Manpower Database'!AM17 -> 250 | N17: ='Manual Manpower Database'!AN17 -> 25.659722 | O17: ='Manual Manpower Database'!AO17 -> 0 | P17: ='Manual Manpower Database'!AP17 -> 12.829861 | Q17: ='Manual Manpower Database'!AQ17 -> 12.316667 | ... X17: ='Manual Manpower Database'!AX17 -> 55.555556 | Y17: =SUM(J17:X17) -> 1409.6951
B18: 01 | C18: General Requirement | D18: 01800 | E18: Facility Operation | F18: Diesel Mechanic | G18: 010 | H18: =D18&G18 -> 01800010 | J18: ='Manual Manpower Database'!AJ19 -> 1200 | K18: ='Manual Manpower Database'!AK19 -> 0 | L18: ='Manual Manpower Database'!AL19 -> 0 | M18: ='Manual Manpower Database'!AM19 -> 150 | N18: ='Manual Manpower Database'!AN19 -> 50 | O18: ='Manual Manpower Database'!AO19 -> 0 | P18: ='Manual Manpower Database'!AP19 -> 25 | Q18: ='Manual Manpower Database'!AQ19 -> 24 | ... X18: ='Manual Manpower Database'!AX19 -> 55.555556 | Y18: =SUM(J18:X18) -> 1942.0556
B19: 01 | C19: General Requirement | D19: 01700 | E19: Execution Requirements | F19: Driver Ambulance | G19: 006 | H19: =D19&G19 -> 01700006 | J19: ='Manual Manpower Database'!AJ20 -> 1006.25 | K19: ='Manual Manpower Database'!AK20 -> 0 | L19: ='Manual Manpower Database'!AL20 -> 0 | M19: ='Manual Manpower Database'!AM20 -> 200 | N19: ='Manual Manpower Database'!AN20 -> 41.927083 | O19: ='Manual Manpower Database'!AO20 -> 0 | P19: ='Manual Manpower Database'!AP20 -> 20.963542 | Q19: ='Manual Manpower Database'!AQ20 -> 20.125 | ... X19: ='Manual Manpower Database'!AX20 -> 55.555556 | Y19: =SUM(J19:X19) -> 1782.3212
B20: 03 | C20: Concrete | D20: 03300 | E20: Cast in Place Concrete | F20: Driver Concrete Mixer | G20: 015 | H20: =D20&G20 -> 03300015 | J20: ='Manual Manpower Database'!AJ21 -> 1180 | K20: ='Manual Manpower Database'!AK21 -> 0 | L20: ='Manual Manpower Database'!AL21 -> 0 | M20: ='Manual Manpower Database'!AM21 -> 150 | N20: ='Manual Manpower Database'!AN21 -> 49.166667 | O20: ='Manual Manpower Database'!AO21 -> 0 | P20: ='Manual Manpower Database'!AP21 -> 24.583333 | Q20: ='Manual Manpower Database'!AQ21 -> 23.6 | ... X20: ='Manual Manpower Database'!AX21 -> 55.555556 | Y20: =SUM(J20:X20) -> 1920.4056
B21: 03 | C21: Concrete | D21: 03300 | E21: Cast in Place Concrete | F21: Form Man | G21: 065 | H21: =D21&G21 -> 03300065 | J21: 641.30063 | K21: 300 | L21: 0 | M21: 250 | N21: 26.72086 | O21: 0 | P21: 13.36043 | Q21: 12.826013 | R21: 125 | S21: 41.666667 | T21: 54.166667 | U21: 208.33333 | V21: 0 | W21: 8.3333333 | X21: 55.555556 | Y21: 1737.2635
B22: 02 | C22: Site Construction | D22: 02200 | E22: Site Preparation | F22: Driver Dump Truck | G22: 005 | H22: =D22&G22 -> 02200005 | J22: ='Manual Manpower Database'!AJ22 -> 1175 | K22: ='Manual Manpower Database'!AK22 -> 0 | L22: ='Manual Manpower Database'!AL22 -> 0 | M22: ='Manual Manpower Database'!AM22 -> 150 | N22: ='Manual Manpower Database'!AN22 -> 48.958333 | O22: ='Manual Manpower Database'!AO22 -> 0 | P22: ='Manual Manpower Database'!AP22 -> 24.479167 | Q22: ='Manual Manpower Database'!AQ22 -> 23.5 | ... X22: ='Manual Manpower Database'!AX22 -> 55.555556 | Y22: =SUM(J22:X22) -> 1914.9931
B23: 02 | C23: Site Construction | D23: 02200 | E23: Site Preparation | F23: Driver Heavy Duty | G23: 010 | H23: =D23&G23 -> 02200010 | J23: ='Manual Manpower Database'!AJ23 -> 976.856 | K23: ='Manual Manpower Database'!AK23 -> 300 | L23: ='Manual Manpower Database'!AL23 -> 0 | M23: ='Manual Manpower Database'!AM23 -> 250 | N23: ='Manual Manpower Database'!AN23 -> 40.702333 | O23: ='Manual Manpower Database'!AO23 -> 0 | P23: ='Manual Manpower Database'!AP23 -> 20.351167 | Q23: ='Manual Manpower Database'!AQ23 -> 19.53712 | ... X23: ='Manual Manpower Database'!AX23 -> 55.555556 | Y23: =SUM(J23:X23) -> 2100.5022
B24: 01 | C24: General Requirement | D24: 01700 | E24: Execution Requirements | F24: Execution Requirements | G24: 009 | H24: =D24&G24 -> 01700009 | J24: ='Manual Manpower Database'!AJ24 -> 2070.6782 | K24: ='Manual Manpower Database'!AK24 -> 300 | L24: ='Manual Manpower Database'!AL24 -> 0 | M24: ='Manual Manpower Database'!AM24 -> 400 | N24: ='Manual Manpower Database'!AN24 -> 86.278257 | O24: ='Manual Manpower Database'!AO24 -> 0 | P24: ='Manual Manpower Database'!AP24 -> 43.139128 | Q24: ='Manual Manpower Database'!AQ24 -> 41.413563 | ... X24: ='Manual Manpower Database'!AX24 -> 55.555556 | Y24: =SUM(J24:X24) -> 3434.5647
B25: 01 | C25: General Requirement | D25: 01700 | E25: Execution Requirements | F25: Execution Requirements | G25: 012 | H25: =D25&G25 -> 01700012 | J25: ='Manual Manpower Database'!AJ25 -> 1100 | K25: ='Manual Manpower Database'!AK25 -> 300 | L25: ='Manual Manpower Database'!AL25 -> 183.33333 | M25: ='Manual Manpower Database'!AM25 -> 200 | N25: ='Manual Manpower Database'!AN25 -> 45.833333 | O25: ='Manual Manpower Database'!AO25 -> 0 | P25: ='Manual Manpower Database'!AP25 -> 22.916667 | Q25: ='Manual Manpower Database'!AQ25 -> 25.666667 | ... X25: ='Manual Manpower Database'!AX25 -> 55.555556 | Y25: =SUM(J25:X25) -> 2370.8056
B26: 02 | C26: Site Construction | D26: 02200 | E26: Site Preparation | F26: Driver Trailer | G26: 015 | H26: =D26&G26 -> 02200015 | J26: ='Manual Manpower Database'!AJ26 -> 958.28814 | K26: ='Manual Manpower Database'!AK26 -> 0 | L26: ='Manual Manpower Database'!AL26 -> 0 | M26: ='Manual Manpower Database'!AM26 -> 250 | N26: ='Manual Manpower Database'!AN26 -> 39.928672 | O26: ='Manual Manpower Database'!AO26 -> 0 | P26: ='Manual Manpower Database'!AP26 -> 19.964336 | Q26: ='Manual Manpower Database'!AQ26 -> 19.165763 | ... X26: ='Manual Manpower Database'!AX26 -> 55.555556 | Y26: =SUM(J26:X26) -> 1780.4025
B27: 15 | C27: Mechanical | D27: 15900 | E27: HVAC instrumentation & Controls | F27: Duct Fabricator | G27: 005 | H27: =D27&G27 -> 15900005 | J27: ='Manual Manpower Database'!AJ27 -> 1182.3529 | K27: ='Manual Manpower Database'!AK27 -> 0 | L27: ='Manual Manpower Database'!AL27 -> 0 | M27: ='Manual Manpower Database'!AM27 -> 150 | N27: ='Manual Manpower Database'!AN27 -> 49.264706 | O27: ='Manual Manpower Database'!AO27 -> 0 | P27: ='Manual Manpower Database'!AP27 -> 24.632353 | Q27: ='Manual Manpower Database'!AQ27 -> 23.647059 | ... X27: ='Manual Manpower Database'!AX27 -> 55.555556 | Y27: =SUM(J27:X27) -> 1922.9526
B28: 15 | C28: Mechanical | D28: 15900 | E28: HVAC instrumentation & Controls | F28: Duct Fitter | G28: 010 | H28: =D28&G28 -> 15900010 | J28: ='Manual Manpower Database'!AJ28 -> 1046.1538 | K28: ='Manual Manpower Database'!AK28 -> 0 | L28: ='Manual Manpower Database'!AL28 -> 0 | M28: ='Manual Manpower Database'!AM28 -> 150 | N28: ='Manual Manpower Database'!AN28 -> 43.589744 | O28: ='Manual Manpower Database'!AO28 -> 0 | P28: ='Manual Manpower Database'!AP28 -> 21.794872 | Q28: ='Manual Manpower Database'!AQ28 -> 20.923077 | ... X28: ='Manual Manpower Database'!AX28 -> 55.555556 | Y28: =SUM(J28:X28) -> 1775.5171
B29: 15 | C29: Mechanical | D29: 15900 | E29: HVAC instrumentation & Controls | F29: Duct Technician | G29: 015 | H29: =D29&G29 -> 15900015 | J29: ='Manual Manpower Database'!AJ29 -> 1100 | K29: ='Manual Manpower Database'!AK29 -> 0 | L29: ='Manual Manpower Database'!AL29 -> 0 | M29: ='Manual Manpower Database'!AM29 -> 150 | N29: ='Manual Manpower Database'!AN29 -> 45.833333 | O29: ='Manual Manpower Database'!AO29 -> 0 | P29: ='Manual Manpower Database'!AP29 -> 22.916667 | Q29: ='Manual Manpower Database'!AQ29 -> 22 | ... X29: ='Manual Manpower Database'!AX29 -> 55.555556 | Y29: =SUM(J29:X29) -> 1833.8056
B30: 16 | C30: Electrical | D30: 16050 | E30: Basic Electrical Materials & Methods | F30: Electrician | G30: 005 | H30: =D30&G30 -> 16050005 | J30: ='Manual Manpower Database'!AJ30 -> 1156.8185 | K30: ='Manual Manpower Database'!AK30 -> 300 | L30: ='Manual Manpower Database'!AL30 -> 0 | M30: ='Manual Manpower Database'!AM30 -> 250 | N30: ='Manual Manpower Database'!AN30 -> 48.200773 | O30: ='Manual Manpower Database'!AO30 -> 0 | P30: ='Manual Manpower Database'!AP30 -> 24.100386 | Q30: ='Manual Manpower Database'!AQ30 -> 23.136371 | ... X30: ='Manual Manpower Database'!AX30 -> 55.555556 | Y30: =SUM(J30:X30) -> 2295.3116
B31: 01 | C31: General Requirement | D31: 01700 | E31: Execution Requirements | F31: Foreman | G31: 015 | H31: =D31&G31 -> 01700015 | J31: ='Manual Manpower Database'!AJ31 -> 2654.8145 | K31: ='Manual Manpower Database'!AK31 -> 500 | L31: ='Manual Manpower Database'!AL31 -> 663.70362 | M31: ='Manual Manpower Database'!AM31 -> 250 | N31: ='Manual Manpower Database'!AN31 -> 110.61727 | O31: ='Manual Manpower Database'!AO31 -> 0 | P31: ='Manual Manpower Database'!AP31 -> 55.308635 | Q31: ='Manual Manpower Database'!AQ31 -> 66.370362 | ... X31: ='Manual Manpower Database'!AX31 -> 55.555556 | Y31: =SUM(J31:X31) -> 4793.8699
B32: 02 | C32: Site Construction | D32: 02900 | E32: Planting | F32: Foreman Asphalt Plant | G32: 025 | H32: =D32&G32 -> 02900025 | J32: ='Manual Manpower Database'!AJ32 -> 3283.3333 | K32: ='Manual Manpower Database'!AK32 -> 0 | L32: ='Manual Manpower Database'!AL32 -> 0 | M32: ='Manual Manpower Database'!AM32 -> 150 | N32: ='Manual Manpower Database'!AN32 -> 136.80556 | O32: ='Manual Manpower Database'!AO32 -> 0 | P32: ='Manual Manpower Database'!AP32 -> 68.402778 | Q32: ='Manual Manpower Database'!AQ32 -> 65.666667 | ... X32: ='Manual Manpower Database'!AX32 -> 55.555556 | Y32: =SUM(J32:X32) -> 4197.2639
B33: 02 | C33: Site Construction | D33: 02900 | E33: Planting | F33: Asphalt Plant Labour | G33: 055 | H33: =D33&G33 -> 02900055 | J33: 641.30063 | K33: 300 | L33: 0 | M33: 250 | N33: 26.72086 | O33: 0 | P33: 13.36043 | Q33: 12.826013 | R33: 125 | S33: 41.666667 | T33: 54.166667 | U33: 208.33333 | V33: 0 | W33: 8.3333333 | X33: 55.555556 | Y33: 1737.2635
B34: 01 | C34: General Requirement | D34: 01700 | E34: Execution Requirements | F34: Foreman Assistant | G34: 018 | H34: =D34&G34 -> 01700018 | J34: ='Manual Manpower Database'!AJ33 -> 2810 | K34: ='Manual Manpower Database'!AK33 -> 300 | L34: ='Manual Manpower Database'!AL33 -> 0 | M34: ='Manual Manpower Database'!AM33 -> 150 | N34: ='Manual Manpower Database'!AN33 -> 117.08333 | O34: ='Manual Manpower Database'!AO33 -> 0 | P34: ='Manual Manpower Database'!AP33 -> 58.541667 | Q34: ='Manual Manpower Database'!AQ33 -> 56.2 | ... X34: ='Manual Manpower Database'!AX33 -> 55.555556 | Y34: =SUM(J34:X34) -> 3984.8806
B35: 01 | C35: General Requirement | D35: 01500 | E35: Temporary facilities & Controls | F35: Foreman Camp | G35: 012 | H35: =D35&G35 -> 01500012 | J35: ='Manual Manpower Database'!AJ34 -> 1150 | K35: ='Manual Manpower Database'!AK34 -> 0 | L35: ='Manual Manpower Database'!AL34 -> 0 | M35: ='Manual Manpower Database'!AM34 -> 150 | N35: ='Manual Manpower Database'!AN34 -> 47.916667 | O35: ='Manual Manpower Database'!AO34 -> 0 | P35: ='Manual Manpower Database'!AP34 -> 23.958333 | Q35: ='Manual Manpower Database'!AQ34 -> 23 | ... X35: ='Manual Manpower Database'!AX34 -> 55.555556 | Y35: =SUM(J35:X35) -> 1887.9306
B36: 03 | C36: Concrete | D36: 03300 | E36: Cast in Place Concrete | F36: Foreman Carpenter | G36: 020 | H36: =D36&G36 -> 03300020 | J36: ='Manual Manpower Database'!AJ35 -> 2906.2 | K36: ='Manual Manpower Database'!AK35 -> 0 | L36: ='Manual Manpower Database'!AL35 -> 0 | M36: ='Manual Manpower Database'!AM35 -> 250 | N36: ='Manual Manpower Database'!AN35 -> 121.09167 | O36: ='Manual Manpower Database'!AO35 -> 0 | P36: ='Manual Manpower Database'!AP35 -> 60.545833 | Q36: ='Manual Manpower Database'!AQ35 -> 58.124 | ... X36: ='Manual Manpower Database'!AX35 -> 55.555556 | Y36: =SUM(J36:X36) -> 3889.0171
B37: 01 | C37: General Requirement | D37: 01700 | E37: Execution Requirements | F37: Foreman Civil | G37: 021 | H37: =D37&G37 -> 01700021 | J37: ='Manual Manpower Database'!AJ36 -> 3194.6993 | K37: ='Manual Manpower Database'!AK36 -> 400 | L37: ='Manual Manpower Database'!AL36 -> 798.67484 | M37: ='Manual Manpower Database'!AM36 -> 150 | N37: ='Manual Manpower Database'!AN36 -> 133.11247 | O37: ='Manual Manpower Database'!AO36 -> 0 | P37: ='Manual Manpower Database'!AP36 -> 66.556236 | Q37: ='Manual Manpower Database'!AQ36 -> 79.867484 | ... X37: ='Manual Manpower Database'!AX36 -> 55.555556 | Y37: =SUM(J37:X37) -> 5315.9659
B38: 02 | C38: Site Construction | D38: 02100 | E38: Site Remediation | F38: Foreman Cleaning | G38: 005 | H38: =D38&G38 -> 02100005 | J38: ='Manual Manpower Database'!AJ37 -> 1150.6386 | K38: ='Manual Manpower Database'!AK37 -> 500 | L38: ='Manual Manpower Database'!AL37 -> 191.7731 | M38: ='Manual Manpower Database'!AM37 -> 250 | N38: ='Manual Manpower Database'!AN37 -> 47.943276 | O38: ='Manual Manpower Database'!AO37 -> 0 | P38: ='Manual Manpower Database'!AP37 -> 23.971638 | Q38: ='Manual Manpower Database'!AQ37 -> 26.848234 | ... X38: ='Manual Manpower Database'!AX37 -> 55.555556 | Y38: =SUM(J38:X38) -> 2684.2304
B39: 02 | C39: Site Construction | D39: 02900 | E39: Planting | F39: Foreman Crusher | G39: 030 | H39: =D39&G39 -> 02900030 | J39: ='Manual Manpower Database'!AJ38 -> 2250 | K39: ='Manual Manpower Database'!AK38 -> 0 | L39: ='Manual Manpower Database'!AL38 -> 0 | M39: ='Manual Manpower Database'!AM38 -> 200 | N39: ='Manual Manpower Database'!AN38 -> 93.75 | O39: ='Manual Manpower Database'!AO38 -> 0 | P39: ='Manual Manpower Database'!AP38 -> 46.875 | Q39: ='Manual Manpower Database'!AQ38 -> 45 | ... X39: ='Manual Manpower Database'!AX38 -> 55.555556 | Y39: =SUM(J39:X39) -> 3128.6806
B40: 15 | C40: Mechanical | D40: 15900 | E40: HVAC instrumentation & Controls | F40: Foreman Ducting | G40: 020 | H40: =D40&G40 -> 15900020 | J40: ='Manual Manpower Database'!AJ39 -> 2812.5 | K40: ='Manual Manpower Database'!AK39 -> 0 | L40: ='Manual Manpower Database'!AL39 -> 0 | M40: ='Manual Manpower Database'!AM39 -> 0 | N40: ='Manual Manpower Database'!AN39 -> 117.1875 | O40: ='Manual Manpower Database'!AO39 -> 0 | P40: ='Manual Manpower Database'!AP39 -> 58.59375 | Q40: ='Manual Manpower Database'!AQ39 -> 56.25 | ... X40: ='Manual Manpower Database'!AX39 -> 55.555556 | Y40: =SUM(J40:X40) -> 3537.5868
B41: 02 | C41: Site Construction | D41: 02300 | E41: Earth Work | F41: Foreman Earthwork | G41: 005 | H41: =D41&G41 -> 02300005 | J41: ='Manual Manpower Database'!AJ40 -> 2750 | K41: ='Manual Manpower Database'!AK40 -> 0 | L41: ='Manual Manpower Database'!AL40 -> 0 | M41: ='Manual Manpower Database'!AM40 -> 0 | N41: ='Manual Manpower Database'!AN40 -> 114.58333 | O41: ='Manual Manpower Database'!AO40 -> 0 | P41: ='Manual Manpower Database'!AP40 -> 57.291667 | Q41: ='Manual Manpower Database'!AQ40 -> 55 | ... X41: ='Manual Manpower Database'!AX40 -> 55.555556 | Y41: =SUM(J41:X41) -> 3469.9306
B42: 16 | C42: Electrical | D42: 16050 | E42: Basic Electrical Materials & Methods | F42: Foreman Electrical | G42: 010 | H42: =D42&G42 -> 16050010 | J42: ='Manual Manpower Database'!AJ41 -> 2875.82 | K42: ='Manual Manpower Database'!AK41 -> 400 | L42: ='Manual Manpower Database'!AL41 -> 479.30333 | M42: ='Manual Manpower Database'!AM41 -> 250 | N42: ='Manual Manpower Database'!AN41 -> 119.82583 | O42: ='Manual Manpower Database'!AO41 -> 0 | P42: ='Manual Manpower Database'!AP41 -> 59.912917 | Q42: ='Manual Manpower Database'!AQ41 -> 67.102467 | ... X42: ='Manual Manpower Database'!AX41 -> 55.555556 | Y42: =SUM(J42:X42) -> 4745.0201
B43: 01 | C43: General Requirement | D43: 01700 | E43: Execution Requirements | F43: Foreman EMD | G43: 024 | H43: =D43&G43 -> 01700024 | J43: ='Manual Manpower Database'!AJ42 -> 2250 | K43: ='Manual Manpower Database'!AK42 -> 0 | L43: ='Manual Manpower Database'!AL42 -> 0 | M43: ='Manual Manpower Database'!AM42 -> 150 | N43: ='Manual Manpower Database'!AN42 -> 93.75 | O43: ='Manual Manpower Database'!AO42 -> 0 | P43: ='Manual Manpower Database'!AP42 -> 46.875 | Q43: ='Manual Manpower Database'!AQ42 -> 45 | ... X43: ='Manual Manpower Database'!AX42 -> 55.555556 | Y43: =SUM(J43:X43) -> 3078.6806
B44: 09 | C44: Finishing | D44: 09050 | E44: Basic Finish Materials & Methods | F44: Foreman Finishing | G44: 005 | H44: =D44&G44 -> 09050005 | J44: ='Manual Manpower Database'!AJ43 -> 3506.2 | K44: ='Manual Manpower Database'!AK43 -> 400 | L44: ='Manual Manpower Database'!AL43 -> 876.55 | M44: ='Manual Manpower Database'!AM43 -> 150 | N44: ='Manual Manpower Database'!AN43 -> 146.09167 | O44: ='Manual Manpower Database'!AO43 -> 0 | P44: ='Manual Manpower Database'!AP43 -> 73.045833 | Q44: ='Manual Manpower Database'!AQ43 -> 87.655 | ... X44: ='Manual Manpower Database'!AX43 -> 55.555556 | Y44: =SUM(J44:X44) -> 5732.5981
B45: 15 | C45: Mechanical | D45: 15900 | E45: HVAC instrumentation & Controls | F45: Foreman HVAC | G45: 025 | H45: =D45&G45 -> 15900025 | J45: ='Manual Manpower Database'!AJ44 -> 2583.3333 | K45: ='Manual Manpower Database'!AK44 -> 0 | L45: ='Manual Manpower Database'!AL44 -> 0 | M45: ='Manual Manpower Database'!AM44 -> 0 | N45: ='Manual Manpower Database'!AN44 -> 107.63889 | O45: ='Manual Manpower Database'!AO44 -> 0 | P45: ='Manual Manpower Database'!AP44 -> 53.819444 | Q45: ='Manual Manpower Database'!AQ44 -> 51.666667 | ... X45: ='Manual Manpower Database'!AX44 -> 55.555556 | Y45: =SUM(J45:X45) -> 3289.5139
B46: 04 | C46: Block Work | D46: 04200 | E46: Masonary Units | F46: Foreman Mason | G46: 005 | H46: =D46&G46 -> 04200005 | J46: ='Manual Manpower Database'!AJ45 -> 2603.125 | K46: ='Manual Manpower Database'!AK45 -> 0 | L46: ='Manual Manpower Database'!AL45 -> 0 | M46: ='Manual Manpower Database'!AM45 -> 150 | N46: ='Manual Manpower Database'!AN45 -> 108.46354 | O46: ='Manual Manpower Database'!AO45 -> 0 | P46: ='Manual Manpower Database'!AP45 -> 54.231771 | Q46: ='Manual Manpower Database'!AQ45 -> 52.0625 | ... X46: ='Manual Manpower Database'!AX45 -> 55.555556 | Y46: =SUM(J46:X46) -> 3460.9384
B47: 09 | C47: Finishing | D47: 09700 | E47: Wall Finishes | F47: Foreman Plaster | G47: 020 | H47: =D47&G47 -> 09700020 | J47: 2603.125 | K47: 0 | L47: 0 | M47: 150 | N47: 108.46354 | O47: 0 | P47: 54.231771 | Q47: 52.0625 | R47: 125 | S47: 41.666667 | T47: 54.166667 | U47: 208.33333 | V47: 0 | W47: 8.3333333 | X47: 55.555556 | Y47: 3460.9384
B48: 09 | C48: Finishing | D48: 09600 | E48: Flooring | F48: Foreman Tile Fixer | G48: 010 | H48: =D48&G48 -> 09600010 | J48: 2603.125 | K48: 0 | L48: 0 | M48: 150 | N48: 108.46354 | O48: 0 | P48: 54.231771 | Q48: 52.0625 | R48: 125 | S48: 41.666667 | T48: 54.166667 | U48: 208.33333 | V48: 0 | W48: 8.3333333 | X48: 55.555556 | Y48: 3460.9384
B49: 01 | C49: General Requirement | D49: 01500 | E49: Temporary facilities & Controls | F49: Foreman Mechanical | G49: 015 | H49: =D49&G49 -> 01500015 | J49: ='Manual Manpower Database'!AJ46 -> 3282.48 | K49: ='Manual Manpower Database'!AK46 -> 300 | L49: ='Manual Manpower Database'!AL46 -> 547.08 | M49: ='Manual Manpower Database'!AM46 -> 150 | N49: ='Manual Manpower Database'!AN46 -> 136.77 | O49: ='Manual Manpower Database'!AO46 -> 0 | P49: ='Manual Manpower Database'!AP46 -> 68.385 | Q49: ='Manual Manpower Database'!AQ46 -> 76.5912 | ... X49: ='Manual Manpower Database'!AX46 -> 55.555556 | Y49: =SUM(J49:X49) -> 5054.3618
B50: 01 | C50: General Requirement | D50: 01800 | E50: Facility Operation | F50: Foreman Operations | G50: 015 | H50: =D50&G50 -> 01800015 | J50: ='Manual Manpower Database'!AJ47 -> 1941 | K50: ='Manual Manpower Database'!AK47 -> 0 | L50: ='Manual Manpower Database'!AL47 -> 0 | M50: ='Manual Manpower Database'!AM47 -> 250 | N50: ='Manual Manpower Database'!AN47 -> 80.875 | O50: ='Manual Manpower Database'!AO47 -> 0 | P50: ='Manual Manpower Database'!AP47 -> 40.4375 | Q50: ='Manual Manpower Database'!AQ47 -> 38.82 | ... X50: ='Manual Manpower Database'!AX47 -> 55.555556 | Y50: =SUM(J50:X50) -> 2844.1881
B51: 09 | C51: Finishing | D51: 09900 | E51: Paints & Coatings | F51: Foreman Painter | G51: 005 | H51: =D51&G51 -> 09900005 | J51: ='Manual Manpower Database'!AJ48 -> 3109 | K51: ='Manual Manpower Database'!AK48 -> 0 | L51: ='Manual Manpower Database'!AL48 -> 518.16667 | M51: ='Manual Manpower Database'!AM48 -> 0 | N51: ='Manual Manpower Database'!AN48 -> 129.54167 | O51: ='Manual Manpower Database'!AO48 -> 0 | P51: ='Manual Manpower Database'!AP48 -> 64.770833 | Q51: ='Manual Manpower Database'!AQ48 -> 72.543333 | ... X51: ='Manual Manpower Database'!AX48 -> 55.555556 | Y51: =SUM(J51:X51) -> 4387.0781
B52: 15 | C52: Mechanical | D52: 15200 | E52: Process Piping | F52: Foreman Piping | G52: 005 | H52: =D52&G52 -> 15200005 | J52: ='Manual Manpower Database'!AJ49 -> 3030 | K52: ='Manual Manpower Database'!AK49 -> 0 | L52: ='Manual Manpower Database'!AL49 -> 505 | M52: ='Manual Manpower Database'!AM49 -> 150 | N52: ='Manual Manpower Database'!AN49 -> 126.25 | O52: ='Manual Manpower Database'!AO49 -> 0 | P52: ='Manual Manpower Database'!AP49 -> 63.125 | Q52: ='Manual Manpower Database'!AQ49 -> 70.7 | ... X52: ='Manual Manpower Database'!AX49 -> 55.555556 | Y52: =SUM(J52:X52) -> 4438.1306
B53: 02 | C53: Site Construction | D53: 02900 | E53: Planting | F53: Foreman Plant Equipment | G53: 035 | H53: =D53&G53 -> 02900035 | J53: ='Manual Manpower Database'!AJ50 -> 4121.3333 | K53: ='Manual Manpower Database'!AK50 -> 0 | L53: ='Manual Manpower Database'!AL50 -> 686.88889 | M53: ='Manual Manpower Database'!AM50 -> 0 | N53: ='Manual Manpower Database'!AN50 -> 171.72222 | O53: ='Manual Manpower Database'!AO50 -> 0 | P53: ='Manual Manpower Database'!AP50 -> 85.861111 | Q53: ='Manual Manpower Database'!AQ50 -> 96.164444 | ... X53: ='Manual Manpower Database'!AX50 -> 55.555556 | Y53: =SUM(J53:X53) -> 5655.0256
B54: 15 | C54: Mechanical | D54: 15100 | E54: Building Services Piping | F54: Foreman Plumbing | G54: 005 | H54: =D54&G54 -> 15100005 | J54: ='Manual Manpower Database'!AJ51 -> 2976.6 | K54: ='Manual Manpower Database'!AK51 -> 0 | L54: ='Manual Manpower Database'!AL51 -> 0 | M54: ='Manual Manpower Database'!AM51 -> 150 | N54: ='Manual Manpower Database'!AN51 -> 124.025 | O54: ='Manual Manpower Database'!AO51 -> 0 | P54: ='Manual Manpower Database'!AP51 -> 62.0125 | Q54: ='Manual Manpower Database'!AQ51 -> 59.532 | ... X54: ='Manual Manpower Database'!AX51 -> 55.555556 | Y54: =SUM(J54:X54) -> 3865.2251
B55: 02 | C55: Site Construction | D55: 02300 | E55: Earth Work | F55: Foreman Roads | G55: 010 | H55: =D55&G55 -> 02300010 | J55: ='Manual Manpower Database'!AJ52 -> 3504.8537 | K55: ='Manual Manpower Database'!AK52 -> 0 | L55: ='Manual Manpower Database'!AL52 -> 876.21341 | M55: ='Manual Manpower Database'!AM52 -> 150 | N55: ='Manual Manpower Database'!AN52 -> 146.03557 | O55: ='Manual Manpower Database'!AO52 -> 0 | P55: ='Manual Manpower Database'!AP52 -> 73.017785 | Q55: ='Manual Manpower Database'!AQ52 -> 87.621341 | ... X55: ='Manual Manpower Database'!AX52 -> 55.555556 | Y55: =SUM(J55:X55) -> 5330.7973
B56: 01 | C56: General Requirement | D56: 02300 | E56: Earth Work | F56: Foreman Scraper | G56: 015 | H56: =D56&G56 -> 02300015 | J56: ='Manual Manpower Database'!AJ53 -> 4020 | K56: ='Manual Manpower Database'!AK53 -> 0 | L56: ='Manual Manpower Database'!AL53 -> 0 | M56: ='Manual Manpower Database'!AM53 -> 300 | N56: ='Manual Manpower Database'!AN53 -> 167.5 | O56: ='Manual Manpower Database'!AO53 -> 0 | P56: ='Manual Manpower Database'!AP53 -> 83.75 | Q56: ='Manual Manpower Database'!AQ53 -> 80.4 | ... X56: ='Manual Manpower Database'!AX53 -> 55.555556 | Y56: =SUM(J56:X56) -> 5144.7056
B57: 03 | C57: Concrete | D57: 03300 | E57: Cast in Place Concrete | F57: Foreman Steel Fixer | G57: 025 | H57: =D57&G57 -> 03300025 | J57: ='Manual Manpower Database'!AJ54 -> 2891.4286 | K57: ='Manual Manpower Database'!AK54 -> 0 | L57: ='Manual Manpower Database'!AL54 -> 481.90476 | M57: ='Manual Manpower Database'!AM54 -> 150 | N57: ='Manual Manpower Database'!AN54 -> 120.47619 | O57: ='Manual Manpower Database'!AO54 -> 0 | P57: ='Manual Manpower Database'!AP54 -> 60.238095 | Q57: ='Manual Manpower Database'!AQ54 -> 67.466667 | ... X57: ='Manual Manpower Database'!AX54 -> 55.555556 | Y57: =SUM(J57:X57) -> 4264.5698
B58: 01 | C58: General Requirement | D58: 01500 | E58: Temporary facilities & Controls | F58: Foreman Traffic Safety | G58: 018 | H58: =D58&G58 -> 01500018 | J58: ='Manual Manpower Database'!AJ55 -> 3000 | K58: ='Manual Manpower Database'!AK55 -> 0 | L58: ='Manual Manpower Database'!AL55 -> 0 | M58: ='Manual Manpower Database'!AM55 -> 0 | N58: ='Manual Manpower Database'!AN55 -> 125 | O58: ='Manual Manpower Database'!AO55 -> 0 | P58: ='Manual Manpower Database'!AP55 -> 62.5 | Q58: ='Manual Manpower Database'!AQ55 -> 60 | ... X58: ='Manual Manpower Database'!AX55 -> 55.555556 | Y58: =SUM(J58:X58) -> 3740.5556
B59: 01 | C59: General Requirement | D59: 01500 | E59: Temporary facilities & Controls | F59: Foreman Traffic Signals | G59: 021 | H59: =D59&G59 -> 01500021 | J59: ='Manual Manpower Database'!AJ56 -> 2200 | K59: ='Manual Manpower Database'!AK56 -> 0 | L59: ='Manual Manpower Database'!AL56 -> 0 | M59: ='Manual Manpower Database'!AM56 -> 150 | N59: ='Manual Manpower Database'!AN56 -> 91.666667 | O59: ='Manual Manpower Database'!AO56 -> 0 | P59: ='Manual Manpower Database'!AP56 -> 45.833333 | Q59: ='Manual Manpower Database'!AQ56 -> 44 | ... X59: ='Manual Manpower Database'!AX56 -> 55.555556 | Y59: =SUM(J59:X59) -> 3024.5556
B60: 14 | C60: Transportaion | D60: 14900 | E60: Transportation | F60: Foreman Transport | G60: 005 | H60: =D60&G60 -> 14900005 | J60: ='Manual Manpower Database'!AJ57 -> 1070 | K60: ='Manual Manpower Database'!AK57 -> 0 | L60: ='Manual Manpower Database'!AL57 -> 0 | M60: ='Manual Manpower Database'!AM57 -> 150 | N60: ='Manual Manpower Database'!AN57 -> 44.583333 | O60: ='Manual Manpower Database'!AO57 -> 0 | P60: ='Manual Manpower Database'!AP57 -> 22.291667 | Q60: ='Manual Manpower Database'!AQ57 -> 21.4 | ... X60: ='Manual Manpower Database'!AX57 -> 55.555556 | Y60: =SUM(J60:X60) -> 1801.3306
... B73: 15 | C73: Mechanical | D73: 15200 | E73: Process Piping | F73: Helper Pipe Fitter | G73: 010 | H73: =D73&G73 -> 15200010 | J73: ='Manual Manpower Database'!AJ70 -> 750 | K73: ='Manual Manpower Database'!AK70 -> 0 | L73: ='Manual Manpower Database'!AL70 -> 0 | M73: ='Manual Manpower Database'!AM70 -> 150 | N73: ='Manual Manpower Database'!AN70 -> 31.25 | O73: ='Manual Manpower Database'!AO70 -> 0 | P73: ='Manual Manpower Database'!AP70 -> 15.625 | Q73: ='Manual Manpower Database'!AQ70 -> 15 | ... X73: ='Manual Manpower Database'!AX70 -> 55.555556 | Y73: =SUM(J73:X73) -> 1454.9306
B74: 03 | C74: Concrete | D74: 03400 | E74: Precast Concrete | F74: Structure Steel Foreman | G74: 005 | H74: =D74&G74 -> 03400005 | J74: 2891.4286 | K74: 0 | L74: 481.90476 | M74: 150 | N74: 120.47619 | O74: 0 | P74: 60.238095 | Q74: 67.466667 | R74: 125 | S74: 41.666667 | T74: 54.166667 | U74: 208.33333 | V74: 0 | W74: 8.3333333 | X74: 55.555556 | Y74: 4264.5698
B75: 03 | C75: Concrete | D75: 03300 | E75: Cast in Place Concrete | F75: Helper Steel fixer | G75: 035 | H75: =D75&G75 -> 03300035 | J75: ='Manual Manpower Database'!AJ71 -> 750 | K75: ='Manual Manpower Database'!AK71 -> 0 | L75: ='Manual Manpower Database'!AL71 -> 0 | M75: ='Manual Manpower Database'!AM71 -> 150 | N75: ='Manual Manpower Database'!AN71 -> 31.25 | O75: ='Manual Manpower Database'!AO71 -> 0 | P75: ='Manual Manpower Database'!AP71 -> 15.625 | Q75: ='Manual Manpower Database'!AQ71 -> 15 | ... X75: ='Manual Manpower Database'!AX71 -> 55.555556 | Y75: =SUM(J75:X75) -> 1454.9306
B76: 01 | C76: General Requirement | D76: 01700 | E76: Execution Requirements | F76: Helper Surveyor | G76: 030 | H76: =D76&G76 -> 01700030 | J76: ='Manual Manpower Database'!AJ72 -> 884.375 | K76: ='Manual Manpower Database'!AK72 -> 0 | L76: ='Manual Manpower Database'!AL72 -> 0 | M76: ='Manual Manpower Database'!AM72 -> 150 | N76: ='Manual Manpower Database'!AN72 -> 36.848958 | O76: ='Manual Manpower Database'!AO72 -> 0 | P76: ='Manual Manpower Database'!AP72 -> 18.424479 | Q76: ='Manual Manpower Database'!AQ72 -> 17.6875 | ... X76: ='Manual Manpower Database'!AX72 -> 55.555556 | Y76: =SUM(J76:X76) -> 1600.3915
B77: 01 | C77: General Requirement | D77: 01700 | E77: Execution Requirements | F77: Helper Technical | G77: 033 | H77: =D77&G77 -> 01700033 | J77: ='Manual Manpower Database'!AJ73 -> 3000 | K77: ='Manual Manpower Database'!AK73 -> 300 | L77: ='Manual Manpower Database'!AL73 -> 0 | M77: ='Manual Manpower Database'!AM73 -> 0 | N77: ='Manual Manpower Database'!AN73 -> 125 | O77: ='Manual Manpower Database'!AO73 -> 0 | P77: ='Manual Manpower Database'!AP73 -> 62.5 | Q77: ='Manual Manpower Database'!AQ73 -> 60 | ... X77: ='Manual Manpower Database'!AX73 -> 55.555556 | Y77: =SUM(J77:X77) -> 4040.5556
B78: 01 | C78: General Requirement | D78: 01700 | E78: Execution Requirements | F78: Helper Welder | G78: 036 | H78: =D78&G78 -> 01700036 | J78: ='Manual Manpower Database'!AJ74 -> 733.33333 | K78: ='Manual Manpower Database'!AK74 -> 0 | L78: ='Manual Manpower Database'!AL74 -> 0 | M78: ='Manual Manpower Database'!AM74 -> 150 | N78: ='Manual Manpower Database'!AN74 -> 30.555556 | O78: ='Manual Manpower Database'!AO74 -> 0 | P78: ='Manual Manpower Database'!AP74 -> 15.277778 | Q78: ='Manual Manpower Database'!AQ74 -> 14.666667 | ... X78: ='Manual Manpower Database'!AX74 -> 55.555556 | Y78: =SUM(J78:X78) -> 1436.8889
B79: 02 | C79: Site Construction | D79: 02100 | E79: Site Remediation | F79: Insect Spray Specialist | G79: 015 | H79: =D79&G79 -> 02100015 | J79: ='Manual Manpower Database'!AJ75 -> 2511.25 | K79: ='Manual Manpower Database'!AK75 -> 0 | L79: ='Manual Manpower Database'!AL75 -> 627.8125 | M79: ='Manual Manpower Database'!AM75 -> 250 | N79: ='Manual Manpower Database'!AN75 -> 104.63542 | O79: ='Manual Manpower Database'!AO75 -> 0 | P79: ='Manual Manpower Database'!AP75 -> 52.317708 | Q79: ='Manual Manpower Database'!AQ75 -> 62.78125 | ... X79: ='Manual Manpower Database'!AX75 -> 55.555556 | Y79: =SUM(J79:X79) -> 4101.8524
B80: 15 | C80: Mechanical | D80: 15900 | E80: HVAC instrumentation & Controls | F80: Insulator | G80: 035 | H80: =D80&G80 -> 15900035 | J80: ='Manual Manpower Database'!AJ76 -> 1056.0606 | K80: ='Manual Manpower Database'!AK76 -> 0 | L80: ='Manual Manpower Database'!AL76 -> 0 | M80: ='Manual Manpower Database'!AM76 -> 150 | N80: ='Manual Manpower Database'!AN76 -> 44.002525 | O80: ='Manual Manpower Database'!AO76 -> 0 | P80: ='Manual Manpower Database'!AP76 -> 22.001263 | Q80: ='Manual Manpower Database'!AQ76 -> 21.121212 | ... X80: ='Manual Manpower Database'!AX76 -> 55.555556 | Y80: =SUM(J80:X80) -> 1786.2412
B81: 01 | C81: General Requirement | D81: 01700 | E81: Execution Requirements | F81: Labour | G81: 039 | H81: =D81&G81 -> 01700039 | J81: ='Manual Manpower Database'!AJ77 -> 641.30063 | K81: ='Manual Manpower Database'!AK77 -> 300 | L81: ='Manual Manpower Database'!AL77 -> 0 | M81: ='Manual Manpower Database'!AM77 -> 250 | N81: ='Manual Manpower Database'!AN77 -> 26.72086 | O81: ='Manual Manpower Database'!AO77 -> 0 | P81: ='Manual Manpower Database'!AP77 -> 13.36043 | Q81: ='Manual Manpower Database'!AQ77 -> 12.826013 | ... X81: ='Manual Manpower Database'!AX77 -> 55.555556 | Y81: =SUM(J81:X81) -> 1737.2635
B82: 01 | C82: General Requirement | D82: 01700 | E82: Execution Requirements | F82: Labour Cleaning | G82: 042 | H82: =D82&G82 -> 01700042 | J82: ='Manual Manpower Database'!AJ78 -> 338.2005 | K82: ='Manual Manpower Database'!AK78 -> 300 | L82: ='Manual Manpower Database'!AL78 -> 0 | M82: ='Manual Manpower Database'!AM78 -> 250 | N82: ='Manual Manpower Database'!AN78 -> 14.091688 | O82: ='Manual Manpower Database'!AO78 -> 0 | P82: ='Manual Manpower Database'!AP78 -> 7.0458439 | Q82: ='Manual Manpower Database'!AQ78 -> 6.7640101 | ... X82: ='Manual Manpower Database'!AX78 -> 55.555556 | Y82: =SUM(J82:X82) -> 1409.1576
B83: 01 | C83: General Requirement | D83: 01700 | E83: Execution Requirements | F83: Labour Workshop | G83: 045 | H83: =D83&G83 -> 01700045 | J83: ='Manual Manpower Database'!AJ79 -> 490 | K83: ='Manual Manpower Database'!AK79 -> 0 | L83: ='Manual Manpower Database'!AL79 -> 0 | M83: ='Manual Manpower Database'!AM79 -> 150 | N83: ='Manual Manpower Database'!AN79 -> 20.416667 | O83: ='Manual Manpower Database'!AO79 -> 0 | P83: ='Manual Manpower Database'!AP79 -> 10.208333 | Q83: ='Manual Manpower Database'!AQ79 -> 9.8 | ... X83: ='Manual Manpower Database'!AX79 -> 55.555556 | Y83: =SUM(J83:X83) -> 1173.4806
B84: 03 | C84: Concrete | D84: 03300 | E84: Cast in Place Concrete | F84: Lead Man Carpenter | G84: 040 | H84: =D84&G84 -> 03300040 | J84: ='Manual Manpower Database'!AJ80 -> 1251.3889 | K84: ='Manual Manpower Database'!AK80 -> 0 | L84: ='Manual Manpower Database'!AL80 -> 0 | M84: ='Manual Manpower Database'!AM80 -> 150 | N84: ='Manual Manpower Database'!AN80 -> 52.141204 | O84: ='Manual Manpower Database'!AO80 -> 0 | P84: ='Manual Manpower Database'!AP80 -> 26.070602 | Q84: ='Manual Manpower Database'!AQ80 -> 25.027778 | ... X84: ='Manual Manpower Database'!AX80 -> 55.555556 | Y84: =SUM(J84:X84) -> 1997.684
B85: 04 | C85: Block Work | D85: 04200 | E85: Masonary Units | F85: Lead Man Mason | G85: 015 | H85: =D85&G85 -> 04200015 | J85: ='Manual Manpower Database'!AJ81 -> 1267.0909 | K85: ='Manual Manpower Database'!AK81 -> 0 | L85: ='Manual Manpower Database'!AL81 -> 0 | M85: ='Manual Manpower Database'!AM81 -> 250 | N85: ='Manual Manpower Database'!AN81 -> 52.795455 | O85: ='Manual Manpower Database'!AO81 -> 0 | P85: ='Manual Manpower Database'!AP81 -> 26.397727 | Q85: ='Manual Manpower Database'!AQ81 -> 25.341818 | ... X85: ='Manual Manpower Database'!AX81 -> 55.555556 | Y85: =SUM(J85:X85) -> 2114.6815
B86: 03 | C86: Concrete | D86: 03300 | E86: Cast in Place Concrete | F86: Lead Man Steel Fixer | G86: 045 | H86: =D86&G86 -> 03300045 | J86: ='Manual Manpower Database'!AJ82 -> 1208.9552 | K86: ='Manual Manpower Database'!AK82 -> 0 | L86: ='Manual Manpower Database'!AL82 -> 0 | M86: ='Manual Manpower Database'!AM82 -> 150 | N86: ='Manual Manpower Database'!AN82 -> 50.373134 | O86: ='Manual Manpower Database'!AO82 -> 0 | P86: ='Manual Manpower Database'!AP82 -> 25.186567 | Q86: ='Manual Manpower Database'!AQ82 -> 24.179104 | ... X86: ='Manual Manpower Database'!AX82 -> 55.555556 | Y86: =SUM(J86:X86) -> 1951.7496
... B91: 01 | C91: General Requirement | D91: 01700 | E91: Execution Requirements | F91: Sculptor | G91: 087 | H91: =D91&G91 -> 01700087 | J91: ='Manual Manpower Database'!AJ87 -> 1239.4444 | K91: ='Manual Manpower Database'!AK87 -> 0 | L91: ='Manual Manpower Database'!AL87 -> 0 | M91: ='Manual Manpower Database'!AM87 -> 150 | N91: ='Manual Manpower Database'!AN87 -> 51.643519 | O91: ='Manual Manpower Database'!AO87 -> 0 | P91: ='Manual Manpower Database'!AP87 -> 25.821759 | Q91: ='Manual Manpower Database'!AQ87 -> 24.788889 | ... X91: ='Manual Manpower Database'!AX87 -> 55.555556 | Y91: =SUM(J91:X91) -> 1984.7542
B92: 09 | C92: Finishing | D92: 09900 | E92: Paints & Coatings | F92: Leadman Painter | G92: 015 | H92: =D92&G92 -> 09900015 | J92: ='Manual Manpower Database'!AJ87 -> 1239.4444 | K92: ='Manual Manpower Database'!AK87 -> 0 | L92: ='Manual Manpower Database'!AL87 -> 0 | M92: ='Manual Manpower Database'!AM87 -> 150 | N92: ='Manual Manpower Database'!AN87 -> 51.643519 | O92: ='Manual Manpower Database'!AO87 -> 0 | P92: ='Manual Manpower Database'!AP87 -> 25.821759 | Q92: ='Manual Manpower Database'!AQ87 -> 24.788889 | ... X92: ='Manual Manpower Database'!AX87 -> 55.555556 | Y92: =SUM(J92:X92) -> 1984.7542
B93: 15 | C93: Mechanical | D93: 15100 | E93: Building Services Piping | F93: Leadman Plumber | G93: 010 | H93: =D93&G93 -> 15100010 | J93: ='Manual Manpower Database'!AJ88 -> 1425.5814 | K93: ='Manual Manpower Database'!AK88 -> 0 | L93: ='Manual Manpower Database'!AL88 -> 0 | M93: ='Manual Manpower Database'!AM88 -> 200 | N93: ='Manual Manpower Database'!AN88 -> 59.399225 | O93: ='Manual Manpower Database'!AO88 -> 0 | P93: ='Manual Manpower Database'!AP88 -> 29.699612 | Q93: ='Manual Manpower Database'!AQ88 -> 28.511628 | ... X93: ='Manual Manpower Database'!AX88 -> 55.555556 | Y93: =SUM(J93:X93) -> 2236.2474
B94: 01 | C94: General Requirement | D94: 01700 | E94: Execution Requirements | F94: Leadman Welder | G94: 054 | H94: =D94&G94 -> 01700054 | J94: ='Manual Manpower Database'!AJ89 -> 1450 | K94: ='Manual Manpower Database'!AK89 -> 0 | L94: ='Manual Manpower Database'!AL89 -> 0 | M94: ='Manual Manpower Database'!AM89 -> 150 | N94: ='Manual Manpower Database'!AN89 -> 60.416667 | O94: ='Manual Manpower Database'!AO89 -> 0 | P94: ='Manual Manpower Database'!AP89 -> 30.208333 | Q94: ='Manual Manpower Database'!AQ89 -> 29 | ... X94: ='Manual Manpower Database'!AX89 -> 55.555556 | Y94: =SUM(J94:X94) -> 2212.6806
B95: 01 | C95: General Requirement | D95: 01700 | E95: Execution Requirements | F95: Maintenance Superintendent | G95: 057 | H95: =D95&G95 -> 01700057 | J95: ='Manual Manpower Database'!AJ90 -> 3200 | K95: ='Manual Manpower Database'!AK90 -> 300 | L95: ='Manual Manpower Database'!AL90 -> 0 | M95: ='Manual Manpower Database'!AM90 -> 0 | N95: ='Manual Manpower Database'!AN90 -> 133.33333 | O95: ='Manual Manpower Database'!AO90 -> 0 | P95: ='Manual Manpower Database'!AP90 -> 66.666667 | Q95: ='Manual Manpower Database'!AQ90 -> 64 | ... X95: ='Manual Manpower Database'!AX90 -> 55.555556 | Y95: =SUM(J95:X95) -> 4257.0556
B96: 09 | C96: Finishing | D96: 09600 | E96: Flooring | F96: Marbler | G96: 015 | H96: =D96&G96 -> 09600015 | J96: 1267.0909 | K96: 0 | L96: 0 | M96: 250 | N96: 52.795455 | O96: 0 | P96: 26.397727 | Q96: 25.341818 | R96: 125 | S96: 41.666667 | T96: 54.166667 | U96: 208.33333 | V96: 0 | W96: 8.3333333 | X96: 55.555556 | Y96: 2114.6815
B97: 04 | C97: Block Work | D97: 04200 | E97: Masonary Units | F97: Mason | G97: 020 | H97: =D97&G97 -> 04200020 | J97: ='Manual Manpower Database'!AJ91 -> 927.59574 | K97: ='Manual Manpower Database'!AK91 -> 0 | L97: ='Manual Manpower Database'!AL91 -> 0 | M97: ='Manual Manpower Database'!AM91 -> 250 | N97: ='Manual Manpower Database'!AN91 -> 38.649823 | O97: ='Manual Manpower Database'!AO91 -> 0 | P97: ='Manual Manpower Database'!AP91 -> 19.324911 | Q97: ='Manual Manpower Database'!AQ91 -> 18.551915 | ... X97: ='Manual Manpower Database'!AX91 -> 55.555556 | Y97: =SUM(J97:X97) -> 1747.1779
B98: 01 | C98: General Requirement | D98: 01500 | E98: Temporary facilities & Controls | F98: Mechanic | G98: 033 | H98: =D98&G98 -> 01500033 | J98: ='Manual Manpower Database'!AJ92 -> 2243.1818 | K98: ='Manual Manpower Database'!AK92 -> 300 | L98: ='Manual Manpower Database'!AL92 -> 0 | M98: ='Manual Manpower Database'!AM92 -> 150 | N98: ='Manual Manpower Database'!AN92 -> 93.465909 | O98: ='Manual Manpower Database'!AO92 -> 0 | P98: ='Manual Manpower Database'!AP92 -> 46.732955 | Q98: ='Manual Manpower Database'!AQ92 -> 44.863636 | ... X98: ='Manual Manpower Database'!AX92 -> 55.555556 | Y98: =SUM(J98:X98) -> 3371.2999
B99: 01 | C99: General Requirement | D99: 01500 | E99: Temporary facilities & Controls | F99: Mechanic Auto | G99: 036 | H99: =D99&G99 -> 01500036 | J99: ='Manual Manpower Database'!AJ93 -> 1542.8571 | K99: ='Manual Manpower Database'!AK93 -> 300 | L99: ='Manual Manpower Database'!AL93 -> 0 | M99: ='Manual Manpower Database'!AM93 -> 150 | N99: ='Manual Manpower Database'!AN93 -> 64.285714 | O99: ='Manual Manpower Database'!AO93 -> 0 | P99: ='Manual Manpower Database'!AP93 -> 32.142857 | Q99: ='Manual Manpower Database'!AQ93 -> 30.857143 | ... X99: ='Manual Manpower Database'!AX93 -> 55.555556 | Y99: =SUM(J99:X99) -> 2613.1984
B100: 01 | C100: General Requirement | D100: 01500 | E100: Temporary facilities & Controls | F100: Mechanic Crusher | G100: 039 | H100: =D100&G100 -> 01500039 | J100: ='Manual Manpower Database'!AJ94 -> 1400 | K100: ='Manual Manpower Database'!AK94 -> 0 | L100: ='Manual Manpower Database'!AL94 -> 0 | M100: ='Manual Manpower Database'!AM94 -> 200 | N100: ='Manual Manpower Database'!AN94 -> 58.333333 | O100: ='Manual Manpower Database'!AO94 -> 0 | P100: ='Manual Manpower Database'!AP94 -> 29.166667 | Q100: ='Manual Manpower Database'!AQ94 -> 28 | ... X100: ='Manual Manpower Database'!AX94 -> 55.555556 | Y100: =SUM(J100:X100) -> 2208.5556
B101: 01 | C101: General Requirement | D101: 01500 | E101: Temporary facilities & Controls | F101: Mechanic Diesel | G101: 042 | H101: =D101&G101 -> 01500042 | J101: ='Manual Manpower Database'!AJ95 -> 1318.5064 | K101: ='Manual Manpower Database'!AK95 -> 300 | L101: ='Manual Manpower Database'!AL95 -> 0 | M101: ='Manual Manpower Database'!AM95 -> 250 | N101: ='Manual Manpower Database'!AN95 -> 54.937767 | O101: ='Manual Manpower Database'!AO95 -> 0 | P101: ='Manual Manpower Database'!AP95 -> 27.468884 | Q101: ='Manual Manpower Database'!AQ95 -> 26.370128 | ... X101: ='Manual Manpower Database'!AX95 -> 55.555556 | Y101: =SUM(J101:X101) -> 2470.3387
B102: 01 | C102: General Requirement | D102: 01500 | E102: Temporary facilities & Controls | F102: Mechanic Gasoline | G102: 045 | H102: =D102&G102 -> 01500045 | J102: ='Manual Manpower Database'!AJ96 -> 1684.2857 | K102: ='Manual Manpower Database'!AK96 -> 300 | L102: ='Manual Manpower Database'!AL96 -> 0 | M102: ='Manual Manpower Database'!AM96 -> 150 | N102: ='Manual Manpower Database'!AN96 -> 70.178571 | O102: ='Manual Manpower Database'!AO96 -> 0 | P102: ='Manual Manpower Database'!AP96 -> 35.089286 | Q102: ='Manual Manpower Database'!AQ96 -> 33.685714 | ... X102: ='Manual Manpower Database'!AX96 -> 55.555556 | Y102: =SUM(J102:X102) -> 2766.2948
B103: 01 | C103: General Requirement | D103: 01500 | E103: Temporary facilities & Controls | F103: Mechanic Heavy Equipment | G103: 048 | H103: =D103&G103 -> 01500048 | J103: ='Manual Manpower Database'!AJ97 -> 1500.9429 | K103: ='Manual Manpower Database'!AK97 -> 0 | L103: ='Manual Manpower Database'!AL97 -> 0 | M103: ='Manual Manpower Database'!AM97 -> 250 | N103: ='Manual Manpower Database'!AN97 -> 62.539286 | O103: ='Manual Manpower Database'!AO97 -> 0 | P103: ='Manual Manpower Database'!AP97 -> 31.269643 | Q103: ='Manual Manpower Database'!AQ97 -> 30.018857 | ... X103: ='Manual Manpower Database'!AX97 -> 55.555556 | Y103: =SUM(J103:X103) -> 2367.8262
B104: 01 | C104: General Requirement | D104: 01500 | E104: Temporary facilities & Controls | F104: Mechanic Hydraulic | G104: 051 | H104: =D104&G104 -> 01500051 | J104: ='Manual Manpower Database'!AJ98 -> 1523.2143 | K104: ='Manual Manpower Database'!AK98 -> 0 | L104: ='Manual Manpower Database'!AL98 -> 0 | M104: ='Manual Manpower Database'!AM98 -> 200 | N104: ='Manual Manpower Database'!AN98 -> 63.467262 | O104: ='Manual Manpower Database'!AO98 -> 0 | P104: ='Manual Manpower Database'!AP98 -> 31.733631 | Q104: ='Manual Manpower Database'!AQ98 -> 30.464286 | ... X104: ='Manual Manpower Database'!AX98 -> 55.555556 | Y104: =SUM(J104:X104) -> 2341.935
B105: 01 | C105: General Requirement | D105: 01500 | E105: Temporary facilities & Controls | F105: Mechanic Pump | G105: 054 | H105: =D105&G105 -> 01500054 | J105: ='Manual Manpower Database'!AJ99 -> 1825 | K105: ='Manual Manpower Database'!AK99 -> 0 | L105: ='Manual Manpower Database'!AL99 -> 0 | M105: ='Manual Manpower Database'!AM99 -> 150 | N105: ='Manual Manpower Database'!AN99 -> 76.041667 | O105: ='Manual Manpower Database'!AO99 -> 0 | P105: ='Manual Manpower Database'!AP99 -> 38.020833 | Q105: ='Manual Manpower Database'!AQ99 -> 36.5 | ... X105: ='Manual Manpower Database'!AX99 -> 55.555556 | Y105: =SUM(J105:X105) -> 2618.6181
